Workbook
Name L_MODE: Lists!$A$2:$A$5
Name L_DATASET: Lists!$B$2:$B$4
Name L_SCEN: Lists!$C$2:$C$5
Name L_UNITS: Lists!$D$2:$D$4
Name L_FINISH: Lists!$E$2:$E$4
Name L_YN: Lists!$F$2:$F$3
Name L_USE: Lists!$G$2:$G$6
Name L_METHOD: Lists!$H$2:$H$3
Name L_BTYPE: Lists!$I$2:$I$6
Name L_LOC: Lists!$J$2:$J$3
Name L_LAND: Lists!$K$2:$K$4
Name L_SCURVE: Lists!$L$2:$L$4
Name L_DRAW: Lists!$M$2:$M$3
Name L_RATETYPE: Lists!$N$2:$N$3
Name L_GRACE: Lists!$O$2:$O$3
Name L_REPAY: Lists!$P$2:$P$4
Name L_FREQ: Lists!$Q$2:$Q$4
Name L_REV: Lists!$R$2:$R$3
Name L_OPEXM: Lists!$S$2:$S$3
Name L_EXIT: Lists!$T$2:$T$3
Name PROJ_NAME: '10_Inputs'!$H$10
Name LOCATION: '10_Inputs'!$H$11
Name LOC_TYPE: '10_Inputs'!$H$12
Name PLOT_AREA: '10_Inputs'!$H$13
Name FAR: '10_Inputs'!$H$14
Name START_DATE: '10_Inputs'!$H$15
Name CONSTR_M: '10_Inputs'!$H$16
Name FX_USD: '10_Inputs'!$H$17
Name BLDG_TYPE: '10_Inputs'!$H$19
Name BASEMENT_YN: '10_Inputs'!$H$20
Name FINISH: '10_Inputs'!$H$21
Name HH_INCOME: '10_Inputs'!$H$22
Name AFFORD_MAX: '10_Inputs'!$H$23
Name EST_LOW: '10_Inputs'!$H$24
Name EST_HIGH: '10_Inputs'!$H$25
Name SAVINGS: '10_Inputs'!$H$26
Name FAMILY: '10_Inputs'!$H$27
Name HOME_LOAN: '10_Inputs'!$H$28
Name RENT_HOME_F: '10_Inputs'!$H$29
Name RENT_HOME_AREA: '10_Inputs'!$H$30
Name RENT_HOME_MONTHLY: '10_Inputs'!$H$31
Name FL_A1: '10_Inputs'!$H$33
Name FL_A2: '10_Inputs'!$H$34
Name FL_A3: '10_Inputs'!$H$35
Name FL_A4: '10_Inputs'!$H$36
Name FL_A5: '10_Inputs'!$H$37
Name FL_A6: '10_Inputs'!$H$38
Name FL_A7: '10_Inputs'!$H$39
Name FL_A8: '10_Inputs'!$H$40
Name FL_A9: '10_Inputs'!$H$41
Name FL_A10: '10_Inputs'!$H$42
Name FL_A11: '10_Inputs'!$H$43
Name FL_A12: '10_Inputs'!$H$44
Name FL_A13: '10_Inputs'!$H$45
Name FL_A14: '10_Inputs'!$H$46
Name FL_A15: '10_Inputs'!$H$47
Name FL_A16: '10_Inputs'!$H$48
Name FL_U1: '10_Inputs'!$H$50
Name FL_U2: '10_Inputs'!$H$51
Name FL_U3: '10_Inputs'!$H$52

Sheet 00_Start
B1: Rapha Development Profitability Model | M1: =HYPERLINK("#'00_Start'!A1","◂ Start") -> ◂ Start
B2: የራፋ የግንባታ ፕሮጀክት ትርፋማነት ሞዴል
B3: =PROJ_NAME&" | Scenario: "&SCEN_NAME&" | Mode: "&MODE_NAME -> SAMPLE B — B+G+8 mixed-use building, Addis Ababa | Scenario: Base | Mode: 3 Mixed
C5: Does my project make money? · ፕሮጀክቴ ያተርፋል?
C6: One workbook, two uses: a quick cost estimate for your own house (Mode 0) or full profitability, IFRS statements and a loan schedule for a commercial project (Modes 1–3).
C8: SET UP · ማዘጋጀት | I8: STATUS · ሁኔታ
G9: code | M9: helper labels
C10: 1. What are you building? | D10: 3 – Mixed (sell part, rent part) · ቅይጥ (ከፊል ሽያጭ፣ ከፊል ኪራይ) | G10: =IFERROR(MATCH(D10,L_MODE,0)-1,0) -> 3 | I10: Checks passed | J10: =CHK_PASS&" / "&CHK_TOTAL -> 23 / 23 | M10: =CHOOSE(PROJECT_MODE+1,"0 Personal residence","1 Build-to-Sell","2 Build-to-Rent","3 Mixed") -> 3 Mixed
C11: ምን እየገነቡ ነው? | I11: Model status | J11: =CHK_STATUS -> ALL CHECKS PASS
C12: 2. Which data? | D12: 3 – SAMPLE B: B+G+8 mixed-use · ምሳሌ ለ | G12: =IFERROR(MATCH(D12,L_DATASET,0),1) -> 3
C13: የትኛውን መረጃ? | I13: Verdict | J13: =VERDICT -> VIABLE
C14: 3. Scenario | D14: 1 – Base · መሠረታዊ | G14: =IFERROR(MATCH(D14,L_SCEN,0),1) -> 1 | I14: ውሳኔ | J14: =VERDICT_AM -> አዋጭ | M14: =CHOOSE(SCEN,"Base","Upside","Downside","Lender") -> Base
C15: ሁኔታ
C16: 4. Show statements in | D16: ETB '000 | G16: =IFERROR(MATCH(D16,L_UNITS,0),2) -> 2 | I16: Total development cost (ETB) | J16: =TDC -> 5.5066043e+08 | M16: =CHOOSE(UNIT_SEL,"ETB","ETB '000","ETB m") -> ETB '000
C17: የመግለጫ መለኪያ | I17: =IF(PROJECT_MODE=0,"Monthly loan instalment (ETB)","Equity IRR") -> Equity IRR | J17: =IF(PROJECT_MODE=0,LN_INSTAL_M,EIRR) -> 0.27572623
C18: =IF(AND(DATA_SET=2,PROJECT_MODE<>0),"Tip: Sample A is a personal house – choose mode 0.",IF(AND(DATA_SET=3,PROJECT_MODE<>3),"Tip: Sample B is a mixed-use building – choose mode 3.",IF(PROJECT_MODE=0,"Home view: open the Home Estimate page.","Commercial view: open the Dashboard."))) -> Commercial view: open the Dashboard.
C21: NAVIGATE · መሄጃ | F21: ALL SHEETS
C22: =HYPERLINK(IF(PROJECT_MODE=0,"#'02_Home'!A1","#'01_Dashboard'!A1"),IF(PROJECT_MODE=0,"▸ Home Estimate (one page) · የቤት ወጪ ግምት","▸ Dashboard · ዳሽቦርድ")) -> ▸ Dashboard · ዳሽቦርድ | F22: =HYPERLINK("#'01_Dashboard'!A1","01 Dashboard") -> 01 Dashboard | G22: =HYPERLINK("#'28_Tax'!A1","28 Tax") -> 28 Tax
C23: =HYPERLINK(IF(PROJECT_MODE=0,"#'10_Inputs'!A1","#'10_Inputs'!A1"),IF(PROJECT_MODE=0,"▸ Inputs – block 2 home card · ግብዓቶች","▸ Inputs · ግብዓቶች")) -> ▸ Inputs · ግብዓቶች | F23: =HYPERLINK("#'02_Home'!A1","02 Home") -> 02 Home | G23: =HYPERLINK("#'29_VAT'!A1","29 VAT") -> 29 VAT
C24: =HYPERLINK(IF(PROJECT_MODE=0,"#'22_Capex'!A1","#'11_Scenarios'!A1"),IF(PROJECT_MODE=0,"▸ Cost breakdown · የወጪ ዝርዝር","▸ Scenarios · ሁኔታዎች")) -> ▸ Scenarios · ሁኔታዎች | F24: =HYPERLINK("#'10_Inputs'!A1","10 Inputs") -> 10 Inputs | G24: =HYPERLINK("#'30_WorkingCap'!A1","30 WorkingCap") -> 30 WorkingCap
C25: =HYPERLINK(IF(PROJECT_MODE=0,"#'23_Construction'!A1","#'40_PL'!A1"),IF(PROJECT_MODE=0,"▸ Monthly cash needed · ወርሃዊ ወጪ","▸ Profit & loss · ትርፍና ኪሳራ")) -> ▸ Profit & loss · ትርፍና ኪሳራ | F25: =HYPERLINK("#'11_Scenarios'!A1","11 Scenarios") -> 11 Scenarios | G25: =HYPERLINK("#'40_PL'!A1","40 PL") -> 40 PL
C26: =HYPERLINK(IF(PROJECT_MODE=0,"#'27_Loan'!A1","#'41_BS'!A1"),IF(PROJECT_MODE=0,"▸ Home-loan schedule · የብድር ሰንጠረዥ","▸ Balance sheet · ሀብትና ዕዳ")) -> ▸ Balance sheet · ሀብትና ዕዳ | F26: =HYPERLINK("#'12_TaxLaw'!A1","12 TaxLaw") -> 12 TaxLaw | G26: =HYPERLINK("#'41_BS'!A1","41 BS") -> 41 BS
C27: =HYPERLINK(IF(PROJECT_MODE=0,"#'11_Scenarios'!A1","#'42_CF'!A1"),IF(PROJECT_MODE=0,"▸ Scenarios · ሁኔታዎች","▸ Cash flow · የገንዘብ ፍሰት")) -> ▸ Cash flow · የገንዘብ ፍሰት | F27: =HYPERLINK("#'20_Timeline'!A1","20 Timeline") -> 20 Timeline | G27: =HYPERLINK("#'42_CF'!A1","42 CF") -> 42 CF
C28: =HYPERLINK(IF(PROJECT_MODE=0,"#'60_Checks'!A1","#'27_Loan'!A1"),IF(PROJECT_MODE=0,"▸ Checks · ማረጋገጫዎች","▸ Loan schedule · የብድር ሰንጠረዥ")) -> ▸ Loan schedule · የብድር ሰንጠረዥ | F28: =HYPERLINK("#'21_Area'!A1","21 Area") -> 21 Area | G28: =HYPERLINK("#'43_Ratios'!A1","43 Ratios") -> 43 Ratios
C29: =HYPERLINK(IF(PROJECT_MODE=0,"#'61_Glossary'!A1","#'50_Returns'!A1"),IF(PROJECT_MODE=0,"▸ Glossary · መዝገበ ቃላት","▸ Returns · ተመላሽ")) -> ▸ Returns · ተመላሽ | F29: =HYPERLINK("#'22_Capex'!A1","22 Capex") -> 22 Capex | G29: =HYPERLINK("#'50_Returns'!A1","50 Returns") -> 50 Returns
C30: =HYPERLINK(IF(PROJECT_MODE=0,"#'00_Start'!A1","#'52_Sensitivity'!A1"),IF(PROJECT_MODE=0,"","▸ Sensitivity & break-even · የስጋት ትንተና")) -> ▸ Sensitivity & break-even · የስጋት ትንተና | F30: =HYPERLINK("#'23_Construction'!A1","23 Construction") -> 23 Construction | G30: =HYPERLINK("#'51_Payback'!A1","51 Payback") -> 51 Payback
C31: =HYPERLINK(IF(PROJECT_MODE=0,"#'00_Start'!A1","#'60_Checks'!A1"),IF(PROJECT_MODE=0,"","▸ Checks · ማረጋገጫዎች")) -> ▸ Checks · ማረጋገጫዎች | F31: =HYPERLINK("#'24_Revenue'!A1","24 Revenue") -> 24 Revenue | G31: =HYPERLINK("#'52_Sensitivity'!A1","52 Sensitivity") -> 52 Sensitivity
F32: =HYPERLINK("#'25_Opex'!A1","25 Opex") -> 25 Opex | G32: =HYPERLINK("#'60_Checks'!A1","60 Checks") -> 60 Checks
F33: =HYPERLINK("#'26_Assets'!A1","26 Assets") -> 26 Assets | G33: =HYPERLINK("#'61_Glossary'!A1","61 Glossary") -> 61 Glossary
F34: =HYPERLINK("#'27_Loan'!A1","27 Loan") -> 27 Loan
C37: HOW TO USE · አጠቃቀም
B38: 1 | C38: Answer question 1. Personal house → 0. Selling, renting or both → 1, 2 or 3.
C39: ጥያቄ 1ን ይመልሱ፡ የግል ቤት → 0፤ ለሽያጭ፣ ለኪራይ ወይም ለሁለቱም → 1፣ 2 ወይም 3።
B40: 2 | C40: Choose 'My project' in question 2 and type your values in column E of sheet 10 Inputs (blue cells only).
C41: በጥያቄ 2 'የእኔ ፕሮጀክት'ን ይምረጡና በገጽ 10 ዓምድ E ሰማያዊ ሕዋሶች ላይ ብቻ ይጻፉ።
B42: 3 | C42: Check the status box: all checks must pass. Then read the Home Estimate (Mode 0) or the Dashboard.
C43: የማረጋገጫ ሳጥኑን ይመልከቱ፤ ከዚያ የቤት ግምቱን ወይም ዳሽቦርዱን ያንብቡ።
B44: 4 | C44: Stress-test: switch scenarios (question 3) and use the flex cells on sheet 52.
C45: ሁኔታዎችን ይቀያይሩና በገጽ 52 የማስተካከያ ሕዋሶችን ይጠቀሙ።
C47: COLOUR CODE · የቀለም ኮድ
C48: Input – type here | D48: ግብዓት – እዚህ ይጻፉ
C49: Formula – do not overwrite | D49: ቀመር – አይጻፉበት
C50: Link from another sheet | D50: ከሌላ ገጽ ማገናኛ
C51: Key output / check | D51: ቁልፍ ውጤት / ማረጋገጫ
C53: METHOD NOTES
C54: No circularity: interest during construction (IDC) is built month by month on the opening balance plus draws; the arrangement fee is charged on a facility base that excludes IDC; undistributed-profits tax uses a closed form.
C55: Timeline: construction is modelled monthly (up to 48 months) and rolled up to C1–C4; operations run O1–O10 annually. Returns use dated cash flows (XIRR).
C56: IFRS: IAS 2 units for sale, IAS 40 let space (cost model), IAS 16 owner-occupied, IAS 23 capitalised borrowing cost, IFRS 15 sales, IFRS 16 rent, IAS 12 tax, IAS 36 impairment test, IAS 7 indirect cash flow.
C57: Sensitivity tables are Excel Data Tables. If Excel is set to 'Automatic except data tables', press F9.
C58: Disclaimer: a planning tool only – not investment, tax or legal advice. Confirm tax rates (sheet 12) before use.
C59: ማሳሰቢያ፡ ይህ የዕቅድ መሣሪያ ብቻ ነው፤ የኢንቨስትመንት፣ የግብር ወይም የሕግ ምክር አይደለም።

Sheet 01_Dashboard
B1: Dashboard | S1: =HYPERLINK("#'00_Start'!A1","◂ Start") -> ◂ Start
B2: ዳሽቦርድ – ፕሮጀክቴ ያተርፋል?
B3: =PROJ_NAME&" | Scenario: "&SCEN_NAME&" | Mode: "&MODE_NAME -> SAMPLE B — B+G+8 mixed-use building, Addis Ababa | Scenario: Base | Mode: 3 Mixed
B5: Scenario | C5: =SCEN_NAME -> Base | E5: Checks | F5: =CHK_PASS&" / "&CHK_TOTAL&" pass" -> 23 / 23 pass | H5: Mode | I5: =MODE_NAME -> 3 Mixed | K5: Verdict · ውሳኔ | L5: =VERDICT&" · "&VERDICT_AM -> VIABLE · አዋጭ | Q5: Equity IRR hurdle | R5: =HURDLE -> 0.2
B6: =IF(PROJECT_MODE=0,"Home view – tiles show the cost estimate; open the Home Estimate page for the full picture.","Commercial view – ETB; IRR on dated cash flows (XIRR); verdict = equity IRR vs hurdle, profit on cost and DSCR covenant.") -> Commercial view – ETB; IRR on dated cash flows (XIRR); verdict = equity IRR vs hurdle, profit on cost and DSCR covenant.
B8: =IF(PROJECT_MODE=0,"TOTAL PROJECT COST","TOTAL DEVELOPMENT COST") -> TOTAL DEVELOPMENT COST | E8: =IF(PROJECT_MODE=0,"COST PER m²","GROSS DEVELOPMENT VALUE") -> GROSS DEVELOPMENT VALUE | H8: =IF(PROJECT_MODE=0,"MONTHLY INSTALMENT","PROFIT ON COST") -> PROFIT ON COST | K8: =IF(PROJECT_MODE=0,"FUNDING GAP","EQUITY IRR") -> EQUITY IRR | N8: =IF(PROJECT_MODE=0,"LOAN DRAWN","PEAK DEBT") -> PEAK DEBT | Q8: =IF(PROJECT_MODE=0,"AFFORDABILITY","MIN DSCR") -> MIN DSCR
B10: =TDC -> 5.5066043e+08 | E10: =IF(PROJECT_MODE=0,TEXT(CC_M2,"#,##0"),GDV) -> 8.3681139e+08 | H10: =IF(PROJECT_MODE=0,TEXT(LN_INSTAL_M,"#,##0"),POC) -> 0.51965049 | K10: =IF(PROJECT_MODE=0,TEXT(FUND_GAP,"#,##0"),EIRR) -> 0.27572623 | N10: =IF(PROJECT_MODE=0,DEBT_DRAWN,PEAK_DEBT) -> 1.3314989e+08 | Q10: =IF(PROJECT_MODE=0,TEXT(AFFORD_PCT,"0%"),MIN_DSCR) -> 1.7426163
B12: ="ETB · "&TEXT(TDC_M2G,"#,##0")&" per m² gross" -> ETB · 86,041 per m² gross | E12: =IF(PROJECT_MODE=0,"construction cost per m²","GDV ÷ TDC = "&TEXT(GDV_TDC,"0.00")&"x") -> GDV ÷ TDC = 1.52x | H12: =IF(PROJECT_MODE=0,"home loan","margin on GDV "&TEXT(DEV_MARGIN,"0.0%")) -> margin on GDV 34.2% | K12: =IF(PROJECT_MODE=0,IF(FUND_GAP>0.5,"to be found","fully funded"),"hurdle "&TEXT(HURDLE,"0.0%")&IF(EIRR>=HURDLE," ✓ above"," ✗ below")) -> hurdle 20.0% ✓ above | N12: ="incl. capitalised IDC "&TEXT(IDC_TOT/1000000,"#,##0.0")&" m" -> incl. capitalised IDC 17.5 m | Q12: =IF(PROJECT_MODE=0,AFFORD_TXT,"covenant "&TEXT(DSCR_COV,"0.00")&"x"&IF(DSCR_OK=1," ✓ met"," ✗ breached")) -> covenant 1.30x ✓ met
B14: (a) Project cash flow and cumulative · ETB m | H14: (b) Loan balance at period end · ETB m | N14: (b) DSCR by year vs covenant · x (capped at 10)
B28: (c) Revenue mix · ETB m | H28: (d) Development cost breakdown · ETB m | N28: Tornado – Equity IRR swing (±20%, delay +6 mo)
B42: SOURCES & USES – construction period (ETB) | K42: ALERTS · ማስጠንቀቂያዎች
B43: Uses | E43: Sources | K43: =IF(CHK_FAIL>0,"✗ "&CHK_FAIL&" model check(s) failing – see sheet 60","✓ All model checks pass") -> ✓ All model checks pass
B44: TDC | C44: =TDC -> 5.5066043e+08 | E44: Equity committed | F44: =EQ_DRAWN -> 1.7687849e+08 | K44: =IF(PROJECT_MODE=0,"–",IF(N_BREACH>0,"✗ DSCR below covenant in "&N_BREACH&" year(s)","✓ DSCR covenant met")) -> ✓ DSCR covenant met
B45: Capex VAT (refundable) | C45: =SUM('23_Construction'!$E$36:$AZ$36) -> 39251694 | E45: Top-up / gap | F45: =FUND_GAP -> 0 | K45: =IF(FUND_GAP>0.5,"✗ Funding gap of "&TEXT(FUND_GAP,"#,##0")&" ETB","✓ Funding fully covered") -> ✓ Funding fully covered
B46: Lease paid in build | C46: =SUM('23_Construction'!$E$37:$AZ$38) -> 27585000 | E46: Bank debt drawn | F46: =DEBT_DRAWN -> 1.1561421e+08 | K46: =IF(PROJECT_MODE=0,"–",IF(N_LOWCASH>0,"! Cash below minimum in "&N_LOWCASH&" year(s)","✓ Cash above minimum")) -> ✓ Cash above minimum
E47: Presale cash used | F47: =PS_USED -> 1.5650262e+08 | K47: =IF(PROJECT_MODE=0,"–",IF(N_IMPAIR>0,"! IAS 36 impairment indicator in "&N_IMPAIR&" year(s)","✓ No impairment indicator")) -> ✓ No impairment indicator
E48: IDC capitalised | F48: =IDC_TOT -> 17535682 | K48: =IF(AND(FAR>0,FAR_ACT>FAR),"! FAR "&TEXT(FAR_ACT,"0.00")&" exceeds permitted "&TEXT(FAR,"0.00"),"✓ FAR within limit") -> ✓ FAR within limit
E49: Land non-cash | F49: =LAND_TOT-LANDCASH_TOT -> 135000000 | K49: =IF(PROJECT_MODE=0,"–",IF(EIRR<HURDLE,"! Equity IRR below hurdle","✓ Equity IRR above hurdle")) -> ✓ Equity IRR above hurdle
E50: Retention held | F50: =RET_TOT -> 15966117 | K50: ="! Tax rates must be verified (sheet 12) · የግብር መጣኔዎችን ያረጋግጡ" -> ! Tax rates must be verified (sheet 12) · የግብር መጣኔዎችን ያረጋግጡ
B51: Total uses | C51: =SUM(C44:C50) -> 6.1749713e+08 | E51: Total sources | F51: =SUM(F44:F50) -> 6.1749713e+08
E52: Check (= 0) | F52: =ROUND(F51-C51,0) -> 0
B62: Chart data (linked – do not edit)
B63: Period | C63: ='20_Timeline'!E12 -> C1 | D63: ='20_Timeline'!F12 -> C2 | E63: ='20_Timeline'!G12 -> C3 | F63: ='20_Timeline'!H12 -> C4 | G63: ='20_Timeline'!I12 -> O1 | H63: ='20_Timeline'!J12 -> O2 | I63: ='20_Timeline'!K12 -> O3 | J63: ='20_Timeline'!L12 -> O4 | ... P63: ='20_Timeline'!R12 -> O10
B64: Project cash flow | C64: ='50_Returns'!E22/1000000 -> -89.631042 | D64: ='50_Returns'!F22/1000000 -> -144.81592 | E64: ='50_Returns'!G22/1000000 -> 145.97377 | F64: ='50_Returns'!H22/1000000 -> -0.20127724 | G64: ='50_Returns'!I22/1000000 -> 90.458332 | H64: ='50_Returns'!J22/1000000 -> 77.263208 | I64: ='50_Returns'!K22/1000000 -> 8.4457986 | J64: ='50_Returns'!L22/1000000 -> 14.240871 | ... P64: ='50_Returns'!R22/1000000 -> 640.00115
B65: Cumulative | C65: ='51_Payback'!E12/1000000 -> -89.631042 | D65: ='51_Payback'!F12/1000000 -> -234.44696 | E65: ='51_Payback'!G12/1000000 -> -88.47319 | F65: ='51_Payback'!H12/1000000 -> -88.674467 | G65: ='51_Payback'!I12/1000000 -> 1.7838649 | H65: ='51_Payback'!J12/1000000 -> 79.047073 | I65: ='51_Payback'!K12/1000000 -> 87.492872 | J65: ='51_Payback'!L12/1000000 -> 101.73374 | ... P65: ='51_Payback'!R12/1000000 -> 841.70561
B66: Loan balance | C66: ='27_Loan'!E20/1000000 -> 0 | D66: ='27_Loan'!F20/1000000 -> 111.77085 | E66: ='27_Loan'!G20/1000000 -> 133.14989 | F66: ='27_Loan'!H20/1000000 -> 133.14989 | G66: ='27_Loan'!I20/1000000 -> 54.4129 | H66: ='27_Loan'!J20/1000000 -> 22.362969 | I66: ='27_Loan'!K20/1000000 -> 20.784742 | J66: ='27_Loan'!L20/1000000 -> 18.956128 | ... P66: ='27_Loan'!R20/1000000 -> 0
B67: DSCR | C67: =IF(ISNUMBER('43_Ratios'!E12),MIN(10,'43_Ratios'!E12),0) -> 0 | D67: =IF(ISNUMBER('43_Ratios'!F12),MIN(10,'43_Ratios'!F12),0) -> 0 | E67: =IF(ISNUMBER('43_Ratios'!G12),MIN(10,'43_Ratios'!G12),0) -> 0 | F67: =IF(ISNUMBER('43_Ratios'!H12),MIN(10,'43_Ratios'!H12),0) -> 0 | G67: =IF(ISNUMBER('43_Ratios'!I12),MIN(10,'43_Ratios'!I12),0) -> 6.2086359 | H67: =IF(ISNUMBER('43_Ratios'!J12),MIN(10,'43_Ratios'!J12),0) -> 6.9508813 | I67: =IF(ISNUMBER('43_Ratios'!K12),MIN(10,'43_Ratios'!K12),0) -> 1.7426163 | J67: =IF(ISNUMBER('43_Ratios'!L12),MIN(10,'43_Ratios'!L12),0) -> 2.93831 | ... P67: =IF(ISNUMBER('43_Ratios'!R12),MIN(10,'43_Ratios'!R12),0) -> 5.5199733
B68: Covenant | C68: =DSCR_COV -> 1.3 | D68: =DSCR_COV -> 1.3 | E68: =DSCR_COV -> 1.3 | F68: =DSCR_COV -> 1.3 | G68: =DSCR_COV -> 1.3 | H68: =DSCR_COV -> 1.3 | I68: =DSCR_COV -> 1.3 | J68: =DSCR_COV -> 1.3 | ... P68: =DSCR_COV -> 1.3
B69: Sales | C69: ='24_Revenue'!E40/1000000 -> 0 | D69: ='24_Revenue'!F40/1000000 -> 0 | E69: ='24_Revenue'!G40/1000000 -> 327.43786 | F69: ='24_Revenue'!H40/1000000 -> 0 | G69: ='24_Revenue'!I40/1000000 -> 98.611128 | H69: ='24_Revenue'!J40/1000000 -> 72.314827 | I69: ='24_Revenue'!K40/1000000 -> 0 | J69: ='24_Revenue'!L40/1000000 -> 0 | ... P69: ='24_Revenue'!R40/1000000 -> 0
B70: Rent | C70: ='24_Revenue'!E55/1000000 -> 0 | D70: ='24_Revenue'!F55/1000000 -> 0 | E70: ='24_Revenue'!G55/1000000 -> 0 | F70: ='24_Revenue'!H55/1000000 -> 0 | G70: ='24_Revenue'!I55/1000000 -> 19.287865 | H70: ='24_Revenue'!J55/1000000 -> 27.774526 | I70: ='24_Revenue'!K55/1000000 -> 34.495961 | J70: ='24_Revenue'!L55/1000000 -> 37.255638 | ... P70: ='24_Revenue'!R55/1000000 -> 59.120015
B71: Other | C71: =('24_Revenue'!E57+'24_Revenue'!E59+'24_Revenue'!E60)/1000000 -> 0 | D71: =('24_Revenue'!F57+'24_Revenue'!F59+'24_Revenue'!F60)/1000000 -> 0 | E71: =('24_Revenue'!G57+'24_Revenue'!G59+'24_Revenue'!G60)/1000000 -> 0 | F71: =('24_Revenue'!H57+'24_Revenue'!H59+'24_Revenue'!H60)/1000000 -> 0 | G71: =('24_Revenue'!I57+'24_Revenue'!I59+'24_Revenue'!I60)/1000000 -> 4.2646944 | H71: =('24_Revenue'!J57+'24_Revenue'!J59+'24_Revenue'!J60)/1000000 -> 5.0884938 | I71: =('24_Revenue'!K57+'24_Revenue'!K59+'24_Revenue'!K60)/1000000 -> 5.759423 | J71: =('24_Revenue'!L57+'24_Revenue'!L59+'24_Revenue'!L60)/1000000 -> 6.0803939 | ... P71: =('24_Revenue'!R57+'24_Revenue'!R59+'24_Revenue'!R60)/1000000 -> 6.73557

Sheet 02_Home
B1: Home Estimate | I1: =HYPERLINK("#'00_Start'!A1","◂ Start") -> ◂ Start
B2: የቤት ግንባታ ወጪ ግምት
B3: =PROJ_NAME&" | Scenario: "&SCEN_NAME&" | Mode: "&MODE_NAME -> SAMPLE B — B+G+8 mixed-use building, Addis Ababa | Scenario: Base | Mode: 3 Mixed
B5: =IF(PROJECT_MODE<>0,"Commercial mode is on – this page still shows the cost estimate for the same inputs. · ይህ ገጽ ለተመሳሳይ ግብዓቶች የወጪ ግምቱን ያሳያል።","") -> Commercial mode is on – this page still shows the cost estimate for the same inputs. · ይህ ገጽ ለተመሳሳይ ግብዓቶች የወጪ ግምቱን ያሳያል።
B6: Project · ፕሮጀክት | C6: =PROJ_NAME -> SAMPLE B — B+G+8 mixed-use building, Addis Ababa
B7: Building · ሕንፃ | C7: =BTYPE_CALC&" · "&TEXT(GFA,"#,##0")&" m² gross · "&INDEX(L_FINISH,FIN_IX)&" finish" -> B1+G+8 · 6,400 m² gross · Standard finish
B8: Where & how long · ቦታና ጊዜ | C8: =INDEX(L_LOC,LOC_TYPE)&" · "&CONSTR_EFF&" months of construction" -> Addis Ababa · 30 months of construction
B10: CONSTRUCTION COST · የግንባታ ወጪ | C10: COST PER m² · ዋጋ በካሬ ሜትር | G10: MONTHLY INSTALMENT · ወርሃዊ ክፍያ | I10: FUNDING GAP · የገንዘብ ክፍተት
B11: =CONSTR_COST -> 3.7632566e+08 | C11: =CC_M2 -> 58800.884 | G11: =LN_INSTAL_M -> 472859.07 | I11: =FUND_GAP -> 0
B13: ="Range "&TEXT(CONSTR_COST*(1+EST_LOW)/1000000,"#,##0.0")&" – "&TEXT(CONSTR_COST*(1+EST_HIGH)/1000000,"#,##0.0")&" m" -> Range 338.7 – 432.8 m | C13: ="All-in incl. land & finance: "&TEXT(TDC_M2G,"#,##0") -> All-in incl. land & finance: 86,041 | G13: =IF(HH_INCOME>0,TEXT(AFFORD_PCT,"0%")&" of income · "&AFFORD_TXT,"enter income") -> enter income | I13: =IF(FUND_GAP>0.5,"find more funds","covered · በቂ ነው") -> covered · በቂ ነው
B15: COST BREAKDOWN · የወጪ ክፍፍል | G15: WHERE THE MONEY GOES
B16: Item | C16: ETB | D16: % total
B17: ='22_Capex'!B74 -> Substructure & basement | C17: ='22_Capex'!D74 -> 35120000 | D17: =IF(HOME_TOTAL>0,C17/HOME_TOTAL,0) -> 0.063777962 | E17: መሠረትና ምድር ቤት
B18: ='22_Capex'!B75 -> Frame & envelope | C18: ='22_Capex'!D75 -> 85632000 | D18: =IF(HOME_TOTAL>0,C18/HOME_TOTAL,0) -> 0.15550781 | E18: ፍሬምና ግድግዳ
B19: ='22_Capex'!B76 -> Internal works & finishes | C19: ='22_Capex'!D76 -> 51200000 | D19: =IF(HOME_TOTAL>0,C19/HOME_TOTAL,0) -> 0.092979261 | E19: የውስጥና ማጠናቀቂያ
B20: ='22_Capex'!B77 -> MEP & specialist systems | C20: ='22_Capex'!D77 -> 73160000 | D20: =IF(HOME_TOTAL>0,C20/HOME_TOTAL,0) -> 0.13285865 | E20: ኤሌክትሪክ፣ ቧንቧ፣ ሲስተሞች
B21: ='22_Capex'!B78 -> Preliminaries & external works | C21: ='22_Capex'!D78 -> 22445000 | D21: =IF(HOME_TOTAL>0,C21/HOME_TOTAL,0) -> 0.040760147 | E21: ቅድመ-ሥራና የውጭ ሥራ
B22: ='22_Capex'!B79 -> Escalation & contingency | C22: ='22_Capex'!D79 -> 77311137 | D22: =IF(HOME_TOTAL>0,C22/HOME_TOTAL,0) -> 0.14039712 | E22: የዋጋ ጭማሪና መጠባበቂያ
B23: ='22_Capex'!B80 -> Fees & permits | C23: ='22_Capex'!D80 -> 25457520 | D23: =IF(HOME_TOTAL>0,C23/HOME_TOTAL,0) -> 0.046230888 | E23: ክፍያዎችና ፈቃድ
B24: ='22_Capex'!B81 -> Furniture & FF&E | C24: ='22_Capex'!D81 -> 6000000 | D24: =IF(HOME_TOTAL>0,C24/HOME_TOTAL,0) -> 0.010896007 | E24: የቤት ዕቃዎች
B25: ='22_Capex'!B82 -> Land | C25: ='22_Capex'!D82 -> 150000000 | D25: =IF(HOME_TOTAL>0,C25/HOME_TOTAL,0) -> 0.27240018 | E25: መሬት
B26: ='22_Capex'!B83 -> Finance costs (fees + IDC) | C26: ='22_Capex'!D83 -> 24334774 | D26: =IF(HOME_TOTAL>0,C26/HOME_TOTAL,0) -> 0.044191979 | E26: የብድር ወጪ
B27: TOTAL PROJECT COST · ጠቅላላ | C27: =SUM(C17:C26) -> 5.5066043e+08
B29: PAYING THE CONTRACTOR · ለኮንትራክተር ክፍያ | G29: CASH NEEDED EACH MONTH (S-curve)
B30: Stage | C30: ETB | D30: Cum. % | E30: ≈ month
B31: ='22_Capex'!B87 -> 1 Mobilisation & site set-up | C31: ='22_Capex'!D87 -> 13198869 | D31: =IF(STAGE_TOT>0,SUM($C$31:C31)/STAGE_TOT,0) -> 0.038272219 | E31: =MIN(CONSTR_EFF,COUNTIF('23_Construction'!$E$16:$AZ$16,"<"&(D31-0.0001))+1) -> 5
B32: ='22_Capex'!B88 -> 2 Foundation / substructure | C32: ='22_Capex'!D88 -> 45267995 | D32: =IF(STAGE_TOT>0,SUM($C$31:C32)/STAGE_TOT,0) -> 0.16953397 | E32: =MIN(CONSTR_EFF,COUNTIF('23_Construction'!$E$16:$AZ$16,"<"&(D32-0.0001))+1) -> 10
B33: ='22_Capex'!B89 -> 3 Frame (columns, beams, slabs) | C33: ='22_Capex'!D89 -> 70778934 | D33: =IF(STAGE_TOT>0,SUM($C$31:C33)/STAGE_TOT,0) -> 0.37476874 | E33: =MIN(CONSTR_EFF,COUNTIF('23_Construction'!$E$16:$AZ$16,"<"&(D33-0.0001))+1) -> 14
B34: ='22_Capex'!B90 -> 4 Walls, windows & roof | C34: ='22_Capex'!D90 -> 39596606 | D34: =IF(STAGE_TOT>0,SUM($C$31:C34)/STAGE_TOT,0) -> 0.4895854 | E34: =MIN(CONSTR_EFF,COUNTIF('23_Construction'!$E$16:$AZ$16,"<"&(D34-0.0001))+1) -> 15
B35: ='22_Capex'!B91 -> 5 MEP & internal works | C35: ='22_Capex'!D91 -> 1.1409803e+08 | D35: =IF(STAGE_TOT>0,SUM($C$31:C35)/STAGE_TOT,0) -> 0.82043079 | E35: =MIN(CONSTR_EFF,COUNTIF('23_Construction'!$E$16:$AZ$16,"<"&(D35-0.0001))+1) -> 21
B36: ='22_Capex'!B92 -> 6 Finishes & external works | C36: ='22_Capex'!D92 -> 61927700 | D36: =IF(STAGE_TOT>0,SUM($C$31:C36)/STAGE_TOT,0) -> 1 | E36: =MIN(CONSTR_EFF,COUNTIF('23_Construction'!$E$16:$AZ$16,"<"&(D36-0.0001))+1) -> 30
B37: Retention released after completion | C37: =RET_TOT -> 15966117 | E37: =CONSTR_EFF+RET_REL_M -> 42
B39: FUNDING & HOME LOAN · ገንዘብና ብድር | G39: HOME-LOAN SCHEDULE · የብድር ሰንጠረዥ
B40: Own savings · ቁጠባ | C40: =SAVINGS -> 0 | G40: Year | H40: Interest | I40: Principal | J40: Closing
B41: Family / diaspora · ቤተሰብ | C41: =FAMILY -> 0 | G41: Build | H41: =SUMIFS('27_Loan'!$E$65:$KF$65,'27_Loan'!$E$56:$KF$56,0) -> 17535682 | J41: =SUMIFS('27_Loan'!$E$75:$KF$75,'27_Loan'!$E$55:$KF$55,0) -> 1.3314989e+08
B42: Home loan drawn · የወጣ ብድር | C42: =DEBT_DRAWN -> 1.1561421e+08 | G42: 1 | H42: =SUMIFS('27_Loan'!$E$65:$KF$65,'27_Loan'!$E$56:$KF$56,$G42) -> 14569759 | I42: =SUMIFS('27_Loan'!$E$72:$KF$72,'27_Loan'!$E$56:$KF$56,$G42)+SUMIFS('27_Loan'!$E$74:$KF$74,'27_Loan'!$E$56:$KF$56,$G42) -> 78736994 | J42: =SUMIFS('27_Loan'!$E$75:$KF$75,'27_Loan'!$E$55:$KF$55,12*$G42) -> 54412900
B43: Funding gap · ክፍተት | C43: =FUND_GAP -> 0 | G43: 2 | H43: =SUMIFS('27_Loan'!$E$65:$KF$65,'27_Loan'!$E$56:$KF$56,$G43) -> 7991598.9 | I43: =SUMIFS('27_Loan'!$E$72:$KF$72,'27_Loan'!$E$56:$KF$56,$G43)+SUMIFS('27_Loan'!$E$74:$KF$74,'27_Loan'!$E$56:$KF$56,$G43) -> 32049931 | J43: =SUMIFS('27_Loan'!$E$75:$KF$75,'27_Loan'!$E$55:$KF$55,12*$G43) -> 22362969
B44: Interest rate · ወለድ | C44: =RATE_EFF -> 0.15 | G44: 3 | H44: =SUMIFS('27_Loan'!$E$65:$KF$65,'27_Loan'!$E$56:$KF$56,$G44) -> 3268392.5 | I44: =SUMIFS('27_Loan'!$E$72:$KF$72,'27_Loan'!$E$56:$KF$56,$G44)+SUMIFS('27_Loan'!$E$74:$KF$74,'27_Loan'!$E$56:$KF$56,$G44) -> 1578227.2 | J44: =SUMIFS('27_Loan'!$E$75:$KF$75,'27_Loan'!$E$55:$KF$55,12*$G44) -> 20784742
B45: Tenor after completion (yrs) | C45: =TENOR_Y -> 10 | G45: 4 | H45: =SUMIFS('27_Loan'!$E$65:$KF$65,'27_Loan'!$E$56:$KF$56,$G45) -> 3018006.1 | I45: =SUMIFS('27_Loan'!$E$72:$KF$72,'27_Loan'!$E$56:$KF$56,$G45)+SUMIFS('27_Loan'!$E$74:$KF$74,'27_Loan'!$E$56:$KF$56,$G45) -> 1828613.6 | J45: =SUMIFS('27_Loan'!$E$75:$KF$75,'27_Loan'!$E$55:$KF$55,12*$G45) -> 18956128
B46: Monthly instalment · ወርሃዊ ክፍያ | C46: =LN_INSTAL_M -> 472859.07 | G46: 5 | H46: =SUMIFS('27_Loan'!$E$65:$KF$65,'27_Loan'!$E$56:$KF$56,$G46) -> 2727895.8 | I46: =SUMIFS('27_Loan'!$E$72:$KF$72,'27_Loan'!$E$56:$KF$56,$G46)+SUMIFS('27_Loan'!$E$74:$KF$74,'27_Loan'!$E$56:$KF$56,$G46) -> 2118723.9 | J46: =SUMIFS('27_Loan'!$E$75:$KF$75,'27_Loan'!$E$55:$KF$55,12*$G46) -> 16837404
B47: Total interest · ጠቅላላ ወለድ | C47: =LN_INT_TOT -> 56507029 | G47: 6 | H47: =SUMIFS('27_Loan'!$E$65:$KF$65,'27_Loan'!$E$56:$KF$56,$G47) -> 2391759.4 | I47: =SUMIFS('27_Loan'!$E$72:$KF$72,'27_Loan'!$E$56:$KF$56,$G47)+SUMIFS('27_Loan'!$E$74:$KF$74,'27_Loan'!$E$56:$KF$56,$G47) -> 2454860.4 | J47: =SUMIFS('27_Loan'!$E$75:$KF$75,'27_Loan'!$E$55:$KF$55,12*$G47) -> 14382544
B48: Loan repaid by · የሚያልቅበት | C48: =LN_FINAL_DATE -> 50951 | G48: 7 | H48: =SUMIFS('27_Loan'!$E$65:$KF$65,'27_Loan'!$E$56:$KF$56,$G48) -> 2002294.8 | I48: =SUMIFS('27_Loan'!$E$72:$KF$72,'27_Loan'!$E$56:$KF$56,$G48)+SUMIFS('27_Loan'!$E$74:$KF$74,'27_Loan'!$E$56:$KF$56,$G48) -> 2844325 | J48: =SUMIFS('27_Loan'!$E$75:$KF$75,'27_Loan'!$E$55:$KF$55,12*$G48) -> 11538219
B49: Instalment ÷ income · ከገቢ ድርሻ | C49: =IF(HH_INCOME>0,LN_INSTAL_M/HH_INCOME,0) -> 0 | G49: 8 | H49: =SUMIFS('27_Loan'!$E$65:$KF$65,'27_Loan'!$E$56:$KF$56,$G49) -> 1551041.4 | I49: =SUMIFS('27_Loan'!$E$72:$KF$72,'27_Loan'!$E$56:$KF$56,$G49)+SUMIFS('27_Loan'!$E$74:$KF$74,'27_Loan'!$E$56:$KF$56,$G49) -> 3295578.3 | J49: =SUMIFS('27_Loan'!$E$75:$KF$75,'27_Loan'!$E$55:$KF$55,12*$G49) -> 8242640.8
B50: Affordability · የመክፈል አቅም | C50: =IF(HH_INCOME<=0,"n/a",IF(AFFORD_PCT<=AFFORD_MAX,"Affordable · ይቻላል",IF(AFFORD_PCT<=AFFORD_MAX*1.25,"Stretch · ከባድ","Not affordable · አይቻልም"))) -> n/a | G50: 9 | H50: =SUMIFS('27_Loan'!$E$65:$KF$65,'27_Loan'!$E$56:$KF$56,$G50) -> 1028196.6 | I50: =SUMIFS('27_Loan'!$E$72:$KF$72,'27_Loan'!$E$56:$KF$56,$G50)+SUMIFS('27_Loan'!$E$74:$KF$74,'27_Loan'!$E$56:$KF$56,$G50) -> 3818423.2 | J50: =SUMIFS('27_Loan'!$E$75:$KF$75,'27_Loan'!$E$55:$KF$55,12*$G50) -> 4424217.6
G51: 10 | H51: =SUMIFS('27_Loan'!$E$65:$KF$65,'27_Loan'!$E$56:$KF$56,$G51) -> 422402.14 | I51: =SUMIFS('27_Loan'!$E$72:$KF$72,'27_Loan'!$E$56:$KF$56,$G51)+SUMIFS('27_Loan'!$E$74:$KF$74,'27_Loan'!$E$56:$KF$56,$G51) -> 4424217.6 | J51: =SUMIFS('27_Loan'!$E$75:$KF$75,'27_Loan'!$E$55:$KF$55,12*$G51) -> 0
B52: OPTIONAL: RENT OUT PART · ከፊሉን ማከራየት | G52: 11 | H52: =SUMIFS('27_Loan'!$E$65:$KF$65,'27_Loan'!$E$56:$KF$56,$G52) -> 0 | I52: =SUMIFS('27_Loan'!$E$72:$KF$72,'27_Loan'!$E$56:$KF$56,$G52)+SUMIFS('27_Loan'!$E$74:$KF$74,'27_Loan'!$E$56:$KF$56,$G52) -> 0 | J52: =SUMIFS('27_Loan'!$E$75:$KF$75,'27_Loan'!$E$55:$KF$55,12*$G52) -> 0
B53: Switched on? (Inputs block 2) | C53: =IF(RENT_HOME_F=1,"Yes · አዎ","No · አይ") -> No · አይ | G53: 12 | H53: =SUMIFS('27_Loan'!$E$65:$KF$65,'27_Loan'!$E$56:$KF$56,$G53) -> 0 | I53: =SUMIFS('27_Loan'!$E$72:$KF$72,'27_Loan'!$E$56:$KF$56,$G53)+SUMIFS('27_Loan'!$E$74:$KF$74,'27_Loan'!$E$56:$KF$56,$G53) -> 0 | J53: =SUMIFS('27_Loan'!$E$75:$KF$75,'27_Loan'!$E$55:$KF$55,12*$G53) -> 0
B54: Rent income, first year · ኪራይ | C54: =IF(RENT_HOME_F=1,'24_Revenue'!$I$55,0) -> 0 | G54: 13 | H54: =SUMIFS('27_Loan'!$E$65:$KF$65,'27_Loan'!$E$56:$KF$56,$G54) -> 0 | I54: =SUMIFS('27_Loan'!$E$72:$KF$72,'27_Loan'!$E$56:$KF$56,$G54)+SUMIFS('27_Loan'!$E$74:$KF$74,'27_Loan'!$E$56:$KF$56,$G54) -> 0 | J54: =SUMIFS('27_Loan'!$E$75:$KF$75,'27_Loan'!$E$55:$KF$55,12*$G54) -> 0
B55: Gross yield on total cost · ገቢ ከወጪ | C55: =IF(AND(RENT_HOME_F=1,HOME_TOTAL>0),'24_Revenue'!$K$55/HOME_TOTAL,0) -> 0 | G55: 14 | H55: =SUMIFS('27_Loan'!$E$65:$KF$65,'27_Loan'!$E$56:$KF$56,$G55) -> 0 | I55: =SUMIFS('27_Loan'!$E$72:$KF$72,'27_Loan'!$E$56:$KF$56,$G55)+SUMIFS('27_Loan'!$E$74:$KF$74,'27_Loan'!$E$56:$KF$56,$G55) -> 0 | J55: =SUMIFS('27_Loan'!$E$75:$KF$75,'27_Loan'!$E$55:$KF$55,12*$G55) -> 0
B56: Simple payback (years) · የመመለሻ ጊዜ | C56: =IF(AND(RENT_HOME_F=1,'24_Revenue'!$K$55>0),HOME_TOTAL/'24_Revenue'!$K$55,0) -> 0 | G56: 15 | H56: =SUMIFS('27_Loan'!$E$65:$KF$65,'27_Loan'!$E$56:$KF$56,$G56) -> 0 | I56: =SUMIFS('27_Loan'!$E$72:$KF$72,'27_Loan'!$E$56:$KF$56,$G56)+SUMIFS('27_Loan'!$E$74:$KF$74,'27_Loan'!$E$56:$KF$56,$G56) -> 0 | J56: =SUMIFS('27_Loan'!$E$75:$KF$75,'27_Loan'!$E$55:$KF$55,12*$G56) -> 0
B57: Rent ÷ monthly instalment · የሚሸፍነው | C57: =IF(AND(RENT_HOME_F=1,LN_INSTAL_M>0),'24_Revenue'!$I$55/12/LN_INSTAL_M,0) -> 0 | G57: 16 | H57: =SUMIFS('27_Loan'!$E$65:$KF$65,'27_Loan'!$E$56:$KF$56,$G57) -> 0 | I57: =SUMIFS('27_Loan'!$E$72:$KF$72,'27_Loan'!$E$56:$KF$56,$G57)+SUMIFS('27_Loan'!$E$74:$KF$74,'27_Loan'!$E$56:$KF$56,$G57) -> 0 | J57: =SUMIFS('27_Loan'!$E$75:$KF$75,'27_Loan'!$E$55:$KF$55,12*$G57) -> 0
G58: 17 | H58: =SUMIFS('27_Loan'!$E$65:$KF$65,'27_Loan'!$E$56:$KF$56,$G58) -> 0 | I58: =SUMIFS('27_Loan'!$E$72:$KF$72,'27_Loan'!$E$56:$KF$56,$G58)+SUMIFS('27_Loan'!$E$74:$KF$74,'27_Loan'!$E$56:$KF$56,$G58) -> 0 | J58: =SUMIFS('27_Loan'!$E$75:$KF$75,'27_Loan'!$E$55:$KF$55,12*$G58) -> 0
G59: 18 | H59: =SUMIFS('27_Loan'!$E$65:$KF$65,'27_Loan'!$E$56:$KF$56,$G59) -> 0 | I59: =SUMIFS('27_Loan'!$E$72:$KF$72,'27_Loan'!$E$56:$KF$56,$G59)+SUMIFS('27_Loan'!$E$74:$KF$74,'27_Loan'!$E$56:$KF$56,$G59) -> 0 | J59: =SUMIFS('27_Loan'!$E$75:$KF$75,'27_Loan'!$E$55:$KF$55,12*$G59) -> 0
G60: 19 | H60: =SUMIFS('27_Loan'!$E$65:$KF$65,'27_Loan'!$E$56:$KF$56,$G60) -> 0 | I60: =SUMIFS('27_Loan'!$E$72:$KF$72,'27_Loan'!$E$56:$KF$56,$G60)+SUMIFS('27_Loan'!$E$74:$KF$74,'27_Loan'!$E$56:$KF$56,$G60) -> 0 | J60: =SUMIFS('27_Loan'!$E$75:$KF$75,'27_Loan'!$E$55:$KF$55,12*$G60) -> 0
G61: 20 | H61: =SUMIFS('27_Loan'!$E$65:$KF$65,'27_Loan'!$E$56:$KF$56,$G61) -> 0 | I61: =SUMIFS('27_Loan'!$E$72:$KF$72,'27_Loan'!$E$56:$KF$56,$G61)+SUMIFS('27_Loan'!$E$74:$KF$74,'27_Loan'!$E$56:$KF$56,$G61) -> 0 | J61: =SUMIFS('27_Loan'!$E$75:$KF$75,'27_Loan'!$E$55:$KF$55,12*$G61) -> 0
B63: Planning estimate only – get a priced BOQ from a licensed quantity surveyor before signing a contract.
B64: ይህ ግምት ብቻ ነው፤ ውል ከመፈረምዎ በፊት ፈቃድ ካለው ባለሙያ የተዘጋጀ የሥራ መጠን ዝርዝር (BOQ) ያግኙ።

Sheet 10_Inputs
B1: 10 · Inputs – all assumptions | J1: =HYPERLINK("#'00_Start'!A1","◂ Start") -> ◂ Start
B2: ግብዓቶች – ሁሉም ግምቶች
B3: =PROJ_NAME&" | Scenario: "&SCEN_NAME&" | Mode: "&MODE_NAME -> SAMPLE B — B+G+8 mixed-use building, Addis Ababa | Scenario: Base | Mode: 3 Mixed
B6: Input | C6: ግብዓት | D6: Unit | E6: MY PROJECT (your values) | F6: SAMPLE A G+1 house | G6: SAMPLE B B+G+8 mixed | H6: ACTIVE (used by model) | I6: Range name | J6: Notes / source
B7: Blue cells on amber are inputs. Column H picks the data set chosen on the Start sheet (1 = My project, 2 = Sample A, 3 = Sample B). Sample columns are examples – "Sample value — not market advice".
B9: 1. Project | C9: 1. ፕሮጀክት
B10: Project name | C10: የፕሮጀክት ስም | D10: text | E10: My project | F10: SAMPLE A — G+1 family house, Addis Ababa | G10: SAMPLE B — B+G+8 mixed-use building, Addis Ababa | H10: =CHOOSE(DATA_SET,E10,F10,G10) -> SAMPLE B — B+G+8 mixed-use building, Addis Ababa | I10: PROJ_NAME | J10: Shown in every sheet header
B11: Location (sub-city / town) | C11: አካባቢ (ክ/ከተማ / ከተማ) | D11: text | F11: Addis Ababa – Bole sub-city | G11: Addis Ababa – Kirkos sub-city | H11: =CHOOSE(DATA_SET,E11,F11,G11) -> Addis Ababa – Kirkos sub-city | I11: LOCATION | J11: Free text
B12: Location class for cost factor | C12: የቦታ ዓይነት (ለወጪ ማስተካከያ) | D12: list | E12: Addis Ababa | F12: Addis Ababa | G12: Addis Ababa | H12: =IFERROR(MATCH(CHOOSE(DATA_SET,E12,F12,G12),L_LOC,0),1) -> 1 | I12: LOC_TYPE | J12: Regional towns use the regional location factor
B13: Plot area | C13: የቦታ ስፋት | D13: m² | E13: 0 | F13: 300 | G13: 1000 | H13: =CHOOSE(DATA_SET,E13,F13,G13) -> 1000 | I13: PLOT_AREA | J13: From title deed / lease contract
B14: Max floor-area ratio (FAR) permitted | C14: የተፈቀደ የወለል ስፋት ጥምርታ | D14: x | E14: 0 | F14: 1.5 | G14: 8 | H14: =CHOOSE(DATA_SET,E14,F14,G14) -> 8 | I14: FAR | J14: From the city master plan / building permit; 0 = not checked
B15: Construction start date | C15: የግንባታ መጀመሪያ ቀን | D15: date | E15: 46388 | F15: 46388 | G15: 46388 | H15: =CHOOSE(DATA_SET,E15,F15,G15) -> 46388 | I15: START_DATE | J15: First month of construction (budget date for prices)
B16: Construction period | C16: የግንባታ ጊዜ | D16: months | E16: 12 | F16: 14 | G16: 30 | H16: =CHOOSE(DATA_SET,E16,F16,G16) -> 30 | I16: CONSTR_M | J16: 1–48 months; scenario delay months are added
B17: Memo: ETB per USD | C17: ብር በአንድ ዶላር (ማስታወሻ) | D17: ETB/USD | E17: 155 | F17: 155 | G17: 155 | H17: =CHOOSE(DATA_SET,E17,F17,G17) -> 155 | I17: FX_USD | J17: Memo only – the model runs in ETB. Verify current NBE rate
B18: 2. Home estimate card (Mode 0) | C18: 2. የቤት ወጪ ግምት መረጃ (ዓይነት 0)
B19: Building type | C19: የሕንፃው ዓይነት | D19: list | E19: G+1 | F19: G+1 | G19: Other / commercial | H19: =IFERROR(MATCH(CHOOSE(DATA_SET,E19,F19,G19),L_BTYPE,0),1) -> 5 | I19: BLDG_TYPE | J19: Checked against the floors entered in block 3
B20: Basement? | C20: ምድር ቤት አለው? | D20: Y/N | E20: No | F20: No | G20: Yes | H20: =IF(CHOOSE(DATA_SET,E20,F20,G20)="Yes",1,0) -> 1 | I20: BASEMENT_YN | J20: Checked against block 3
B21: Finish level | C21: የማጠናቀቂያ ደረጃ | D21: list | E21: Standard | F21: Standard | G21: Standard | H21: =IFERROR(MATCH(CHOOSE(DATA_SET,E21,F21,G21),L_FINISH,0),1) -> 2 | I21: FINISH | J21: Selects the column of the cost library (block 4)
B22: Household monthly income (for affordability) | C22: የቤተሰብ ወርሃዊ ገቢ | D22: ETB/month | E22: 0 | F22: 300000 | G22: 0 | H22: =CHOOSE(DATA_SET,E22,F22,G22) -> 0 | I22: HH_INCOME | J22: Net income of all earners
B23: Max instalment as % of income | C23: ከገቢ ከፍተኛ የክፍያ ድርሻ | D23: % | E23: 0.35 | F23: 0.35 | G23: 0.35 | H23: =CHOOSE(DATA_SET,E23,F23,G23) -> 0.35 | I23: AFFORD_MAX | J23: Typical bank rule of thumb 30–40%
B24: Estimate range – low side | C24: የግምት ዝቅተኛ ወሰን | D24: % | E24: -0.1 | F24: -0.1 | G24: -0.1 | H24: =CHOOSE(DATA_SET,E24,F24,G24) -> -0.1 | I24: EST_LOW | J24: Applied to construction cost for the low estimate
B25: Estimate range – high side | C25: የግምት ከፍተኛ ወሰን | D25: % | E25: 0.15 | F25: 0.15 | G25: 0.15 | H25: =CHOOSE(DATA_SET,E25,F25,G25) -> 0.15 | I25: EST_HIGH | J25: Applied to construction cost for the high estimate
B26: Own savings available | C26: የራስ ቁጠባ | D26: ETB | E26: 0 | F26: 5000000 | G26: 0 | H26: =CHOOSE(DATA_SET,E26,F26,G26) -> 0 | I26: SAVINGS | J26: Mode 0 funding, drawn first
B27: Family / diaspora contributions | C27: የቤተሰብ / ዳያስፖራ መዋጮ | D27: ETB | E27: 0 | F27: 2500000 | G27: 0 | H27: =CHOOSE(DATA_SET,E27,F27,G27) -> 0 | I27: FAMILY | J27: Mode 0 funding, drawn after savings
B28: Home loan amount (maximum) | C28: የቤት ብድር መጠን | D28: ETB | E28: 0 | F28: 7000000 | G28: 0 | H28: =CHOOSE(DATA_SET,E28,F28,G28) -> 0 | I28: HOME_LOAN | J28: Mode 0: bank home-loan limit. Uses the loan terms in block 9
B29: I may rent out part of the house | C29: የቤቱን ከፊል ለማከራየት እችላለሁ | D29: Y/N | E29: No | F29: No | G29: No | H29: =IF(CHOOSE(DATA_SET,E29,F29,G29)="Yes",1,0) -> 0 | I29: RENT_HOME_F | J29: Upgrade path inside Mode 0: adds rent, payback and yield
B30: Area rented out | C30: የሚከራየው ስፋት | D30: m² | E30: 0 | F30: 60 | G30: 0 | H30: =CHOOSE(DATA_SET,E30,F30,G30) -> 0 | I30: RENT_HOME_AREA | J30: e.g. ground-floor unit or service quarter
B31: Expected rent for that part (today's prices) | C31: የሚጠበቅ ወርሃዊ ኪራይ | D31: ETB/month | E31: 0 | F31: 25000 | G31: 0 | H31: =CHOOSE(DATA_SET,E31,F31,G31) -> 0 | I31: RENT_HOME_MONTHLY | J31: Escalated with rent escalation (block 7)
B32: 3. Area programme – gross floor area by floor | C32: 3. የወለል ስፋት በፎቅ
B33: Basement 2 – gross area | C33: ምድር ቤት 2 – ጠቅላላ ስፋት | D33: m² | E33: 0 | F33: 0 | G33: 0 | H33: =CHOOSE(DATA_SET,E33,F33,G33) -> 0 | I33: FL_A1 | J33: Gross floor area incl. walls & common areas
B34: Basement 1 – gross area | C34: ምድር ቤት 1 – ጠቅላላ ስፋት | D34: m² | E34: 0 | F34: 0 | G34: 900 | H34: =CHOOSE(DATA_SET,E34,F34,G34) -> 900 | I34: FL_A2 | J34: Gross floor area incl. walls & common areas
B35: Ground floor – gross area | C35: ምድር ወለል – ጠቅላላ ስፋት | D35: m² | E35: 0 | F35: 130 | G35: 650 | H35: =CHOOSE(DATA_SET,E35,F35,G35) -> 650 | I35: FL_A3 | J35: Gross floor area incl. walls & common areas
B36: Floor 1 – gross area | C36: 1ኛ ፎቅ – ጠቅላላ ስፋት | D36: m² | E36: 0 | F36: 120 | G36: 650 | H36: =CHOOSE(DATA_SET,E36,F36,G36) -> 650 | I36: FL_A4 | J36: Gross floor area incl. walls & common areas
B37: Floor 2 – gross area | C37: 2ኛ ፎቅ – ጠቅላላ ስፋት | D37: m² | E37: 0 | F37: 0 | G37: 600 | H37: =CHOOSE(DATA_SET,E37,F37,G37) -> 600 | I37: FL_A5 | J37: Gross floor area incl. walls & common areas
B38: Floor 3 – gross area | C38: 3ኛ ፎቅ – ጠቅላላ ስፋት | D38: m² | E38: 0 | F38: 0 | G38: 600 | H38: =CHOOSE(DATA_SET,E38,F38,G38) -> 600 | I38: FL_A6 | J38: Gross floor area incl. walls & common areas
B39: Floor 4 – gross area | C39: 4ኛ ፎቅ – ጠቅላላ ስፋት | D39: m² | E39: 0 | F39: 0 | G39: 600 | H39: =CHOOSE(DATA_SET,E39,F39,G39) -> 600 | I39: FL_A7 | J39: Gross floor area incl. walls & common areas
B40: Floor 5 – gross area | C40: 5ኛ ፎቅ – ጠቅላላ ስፋት | D40: m² | E40: 0 | F40: 0 | G40: 600 | H40: =CHOOSE(DATA_SET,E40,F40,G40) -> 600 | I40: FL_A8 | J40: Gross floor area incl. walls & common areas
B41: Floor 6 – gross area | C41: 6ኛ ፎቅ – ጠቅላላ ስፋት | D41: m² | E41: 0 | F41: 0 | G41: 600 | H41: =CHOOSE(DATA_SET,E41,F41,G41) -> 600 | I41: FL_A9 | J41: Gross floor area incl. walls & common areas
B42: Floor 7 – gross area | C42: 7ኛ ፎቅ – ጠቅላላ ስፋት | D42: m² | E42: 0 | F42: 0 | G42: 600 | H42: =CHOOSE(DATA_SET,E42,F42,G42) -> 600 | I42: FL_A10 | J42: Gross floor area incl. walls & common areas
B43: Floor 8 – gross area | C43: 8ኛ ፎቅ – ጠቅላላ ስፋት | D43: m² | E43: 0 | F43: 0 | G43: 600 | H43: =CHOOSE(DATA_SET,E43,F43,G43) -> 600 | I43: FL_A11 | J43: Gross floor area incl. walls & common areas
B44: Floor 9 – gross area | C44: 9ኛ ፎቅ – ጠቅላላ ስፋት | D44: m² | E44: 0 | F44: 0 | G44: 0 | H44: =CHOOSE(DATA_SET,E44,F44,G44) -> 0 | I44: FL_A12 | J44: Gross floor area incl. walls & common areas
... B48: Floor 13 – gross area | C48: 13ኛ ፎቅ – ጠቅላላ ስፋት | D48: m² | E48: 0 | F48: 0 | G48: 0 | H48: =CHOOSE(DATA_SET,E48,F48,G48) -> 0 | I48: FL_A16 | J48: Gross floor area incl. walls & common areas
B49: 3b. Use of each floor | C49: 3ለ. የእያንዳንዱ ፎቅ አገልግሎት
B50: Basement 2 – use | C50: ምድር ቤት 2 – አገልግሎት | D50: list | E50: Residential | F50: Residential | G50: Parking | H50: =CHOOSE(DATA_SET,E50,F50,G50) -> Parking | I50: FL_U1 | J50: Residential / Retail / Office / Parking / Other
B51: Basement 1 – use | C51: ምድር ቤት 1 – አገልግሎት | D51: list | E51: Residential | F51: Residential | G51: Parking | H51: =CHOOSE(DATA_SET,E51,F51,G51) -> Parking | I51: FL_U2 | J51: Residential / Retail / Office / Parking / Other
B52: Ground floor – use | C52: ምድር ወለል – አገልግሎት | D52: list | E52: Residential | F52: Residential | G52: Retail | H52: =CHOOSE(DATA_SET,E52,F52,G52) -> Retail | I52: FL_U3 | J52: Residential / Retail / Office / Parking / Other
B53: Floor 1 – use | C53: 1ኛ ፎቅ – አገልግሎት | D53: list | E53: Residential | F53: Residential | G53: Retail | H53: =CHOOSE(DATA_SET,E53,F53,G53) -> Retail | I53: FL_U4 | J53: Residential / Retail / Office / Parking / Other
B54: Floor 2 – use | C54: 2ኛ ፎቅ – አገልግሎት | D54: list | E54: Residential | F54: Residential | G54: Residential | H54: =CHOOSE(DATA_SET,E54,F54,G54) -> Residential | I54: FL_U5 | J54: Residential / Retail / Office / Parking / Other
B55: Floor 3 – use | C55: 3ኛ ፎቅ – አገልግሎት | D55: list | E55: Residential | F55: Residential | G55: Residential | H55: =CHOOSE(DATA_SET,E55,F55,G55) -> Residential | I55: FL_U6 | J55: Residential / Retail / Office / Parking / Other
B56: Floor 4 – use | C56: 4ኛ ፎቅ – አገልግሎት | D56: list | E56: Residential | F56: Residential | G56: Residential | H56: =CHOOSE(DATA_SET,E56,F56,G56) -> Residential | I56: FL_U7 | J56: Residential / Retail / Office / Parking / Other
B57: Floor 5 – use | C57: 5ኛ ፎቅ – አገልግሎት | D57: list | E57: Residential | F57: Residential | G57: Residential | H57: =CHOOSE(DATA_SET,E57,F57,G57) -> Residential | I57: FL_U8 | J57: Residential / Retail / Office / Parking / Other
B58: Floor 6 – use | C58: 6ኛ ፎቅ – አገልግሎት | D58: list | E58: Residential | F58: Residential | G58: Residential | H58: =CHOOSE(DATA_SET,E58,F58,G58) -> Residential | I58: FL_U9 | J58: Residential / Retail / Office / Parking / Other
B59: Floor 7 – use | C59: 7ኛ ፎቅ – አገልግሎት | D59: list | E59: Residential | F59: Residential | G59: Residential | H59: =CHOOSE(DATA_SET,E59,F59,G59) -> Residential | I59: FL_U10 | J59: Residential / Retail / Office / Parking / Other
B60: Floor 8 – use | C60: 8ኛ ፎቅ – አገልግሎት | D60: list | E60: Residential | F60: Residential | G60: Residential | H60: =CHOOSE(DATA_SET,E60,F60,G60) -> Residential | I60: FL_U11 | J60: Residential / Retail / Office / Parking / Other
B61: Floor 9 – use | C61: 9ኛ ፎቅ – አገልግሎት | D61: list | E61: Residential | F61: Residential | G61: Residential | H61: =CHOOSE(DATA_SET,E61,F61,G61) -> Residential | I61: FL_U12 | J61: Residential / Retail / Office / Parking / Other
... B65: Floor 13 – use | C65: 13ኛ ፎቅ – አገልግሎት | D65: list | E65: Residential | F65: Residential | G65: Residential | H65: =CHOOSE(DATA_SET,E65,F65,G65) -> Residential | I65: FL_U16 | J65: Residential / Retail / Office / Parking / Other
B66: 3c. Efficiency and disposition by use | C66: 3ሐ. ቅልጥፍናና አጠቃቀም በአገልግሎት
B67: Net-to-gross efficiency – Residential | C67: የተጣራ/ጠቅላላ ጥምርታ – መኖሪያ | D67: % | E67: 0.8 | F67: 0.85 | G67: 0.8 | H67: =CHOOSE(DATA_SET,E67,F67,G67) -> 0.8 | I67: EFF_RES | J67: Saleable or lettable m² ÷ gross m²
B68: Net-to-gross efficiency – Retail | C68: የተጣራ/ጠቅላላ ጥምርታ – የንግድ ሱቅ | D68: % | E68: 0.85 | F68: 0.85 | G68: 0.85 | H68: =CHOOSE(DATA_SET,E68,F68,G68) -> 0.85 | I68: EFF_RET | J68: Saleable or lettable m² ÷ gross m²
B69: Net-to-gross efficiency – Office | C69: የተጣራ/ጠቅላላ ጥምርታ – ቢሮ | D69: % | E69: 0.82 | F69: 0.82 | G69: 0.82 | H69: =CHOOSE(DATA_SET,E69,F69,G69) -> 0.82 | I69: EFF_OFF | J69: Saleable or lettable m² ÷ gross m²
B70: Net-to-gross efficiency – Parking | C70: የተጣራ/ጠቅላላ ጥምርታ – መኪና ማቆሚያ | D70: % | E70: 0 | F70: 0 | G70: 0 | H70: =CHOOSE(DATA_SET,E70,F70,G70) -> 0 | I70: EFF_PAR | J70: Saleable or lettable m² ÷ gross m²
B71: Net-to-gross efficiency – Other | C71: የተጣራ/ጠቅላላ ጥምርታ – ሌላ | D71: % | E71: 0 | F71: 0 | G71: 0 | H71: =CHOOSE(DATA_SET,E71,F71,G71) -> 0 | I71: EFF_OTH | J71: Saleable or lettable m² ÷ gross m²
B72: Mode 3 (Mixed): % of Residential area sold | C72: ቅይጥ፡ የሚሸጠው የመኖሪያ ድርሻ | D72: % | E72: 1 | F72: 0 | G72: 1 | H72: =CHOOSE(DATA_SET,E72,F72,G72) -> 1 | I72: SOLD_RES | J72: Rest is retained and let (IAS 40). Modes 1/2 override this
B73: Mode 3 (Mixed): % of Retail area sold | C73: ቅይጥ፡ የሚሸጠው የየንግድ ሱቅ ድርሻ | D73: % | E73: 0 | F73: 0 | G73: 0 | H73: =CHOOSE(DATA_SET,E73,F73,G73) -> 0 | I73: SOLD_RET | J73: Rest is retained and let (IAS 40). Modes 1/2 override this
B74: Mode 3 (Mixed): % of Office area sold | C74: ቅይጥ፡ የሚሸጠው የቢሮ ድርሻ | D74: % | E74: 0 | F74: 0 | G74: 0 | H74: =CHOOSE(DATA_SET,E74,F74,G74) -> 0 | I74: SOLD_OFF | J74: Rest is retained and let (IAS 40). Modes 1/2 override this
B75: Mode 3 (Mixed): % of Parking area sold | C75: ቅይጥ፡ የሚሸጠው የመኪና ማቆሚያ ድርሻ | D75: % | E75: 0 | F75: 0 | G75: 0 | H75: =CHOOSE(DATA_SET,E75,F75,G75) -> 0 | I75: SOLD_PAR | J75: Rest is retained and let (IAS 40). Modes 1/2 override this
B76: Mode 3 (Mixed): % of Other area sold | C76: ቅይጥ፡ የሚሸጠው የሌላ ድርሻ | D76: % | E76: 0 | F76: 0 | G76: 0 | H76: =CHOOSE(DATA_SET,E76,F76,G76) -> 0 | I76: SOLD_OTH | J76: Rest is retained and let (IAS 40). Modes 1/2 override this
B77: Commercial modes: % of retained area owner-occupied | C77: ለባለቤቱ አገልግሎት የሚውል ድርሻ | D77: % | E77: 0 | F77: 0 | G77: 0 | H77: =CHOOSE(DATA_SET,E77,F77,G77) -> 0 | I77: OWNUSE_PCT | J77: Owner-occupied = IAS 16; let = IAS 40; sold = IAS 2
B78: 4. Construction cost | C78: 4. የግንባታ ወጪ
B79: Preliminaries – entry method | C79: ቅድመ-ሥራዎች – አገባብ | D79: list | E79: Rate x area | F79: Rate x area | G79: Rate x area | H79: =IFERROR(MATCH(CHOOSE(DATA_SET,E79,F79,G79),L_METHOD,0),1) -> 1 | I79: METH_PRELIM | J79: Rate x area uses the cost library below; Lump sum = detailed BOQ override
B80: Substructure – entry method | C80: የመሠረት ሥራ – አገባብ | D80: list | E80: Rate x area | F80: Rate x area | G80: Rate x area | H80: =IFERROR(MATCH(CHOOSE(DATA_SET,E80,F80,G80),L_METHOD,0),1) -> 1 | I80: METH_SUBSTR | J80: Rate x area uses the cost library below; Lump sum = detailed BOQ override
B81: Superstructure (frame) – entry method | C81: ከመሬት በላይ መዋቅር (ፍሬም) – አገባብ | D81: list | E81: Rate x area | F81: Rate x area | G81: Rate x area | H81: =IFERROR(MATCH(CHOOSE(DATA_SET,E81,F81,G81),L_METHOD,0),1) -> 1 | I81: METH_SUPER | J81: Rate x area uses the cost library below; Lump sum = detailed BOQ override
B82: Envelope (walls, windows, roof) – entry method | C82: ግድግዳ፣ መስኮትና ጣሪያ – አገባብ | D82: list | E82: Rate x area | F82: Rate x area | G82: Rate x area | H82: =IFERROR(MATCH(CHOOSE(DATA_SET,E82,F82,G82),L_METHOD,0),1) -> 1 | I82: METH_ENVEL | J82: Rate x area uses the cost library below; Lump sum = detailed BOQ override
B83: Internal works (partitions, doors) – entry method | C83: የውስጥ ሥራዎች (ክፍልፋይ፣ በር) – አገባብ | D83: list | E83: Rate x area | F83: Rate x area | G83: Rate x area | H83: =IFERROR(MATCH(CHOOSE(DATA_SET,E83,F83,G83),L_METHOD,0),1) -> 1 | I83: METH_INTERN | J83: Rate x area uses the cost library below; Lump sum = detailed BOQ override
B84: Finishes – entry method | C84: የማጠናቀቂያ ሥራዎች – አገባብ | D84: list | E84: Rate x area | F84: Rate x area | G84: Rate x area | H84: =IFERROR(MATCH(CHOOSE(DATA_SET,E84,F84,G84),L_METHOD,0),1) -> 1 | I84: METH_FINISH | J84: Rate x area uses the cost library below; Lump sum = detailed BOQ override
B85: MEP (electrical, mechanical, plumbing) – entry method | C85: ኤሌክትሪክ፣ ሜካኒካልና ቧንቧ – አገባብ | D85: list | E85: Rate x area | F85: Rate x area | G85: Rate x area | H85: =IFERROR(MATCH(CHOOSE(DATA_SET,E85,F85,G85),L_METHOD,0),1) -> 1 | I85: METH_MEP | J85: Rate x area uses the cost library below; Lump sum = detailed BOQ override
B86: External works – entry method | C86: የውጭ ሥራዎች – አገባብ | D86: list | E86: Rate x area | F86: Rate x area | G86: Rate x area | H86: =IFERROR(MATCH(CHOOSE(DATA_SET,E86,F86,G86),L_METHOD,0),1) -> 1 | I86: METH_EXTW | J86: Rate x area uses the cost library below; Lump sum = detailed BOQ override
B87: Specialist systems (lifts, fire, CCTV) – entry method | C87: ልዩ ሲስተሞች (ሊፍት፣ እሳት፣ ካሜራ) – አገባብ | D87: list | E87: Rate x area | F87: Rate x area | G87: Lump sum (BOQ) | H87: =IFERROR(MATCH(CHOOSE(DATA_SET,E87,F87,G87),L_METHOD,0),1) -> 2 | I87: METH_SPEC | J87: Rate x area uses the cost library below; Lump sum = detailed BOQ override
B88: Preliminaries – lump sum (if BOQ) | C88: ቅድመ-ሥራዎች – ጠቅላላ ዋጋ (BOQ) | D88: ETB | E88: 0 | F88: 0 | G88: 0 | H88: =CHOOSE(DATA_SET,E88,F88,G88) -> 0 | I88: LUMP_PRELIM | J88: Used only when method = Lump sum (BOQ)
B89: Substructure – lump sum (if BOQ) | C89: የመሠረት ሥራ – ጠቅላላ ዋጋ (BOQ) | D89: ETB | E89: 0 | F89: 0 | G89: 0 | H89: =CHOOSE(DATA_SET,E89,F89,G89) -> 0 | I89: LUMP_SUBSTR | J89: Used only when method = Lump sum (BOQ)
B90: Superstructure (frame) – lump sum (if BOQ) | C90: ከመሬት በላይ መዋቅር (ፍሬም) – ጠቅላላ ዋጋ (BOQ) | D90: ETB | E90: 0 | F90: 0 | G90: 0 | H90: =CHOOSE(DATA_SET,E90,F90,G90) -> 0 | I90: LUMP_SUPER | J90: Used only when method = Lump sum (BOQ)
B91: Envelope (walls, windows, roof) – lump sum (if BOQ) | C91: ግድግዳ፣ መስኮትና ጣሪያ – ጠቅላላ ዋጋ (BOQ) | D91: ETB | E91: 0 | F91: 0 | G91: 0 | H91: =CHOOSE(DATA_SET,E91,F91,G91) -> 0 | I91: LUMP_ENVEL | J91: Used only when method = Lump sum (BOQ)
B92: Internal works (partitions, doors) – lump sum (if BOQ) | C92: የውስጥ ሥራዎች (ክፍልፋይ፣ በር) – ጠቅላላ ዋጋ (BOQ) | D92: ETB | E92: 0 | F92: 0 | G92: 0 | H92: =CHOOSE(DATA_SET,E92,F92,G92) -> 0 | I92: LUMP_INTERN | J92: Used only when method = Lump sum (BOQ)
B93: Finishes – lump sum (if BOQ) | C93: የማጠናቀቂያ ሥራዎች – ጠቅላላ ዋጋ (BOQ) | D93: ETB | E93: 0 | F93: 0 | G93: 0 | H93: =CHOOSE(DATA_SET,E93,F93,G93) -> 0 | I93: LUMP_FINISH | J93: Used only when method = Lump sum (BOQ)
B94: MEP (electrical, mechanical, plumbing) – lump sum (if BOQ) | C94: ኤሌክትሪክ፣ ሜካኒካልና ቧንቧ – ጠቅላላ ዋጋ (BOQ) | D94: ETB | E94: 0 | F94: 0 | G94: 0 | H94: =CHOOSE(DATA_SET,E94,F94,G94) -> 0 | I94: LUMP_MEP | J94: Used only when method = Lump sum (BOQ)
B95: External works – lump sum (if BOQ) | C95: የውጭ ሥራዎች – ጠቅላላ ዋጋ (BOQ) | D95: ETB | E95: 0 | F95: 0 | G95: 0 | H95: =CHOOSE(DATA_SET,E95,F95,G95) -> 0 | I95: LUMP_EXTW | J95: Used only when method = Lump sum (BOQ)
B96: Specialist systems (lifts, fire, CCTV) – lump sum (if BOQ) | C96: ልዩ ሲስተሞች (ሊፍት፣ እሳት፣ ካሜራ) – ጠቅላላ ዋጋ (BOQ) | D96: ETB | E96: 0 | F96: 0 | G96: 45000000 | H96: =CHOOSE(DATA_SET,E96,F96,G96) -> 45000000 | I96: LUMP_SPEC | J96: Used only when method = Lump sum (BOQ)
B97: Superstructure uplift per storey above G+3 | C97: ከG+3 በላይ ለእያንዳንዱ ፎቅ ጭማሪ | D97: % | E97: 0.02 | F97: 0.02 | G97: 0.02 | H97: =CHOOSE(DATA_SET,E97,F97,G97) -> 0.02 | I97: STOREY_UPLIFT | J97: Taller frames cost more per m²
B98: Basement extra (excavation, retaining, waterproofing) | C98: የምድር ቤት ተጨማሪ ወጪ | D98: ETB/m² | E98: 12000 | F98: 12000 | G98: 12000 | H98: =CHOOSE(DATA_SET,E98,F98,G98) -> 12000 | I98: BASEMENT_RATE | J98: Applied to basement gross area
B99: Compound wall? | C99: የአጥር ግንብ? | D99: Y/N | E99: No | F99: Yes | G99: Yes | H99: =IF(CHOOSE(DATA_SET,E99,F99,G99)="Yes",1,0) -> 1 | I99: COMPOUND_YN
B100: Compound wall length | C100: የአጥር ርዝመት | D100: m | E100: 0 | F100: 70 | G100: 120 | H100: =CHOOSE(DATA_SET,E100,F100,G100) -> 120 | I100: COMPOUND_LEN
B101: Compound wall rate | C101: የአጥር ዋጋ በሜትር | D101: ETB/m | E101: 18000 | F101: 18000 | G101: 20000 | H101: =CHOOSE(DATA_SET,E101,F101,G101) -> 20000 | I101: COMPOUND_RATE | J101: Incl. gate
B102: Septic tank? | C102: የፍሳሽ ጉድጓድ? | D102: Y/N | E102: No | F102: Yes | G102: No | H102: =IF(CHOOSE(DATA_SET,E102,F102,G102)="Yes",1,0) -> 0 | I102: SEPTIC_YN | J102: Not needed where sewer exists
B103: Septic tanks – number | C103: የፍሳሽ ጉድጓድ ብዛት | D103: no. | E103: 0 | F103: 1 | G103: 0 | H103: =CHOOSE(DATA_SET,E103,F103,G103) -> 0 | I103: SEPTIC_QTY
B104: Septic tank – cost each | C104: የአንዱ ዋጋ | D104: ETB | E104: 450000 | F104: 450000 | G104: 450000 | H104: =CHOOSE(DATA_SET,E104,F104,G104) -> 450000 | I104: SEPTIC_RATE
B105: Water tanks? | C105: የውሃ ታንከር? | D105: Y/N | E105: No | F105: Yes | G105: Yes | H105: =IF(CHOOSE(DATA_SET,E105,F105,G105)="Yes",1,0) -> 1 | I105: WTANK_YN
B106: Water tanks – number | C106: የውሃ ታንከር ብዛት | D106: no. | E106: 0 | F106: 2 | G106: 4 | H106: =CHOOSE(DATA_SET,E106,F106,G106) -> 4 | I106: WTANK_QTY
B107: Water tank – cost each (incl. stand, pump) | C107: የአንዱ ዋጋ | D107: ETB | E107: 60000 | F107: 60000 | G107: 250000 | H107: =CHOOSE(DATA_SET,E107,F107,G107) -> 250000 | I107: WTANK_RATE
B108: Paving / landscaping area | C108: የንጣፍ / የአትክልት ስፋት | D108: m² | E108: 0 | F108: 80 | G108: 250 | H108: =CHOOSE(DATA_SET,E108,F108,G108) -> 250 | I108: EXT_M2
B109: Paving / landscaping rate | C109: የንጣፍ ዋጋ በካሬ | D109: ETB/m² | E109: 3500 | F109: 3500 | G109: 4500 | H109: =CHOOSE(DATA_SET,E109,F109,G109) -> 4500 | I109: EXT_RATE
...

Sheet 11_Scenarios
B1: 11 · Scenarios – Base / Upside / Downside / Lender | J1: =HYPERLINK("#'00_Start'!A1","◂ Start") -> ◂ Start
B2: ሁኔታዎች – መሠረታዊ፣ ብሩህ፣ አስቸጋሪ፣ ባንክ
B3: =PROJ_NAME&" | Scenario: "&SCEN_NAME&" | Mode: "&MODE_NAME -> SAMPLE B — B+G+8 mixed-use building, Addis Ababa | Scenario: Base | Mode: 3 Mixed
B10: Scenario adjustments (applied on top of the Inputs). Active = CHOOSE(SCEN, Base, Upside, Downside, Lender) | C10: የሁኔታ ማስተካከያዎች
B11: Driver | C11: ነጂ | D11: Unit | E11: Base | F11: Upside | G11: Downside | H11: Lender | I11: ACTIVE | J11: Name
B12: Sale price | C12: የሽያጭ ዋጋ | D12: % | E12: 0 | F12: 0.1 | G12: -0.1 | H12: -0.15 | I12: =CHOOSE(SCEN,E12,F12,G12,H12) -> 0 | J12: SC_PRICE
B13: Rent | C13: ኪራይ | D13: % | E13: 0 | F13: 0.1 | G13: -0.1 | H13: -0.15 | I13: =CHOOSE(SCEN,E13,F13,G13,H13) -> 0 | J13: SC_RENT
B14: Occupancy (points) | C14: የተያዘ መጠን | D14: pts | E14: 0 | F14: 0.03 | G14: -0.1 | H14: -0.15 | I14: =CHOOSE(SCEN,E14,F14,G14,H14) -> 0 | J14: SC_OCC
B15: Construction cost | C15: የግንባታ ወጪ | D15: % | E15: 0 | F15: -0.05 | G15: 0.1 | H15: 0.15 | I15: =CHOOSE(SCEN,E15,F15,G15,H15) -> 0 | J15: SC_COST
B16: Construction delay | C16: የግንባታ መዘግየት | D16: months | E16: 0 | F16: 0 | G16: 6 | H16: 6 | I16: =CHOOSE(SCEN,E16,F16,G16,H16) -> 0 | J16: SC_DELAY
B17: Interest rate (points) | C17: የወለድ መጠን | D17: pts | E17: 0 | F17: -0.01 | G17: 0.02 | H17: 0.03 | I17: =CHOOSE(SCEN,E17,F17,G17,H17) -> 0 | J17: SC_RATE
B18: Presales achieved | C18: ቅድመ-ሽያጭ | D18: % | E18: 0 | F18: 0.1 | G18: -0.25 | H18: -0.4 | I18: =CHOOSE(SCEN,E18,F18,G18,H18) -> 0 | J18: SC_PRESALE
B19: Exit cap rate (points) | C19: የመውጫ ካፕ ሬት | D19: pts | E19: 0 | F19: -0.005 | G19: 0.01 | H19: 0.015 | I19: =CHOOSE(SCEN,E19,F19,G19,H19) -> 0 | J19: SC_EXITCAP
B20: Operating costs | C20: የሥራ ማስኬጃ ወጪ | D20: % | E20: 0 | F20: -0.05 | G20: 0.1 | H20: 0.15 | I20: =CHOOSE(SCEN,E20,F20,G20,H20) -> 0 | J20: SC_OPEX
B21: Cost escalation (points) | C21: የዋጋ ጭማሪ | D21: pts | E21: 0 | F21: -0.02 | G21: 0.05 | H21: 0.05 | I21: =CHOOSE(SCEN,E21,F21,G21,H21) -> 0 | J21: SC_ESC
B22: Rent escalation (points) | C22: የኪራይ ጭማሪ | D22: pts | E22: 0 | F22: 0.01 | G22: -0.02 | H22: -0.03 | I22: =CHOOSE(SCEN,E22,F22,G22,H22) -> 0 | J22: SC_RESC
B23: Sale price escalation (points) | C23: የሽያጭ ዋጋ ጭማሪ | D23: pts | E23: 0 | F23: 0.02 | G23: -0.03 | H23: -0.05 | I23: =CHOOSE(SCEN,E23,F23,G23,H23) -> 0 | J23: SC_PESC
... B26: Sales absorption speed | C26: የሽያጭ ፍጥነት | D26: % | E26: 0 | F26: 0.2 | G26: -0.3 | H26: -0.5 | I26: =CHOOSE(SCEN,E26,F26,G26,H26) -> 0 | J26: SC_ABS
B28: Effective drivers used by the engine (scenario × flex cell) | C28: ሞዴሉ የሚጠቀማቸው ውጤታማ ነጂዎች
B29: Active scenario (1–4) | D29: =IF(SCEN_OVR>0,SCEN_OVR,SCEN_SEL) -> 1
B30: Sale price factor | D30: =(1+SC_PRICE)*FLX_PRICE -> 1
B31: Rent factor | D31: =(1+SC_RENT)*FLX_RENT -> 1
B32: Construction cost factor | D32: =(1+SC_COST)*FLX_COST -> 1
B33: Opex factor | D33: =(1+SC_OPEX)*FLX_OPEX -> 1
B34: Occupancy points added | D34: =SC_OCC -> 0
B35: Occupancy factor | D35: =FLX_OCC -> 1
B36: Interest rate points added | D36: =SC_RATE -> 0
B37: Interest rate factor | D37: =FLX_RATE -> 1
B38: Effective base interest rate | D38: =MAX(0,(RATE+D_RATE_ADD)*D_RATE_F) -> 0.15
B39: Effective construction months (incl. delay) | D39: =MAX(1,MIN(48,ROUND(CONSTR_M+SC_DELAY+FLX_DELAY,0))) -> 30
B40: Presale factor | D40: =MAX(0,1+SC_PRESALE) -> 1
B41: Effective exit cap rate | D41: =MAX(0.001,EXIT_CAP+SC_EXITCAP) -> 0.09
B42: Effective cost escalation | D42: =ESC_PA+SC_ESC -> 0.15
B43: Effective rent escalation | D43: =RENT_ESC+SC_RESC -> 0.08
B44: Effective sale-price escalation | D44: =PRICE_ESC+SC_PESC -> 0.1
B45: Effective default allowance | D45: =MIN(1,MAX(0,DEFAULT_PCT+SC_DEFAULT)) -> 0.02
B46: Effective project discount rate | D46: =DISC+SC_DISC -> 0.18
B47: Effective cost of equity | D47: =COE+SC_DISC -> 0.22
B48: Absorption factor | D48: =MAX(0,1+SC_ABS) -> 1

Sheet 12_TaxLaw
B1: 12 · Tax law register | G1: =HYPERLINK("#'00_Start'!A1","◂ Start") -> ◂ Start
B2: የግብር ሕግ መዝገብ
B3: =PROJ_NAME&" | Scenario: "&SCEN_NAME&" | Mode: "&MODE_NAME -> SAMPLE B — B+G+8 mixed-use building, Addis Ababa | Scenario: Base | Mode: 3 Mixed
B10: Rates used by the model and their statutory source – YOU MUST CONFIRM CURRENT RATES BEFORE USE | C10: የግብር መጣኔዎች
B11: Item | C11: Rate used | D11: Statutory source | E11: Last verified | F11: Verify before use | G11: Model name
B12: Corporate income tax | C12: =CIT -> 0.3 | D12: Federal Income Tax Proclamation No. 979/2016, Art. 19(1) – 30% for bodies | E12: 46300 | F12: YES – verify | G12: CIT
B13: Tax depreciation – buildings | C13: =TAXDEP_BLD -> 0.05 | D13: Proc. 979/2016, Art. 25 & Income Tax Regulation No. 410/2017 – buildings 5% straight line | E13: 46300 | F13: YES – verify | G13: TAXDEP_BLD
B14: Tax depreciation – plant & equipment | C14: =TAXDEP_PLANT -> 0.2 | D14: Proc. 979/2016, Art. 25 – other business assets 20% (pool / diminishing value per spec) | E14: 46300 | F14: YES – verify | G14: TAXDEP_PLANT
B15: Loss carry-forward period | C15: =LCF_YEARS -> 5 | D15: Proc. 979/2016, Art. 26 – losses carried forward up to 5 years (limits on number of carry-forwards apply) | E15: 46300 | F15: YES – verify | G15: LCF_YEARS
B16: Loss offset cap | C16: =LCF_CAP -> 1 | D16: Model assumption – no statutory cap identified; set below 100% if a cap applies | E16: 46300 | F16: YES – verify | G16: LCF_CAP
B17: VAT – standard rate | C17: =VAT_R -> 0.15 | D17: Value Added Tax Proclamation No. 1341/2024 – 15% standard rate | E17: 46300 | F17: YES – verify | G17: VAT_R
B18: VAT on sale of buildings (share taxable) | C18: =VAT_SALES_PCT -> 0 | D18: Proc. 1341/2024 – exemptions for residential dwellings; confirm treatment of new-build sales | E18: 46300 | F18: YES – verify | G18: VAT_SALES_PCT
B19: VAT on rent (share taxable) | C19: =RENT_VAT_PCT -> 1 | D19: Proc. 1341/2024 – residential rent exempt; commercial rent taxable | E19: 46300 | F19: YES – verify | G19: RENT_VAT_PCT
B20: Undistributed profits tax | C20: =UPT_R -> 0.1 | D20: Proc. 979/2016, Art. 55 – undistributed / non-reinvested profits treated as dividend (10%) | E20: 46300 | F20: YES – verify | G20: UPT_R
B21: Dividend withholding tax | C21: =DIV_WHT -> 0.1 | D21: Proc. 979/2016, Art. 55 – 10% on dividends | E21: 46300 | F21: YES – verify | G21: DIV_WHT
B22: Legal reserve transfer | C22: =LR_PCT -> 0.05 | D22: Commercial Code of Ethiopia, Proc. No. 1243/2021, Art. 434 – 5% of profits | E22: 46300 | F22: YES – verify | G22: LR_PCT
B23: Legal reserve cap | C23: =LR_CAP -> 0.1 | D23: Commercial Code, Art. 434 – until reserve reaches 10% of capital | E23: 46300 | F23: YES – verify | G23: LR_CAP
B24: Property tax | C24: =PROPTAX_PCT -> 0.001 | D24: City property-tax proclamation (Addis Ababa) – rate and base to be confirmed | E24: 46300 | F24: YES – verify | G24: PROPTAX_PCT
B25: Land lease down payment | C25: =LEASE_DP -> 0.1 | D25: Urban Lands Lease Holding Proclamation No. 721/2011 and city regulations – minimum down payment | E25: 46300 | F25: YES – verify | G25: LEASE_DP
B26: Land lease instalment period | C26: =LEASE_N -> 30 | D26: Proc. 721/2011 – instalment period per lease contract | E26: 46300 | F26: YES – verify | G26: LEASE_N
B27: Interest on unpaid lease | C27: =LEASE_INT -> 0.07 | D27: Lease contract / city regulation – usually linked to the NBE / bank lending rate | E27: 46300 | F27: YES – verify | G27: LEASE_INT
B29: Note: 'Last verified' records a desk review on that date, not confirmation against the official gazette. Tax law in Ethiopia changes frequently – confirm every rate with the Ministry of Revenue, the city administration or a licensed tax adviser before relying on results.
B30: ማሳሰቢያ፡ ሞዴሉን ከመጠቀምዎ በፊት ሁሉንም የግብር መጣኔዎች ከገቢዎች ሚኒስቴር ወይም ፈቃድ ካለው የግብር አማካሪ ያረጋግጡ።

Sheet 20_Timeline
B1: 20 · Timeline & flags | R1: =HYPERLINK("#'00_Start'!A1","◂ Start") -> ◂ Start
B2: የጊዜ ሰሌዳና ጠቋሚዎች
B3: =PROJ_NAME&" | Scenario: "&SCEN_NAME&" | Mode: "&MODE_NAME -> SAMPLE B — B+G+8 mixed-use building, Addis Ababa | Scenario: Base | Mode: 3 Mixed
B6: Period | D6: Total | E6: =E12 -> C1 | F6: =F12 -> C2 | G6: =G12 -> C3 | H6: =H12 -> C4 | I6: =I12 -> O1 | J6: =J12 -> O2 | K6: =K12 -> O3 | L6: =L12 -> O4 | ... R6: =R12 -> O10
B7: Period end (Gregorian) | E7: =E22 -> 46752 | F7: =F22 -> 47118 | G7: =G22 -> 47299 | H7: =H22 -> 47299 | I7: =I22 -> 47664 | J7: =J22 -> 48029 | K7: =K22 -> 48395 | L7: =L22 -> 48760 | ... R7: =R22 -> 50951
B8: Ethiopian calendar year | E8: =E26 -> EC 2020 | F8: =F26 -> EC 2021 | G8: =G26 -> EC 2021 | H8: =H26 -> EC 2021 | I8: =I26 -> EC 2022 | J8: =J26 -> EC 2023 | K8: =K26 -> EC 2024 | L8: =L26 -> EC 2025 | ... R8: =R26 -> EC 2031
B10: Annual periods: C1–C4 construction years, O1–O10 operating years | C10: ዓመታዊ ጊዜያት
B11: Period number | C11: no. | E11: 1 | F11: 2 | G11: 3 | H11: 4 | I11: 5 | J11: 6 | K11: 7 | L11: 8 | M11: 9 | N11: 10 | O11: 11 | P11: 12 | Q11: 13 | R11: 14
B12: Period label | E12: C1 | F12: C2 | G12: C3 | H12: C4 | I12: O1 | J12: O2 | K12: O3 | L12: O4 | M12: O5 | N12: O6 | O12: O7 | P12: O8 | Q12: O9 | R12: O10
B13: Construction-year index | C13: no. | E13: 1 | F13: 2 | G13: 3 | H13: 4 | I13: 0 | J13: 0 | K13: 0 | L13: 0 | M13: 0 | N13: 0 | O13: 0 | P13: 0 | Q13: 0 | R13: 0
B14: Operating-year index | C14: no. | E14: 0 | F14: 0 | G14: 0 | H14: 0 | I14: 1 | J14: 2 | K14: 3 | L14: 4 | M14: 5 | N14: 6 | O14: 7 | P14: 8 | Q14: 9 | R14: 10
B15: Months in period | C15: months | D15: =SUM(E15:R15) -> 150 | E15: =MAX(0,MIN(12,CONSTR_EFF-12*(E13-1))) -> 12 | F15: =MAX(0,MIN(12,CONSTR_EFF-12*(F13-1))) -> 12 | G15: =MAX(0,MIN(12,CONSTR_EFF-12*(G13-1))) -> 6 | H15: =MAX(0,MIN(12,CONSTR_EFF-12*(H13-1))) -> 0 | I15: 12 | J15: 12 | K15: 12 | L15: 12 | M15: 12 | N15: 12 | O15: 12 | P15: 12 | Q15: 12 | R15: 12
B16: Period active flag | C16: flag | E16: =IF(E15>0,1,0) -> 1 | F16: =IF(F15>0,1,0) -> 1 | G16: =IF(G15>0,1,0) -> 1 | H16: =IF(H15>0,1,0) -> 0 | I16: =IF(I15>0,1,0) -> 1 | J16: =IF(J15>0,1,0) -> 1 | K16: =IF(K15>0,1,0) -> 1 | L16: =IF(L15>0,1,0) -> 1 | ... R16: =IF(R15>0,1,0) -> 1
B17: Construction flag | C17: flag | D17: =SUM(E17:R17) -> 3 | E17: =IF(AND(E13>0,E15>0),1,0) -> 1 | F17: =IF(AND(F13>0,F15>0),1,0) -> 1 | G17: =IF(AND(G13>0,G15>0),1,0) -> 1 | H17: =IF(AND(H13>0,H15>0),1,0) -> 0 | I17: 0 | J17: 0 | K17: 0 | L17: 0 | M17: 0 | N17: 0 | O17: 0 | P17: 0 | Q17: 0 | R17: 0
B18: Operating flag | C18: flag | D18: =SUM(E18:R18) -> 10 | E18: =IF(AND(E14>=1,E14<=OPS_YEARS),1,0) -> 0 | F18: =IF(AND(F14>=1,F14<=OPS_YEARS),1,0) -> 0 | G18: =IF(AND(G14>=1,G14<=OPS_YEARS),1,0) -> 0 | H18: =IF(AND(H14>=1,H14<=OPS_YEARS),1,0) -> 0 | I18: =IF(AND(I14>=1,I14<=OPS_YEARS),1,0) -> 1 | J18: =IF(AND(J14>=1,J14<=OPS_YEARS),1,0) -> 1 | K18: =IF(AND(K14>=1,K14<=OPS_YEARS),1,0) -> 1 | L18: =IF(AND(L14>=1,L14<=OPS_YEARS),1,0) -> 1 | ... R18: =IF(AND(R14>=1,R14<=OPS_YEARS),1,0) -> 1
B19: Completion (COD) period flag | C19: flag | D19: =SUM(E19:R19) -> 1 | E19: =IF(AND(E15>0,MIN(12*E13,CONSTR_EFF)=CONSTR_EFF),1,0) -> 0 | F19: =IF(AND(F15>0,MIN(12*F13,CONSTR_EFF)=CONSTR_EFF),1,0) -> 0 | G19: =IF(AND(G15>0,MIN(12*G13,CONSTR_EFF)=CONSTR_EFF),1,0) -> 1 | H19: =IF(AND(H15>0,MIN(12*H13,CONSTR_EFF)=CONSTR_EFF),1,0) -> 0 | I19: 0 | J19: 0 | K19: 0 | L19: 0 | M19: 0 | N19: 0 | O19: 0 | P19: 0 | Q19: 0 | R19: 0
B20: First month index | C20: no. | E20: =12*(E13-1)+1 -> 1 | F20: =12*(F13-1)+1 -> 13 | G20: =12*(G13-1)+1 -> 25 | H20: =12*(H13-1)+1 -> 37 | I20: =CONSTR_EFF+12*(I14-1)+1 -> 31 | J20: =CONSTR_EFF+12*(J14-1)+1 -> 43 | K20: =CONSTR_EFF+12*(K14-1)+1 -> 55 | L20: =CONSTR_EFF+12*(L14-1)+1 -> 67 | M20: =CONSTR_EFF+12*(M14-1)+1 -> 79 | N20: =CONSTR_EFF+12*(N14-1)+1 -> 91 | O20: =CONSTR_EFF+12*(O14-1)+1 -> 103 | P20: =CONSTR_EFF+12*(P14-1)+1 -> 115 | ... R20: =CONSTR_EFF+12*(R14-1)+1 -> 139
B21: Last month index | C21: no. | E21: =MIN(12*E13,CONSTR_EFF) -> 12 | F21: =MIN(12*F13,CONSTR_EFF) -> 24 | G21: =MIN(12*G13,CONSTR_EFF) -> 30 | H21: =MIN(12*H13,CONSTR_EFF) -> 30 | I21: =CONSTR_EFF+12*I14 -> 42 | J21: =CONSTR_EFF+12*J14 -> 54 | K21: =CONSTR_EFF+12*K14 -> 66 | L21: =CONSTR_EFF+12*L14 -> 78 | M21: =CONSTR_EFF+12*M14 -> 90 | N21: =CONSTR_EFF+12*N14 -> 102 | O21: =CONSTR_EFF+12*O14 -> 114 | P21: =CONSTR_EFF+12*P14 -> 126 | ... R21: =CONSTR_EFF+12*R14 -> 150
B22: Period end date | C22: date | E22: =EDATE(START_DATE,E21)-1 -> 46752 | F22: =EDATE(START_DATE,F21)-1 -> 47118 | G22: =EDATE(START_DATE,G21)-1 -> 47299 | H22: =EDATE(START_DATE,H21)-1 -> 47299 | I22: =EDATE(START_DATE,I21)-1 -> 47664 | J22: =EDATE(START_DATE,J21)-1 -> 48029 | K22: =EDATE(START_DATE,K21)-1 -> 48395 | L22: =EDATE(START_DATE,L21)-1 -> 48760 | ... R22: =EDATE(START_DATE,R21)-1 -> 50951
B23: Years from start (end of period) | C23: years | E23: =(E22+1-START_DATE)/365 -> 1 | F23: =(F22+1-START_DATE)/365 -> 2.0027397 | G23: =(G22+1-START_DATE)/365 -> 2.4986301 | H23: =(H22+1-START_DATE)/365 -> 2.4986301 | I23: =(I22+1-START_DATE)/365 -> 3.4986301 | J23: =(J22+1-START_DATE)/365 -> 4.4986301 | K23: =(K22+1-START_DATE)/365 -> 5.5013699 | L23: =(L22+1-START_DATE)/365 -> 6.5013699 | ... R23: =(R22+1-START_DATE)/365 -> 12.50411
B24: Period length | C24: years | D24: =SUM(E24:R24) -> 12.5 | E24: =E15/12 -> 1 | F24: =F15/12 -> 1 | G24: =G15/12 -> 0.5 | H24: =H15/12 -> 0 | I24: =I15/12 -> 1 | J24: =J15/12 -> 1 | K24: =K15/12 -> 1 | L24: =L15/12 -> 1 | ... R24: =R15/12 -> 1
B25: Gregorian year (period end) | E25: ="GC "&YEAR(E22) -> GC 2027 | F25: ="GC "&YEAR(F22) -> GC 2028 | G25: ="GC "&YEAR(G22) -> GC 2029 | H25: ="GC "&YEAR(H22) -> GC 2029 | I25: ="GC "&YEAR(I22) -> GC 2030 | J25: ="GC "&YEAR(J22) -> GC 2031 | K25: ="GC "&YEAR(K22) -> GC 2032 | L25: ="GC "&YEAR(L22) -> GC 2033 | ... R25: ="GC "&YEAR(R22) -> GC 2039
B26: Ethiopian calendar year (period end) | E26: ="EC "&(YEAR(E22)-8+IF(E22>=DATE(YEAR(E22),9,11),1,0)) -> EC 2020 | F26: ="EC "&(YEAR(F22)-8+IF(F22>=DATE(YEAR(F22),9,11),1,0)) -> EC 2021 | G26: ="EC "&(YEAR(G22)-8+IF(G22>=DATE(YEAR(G22),9,11),1,0)) -> EC 2021 | H26: ="EC "&(YEAR(H22)-8+IF(H22>=DATE(YEAR(H22),9,11),1,0)) -> EC 2021 | I26: ="EC "&(YEAR(I22)-8+IF(I22>=DATE(YEAR(I22),9,11),1,0)) -> EC 2022 | J26: ="EC "&(YEAR(J22)-8+IF(J22>=DATE(YEAR(J22),9,11),1,0)) -> EC 2023 | K26: ="EC "&(YEAR(K22)-8+IF(K22>=DATE(YEAR(K22),9,11),1,0)) -> EC 2024 | L26: ="EC "&(YEAR(L22)-8+IF(L22>=DATE(YEAR(L22),9,11),1,0)) -> EC 2025 | ... R26: ="EC "&(YEAR(R22)-8+IF(R22>=DATE(YEAR(R22),9,11),1,0)) -> EC 2031
B27: Discount factor @ project rate | C27: x | E27: =(1+DISC_EFF)^(-E23) -> 0.84745763 | F27: =(1+DISC_EFF)^(-F23) -> 0.71785883 | G27: =(1+DISC_EFF)^(-G23) -> 0.66129228 | H27: =(1+DISC_EFF)^(-H23) -> 0.66129228 | I27: =(1+DISC_EFF)^(-I23) -> 0.56041718 | J27: =(1+DISC_EFF)^(-J23) -> 0.47492982 | K27: =(1+DISC_EFF)^(-K23) -> 0.40230042 | L27: =(1+DISC_EFF)^(-L23) -> 0.34093256 | ... R27: =(1+DISC_EFF)^(-R23) -> 0.12623492
B28: Discount factor @ cost of equity | C28: x | E28: =(1+COE_EFF)^(-E23) -> 0.81967213 | F28: =(1+COE_EFF)^(-F23) -> 0.67149647 | G28: =(1+COE_EFF)^(-G23) -> 0.60844135 | H28: =(1+COE_EFF)^(-H23) -> 0.60844135 | I28: =(1+COE_EFF)^(-I23) -> 0.49872242 | J28: =(1+COE_EFF)^(-J23) -> 0.40878887 | K28: =(1+COE_EFF)^(-K23) -> 0.33489035 | L28: =(1+COE_EFF)^(-L23) -> 0.27450028 | ... R28: =(1+COE_EFF)^(-R23) -> 0.083204576
B30: Key timing scalars | C30: ቁልፍ የጊዜ መረጃዎች
B31: Operating horizon (fixed design horizon) | C31: years | D31: 10 | E31: Statements always show C1–C4 + O1–O10
B32: Number of construction periods used | C32: no. | D32: =ROUNDUP(CONSTR_EFF/12,0) -> 3
B33: Completion (COD) date | C33: date | D33: =EDATE(START_DATE,CONSTR_EFF)-1 -> 47299
B34: End of operating horizon (O10) | C34: date | D34: =EDATE(START_DATE,CONSTR_EFF+12*OPS_YEARS)-1 -> 50951
B36: Monthly timeline (construction up to 48 months + 240 months of loan life) | C36: ወርሃዊ የጊዜ ሰሌዳ
B37: Month index t | C37: no. | E37: 1 | F37: 2 | G37: 3 | H37: 4 | I37: 5 | J37: 6 | K37: 7 | L37: 8 | M37: 9 | N37: 10 | O37: 11 | P37: 12 | Q37: 13 | R37: 14 | S37: 15 | T37: 16 | U37: 17 | V37: 18 | W37: 19 | X37: 20 | Y37: 21 | Z37: 22 | AA37: 23 | AB37: 24 | AC37: 25 | AD37: 26 | AE37: 27 | AF37: 28 | AG37: 29 | AH37: 30 | AI37: 31 | AJ37: 32 | AK37: 33 | AL37: 34 | AM37: 35 | AN37: 36 | AO37: 37 | AP37: 38 | AQ37: 39 | AR37: 40 | AS37: 41 | AT37: 42 | AU37: 43 | AV37: 44 | AW37: 45 | AX37: 46 | AY37: 47 | AZ37: 48 | BA37: 49 | BB37: 50 | BC37: 51 | BD37: 52 | BE37: 53 | BF37: 54 | BG37: 55 | BH37: 56 | BI37: 57 | BJ37: 58 | BK37: 59 | BL37: 60 | BM37: 61 | BN37: 62 | BO37: 63 | BP37: 64 | BQ37: 65 | BR37: 66 | BS37: 67 | BT37: 68 | BU37: 69 | BV37: 70 | BW37: 71 | BX37: 72 | BY37: 73 | BZ37: 74 | CA37: 75 | CB37: 76 | CC37: 77 | CD37: 78 | CE37: 79 | CF37: 80 | CG37: 81 | CH37: 82 | CI37: 83 | CJ37: 84 | CK37: 85 | CL37: 86 | CM37: 87 | CN37: 88 | CO37: 89 | CP37: 90 | CQ37: 91 | CR37: 92 | CS37: 93 | CT37: 94 | CU37: 95 | CV37: 96 | CW37: 97 | CX37: 98 | CY37: 99 | CZ37: 100 | DA37: 101 | DB37: 102 | DC37: 103 | DD37: 104 | DE37: 105 | DF37: 106 | DG37: 107 | DH37: 108 | DI37: 109 | DJ37: 110 | DK37: 111 | DL37: 112 | DM37: 113 | DN37: 114 | DO37: 115 | DP37: 116 | DQ37: 117 | DR37: 118 | DS37: 119 | DT37: 120 | DU37: 121 | DV37: 122 | DW37: 123 | DX37: 124 | DY37: 125 | DZ37: 126 | EA37: 127 | EB37: 128 | EC37: 129 | ED37: 130 | EE37: 131 | EF37: 132 | EG37: 133 | EH37: 134 | EI37: 135 | EJ37: 136 | EK37: 137 | EL37: 138 | EM37: 139 | EN37: 140 | EO37: 141 | EP37: 142 | EQ37: 143 | ER37: 144 | ES37: 145 | ET37: 146 | EU37: 147 | EV37: 148 | EW37: 149 | EX37: 150 | EY37: 151 | EZ37: 152 | FA37: 153 | FB37: 154 | FC37: 155 | FD37: 156 | FE37: 157 | FF37: 158 | FG37: 159 | FH37: 160 | FI37: 161 | FJ37: 162 | FK37: 163 | FL37: 164 | FM37: 165 | FN37: 166 | FO37: 167 | FP37: 168 | FQ37: 169 | FR37: 170 | FS37: 171 | FT37: 172 | FU37: 173 | FV37: 174 | FW37: 175 | FX37: 176 | FY37: 177 | FZ37: 178 | GA37: 179 | GB37: 180 | GC37: 181 | GD37: 182 | GE37: 183 | GF37: 184 | GG37: 185 | GH37: 186 | GI37: 187 | GJ37: 188 | GK37: 189 | GL37: 190 | GM37: 191 | GN37: 192 | GO37: 193 | GP37: 194 | GQ37: 195 | GR37: 196 | GS37: 197 | GT37: 198 | GU37: 199 | GV37: 200 | GW37: 201 | GX37: 202 | GY37: 203 | GZ37: 204 | HA37: 205 | HB37: 206 | HC37: 207 | HD37: 208 | HE37: 209 | HF37: 210 | HG37: 211 | HH37: 212 | HI37: 213 | HJ37: 214 | HK37: 215 | HL37: 216 | HM37: 217 | HN37: 218 | HO37: 219 | HP37: 220 | HQ37: 221 | HR37: 222 | HS37: 223 | HT37: 224 | HU37: 225 | HV37: 226 | HW37: 227 | HX37: 228 | HY37: 229 | HZ37: 230 | IA37: 231 | IB37: 232 | IC37: 233 | ID37: 234 | IE37: 235 | IF37: 236 | IG37: 237 | IH37: 238 | II37: 239 | IJ37: 240 | IK37: 241 | IL37: 242 | IM37: 243 | IN37: 244 | IO37: 245 | IP37: 246 | IQ37: 247 | IR37: 248 | IS37: 249 | IT37: 250 | IU37: 251 | IV37: 252 | IW37: 253 | IX37: 254 | IY37: 255 | IZ37: 256 | JA37: 257 | JB37: 258 | JC37: 259 | JD37: 260 | JE37: 261 | JF37: 262 | JG37: 263 | JH37: 264 | JI37: 265 | JJ37: 266 | JK37: 267 | JL37: 268 | JM37: 269 | JN37: 270 | JO37: 271 | JP37: 272 | JQ37: 273 | JR37: 274 | JS37: 275 | JT37: 276 | JU37: 277 | JV37: 278 | JW37: 279 | JX37: 280 | JY37: 281 | JZ37: 282 | KA37: 283 | KB37: 284 | KC37: 285 | KD37: 286 | KE37: 287 | KF37: 288
B38: Month start date | C38: date | E38: =EDATE(START_DATE,E37-1) -> 46388 | F38: =EDATE(START_DATE,F37-1) -> 46419 | G38: =EDATE(START_DATE,G37-1) -> 46447 | H38: =EDATE(START_DATE,H37-1) -> 46478 | I38: =EDATE(START_DATE,I37-1) -> 46508 | J38: =EDATE(START_DATE,J37-1) -> 46539 | K38: =EDATE(START_DATE,K37-1) -> 46569 | L38: =EDATE(START_DATE,L37-1) -> 46600 | ... KF38: =EDATE(START_DATE,KF37-1) -> 55123
B39: Construction month flag | C39: flag | D39: =SUM(E39:KF39) -> 30 | E39: =IF(E37<=CONSTR_EFF,1,0) -> 1 | F39: =IF(F37<=CONSTR_EFF,1,0) -> 1 | G39: =IF(G37<=CONSTR_EFF,1,0) -> 1 | H39: =IF(H37<=CONSTR_EFF,1,0) -> 1 | I39: =IF(I37<=CONSTR_EFF,1,0) -> 1 | J39: =IF(J37<=CONSTR_EFF,1,0) -> 1 | K39: =IF(K37<=CONSTR_EFF,1,0) -> 1 | L39: =IF(L37<=CONSTR_EFF,1,0) -> 1 | ... KF39: =IF(KF37<=CONSTR_EFF,1,0) -> 0
B40: Months after completion k | C40: no. | E40: =E37-CONSTR_EFF -> -29 | F40: =F37-CONSTR_EFF -> -28 | G40: =G37-CONSTR_EFF -> -27 | H40: =H37-CONSTR_EFF -> -26 | I40: =I37-CONSTR_EFF -> -25 | J40: =J37-CONSTR_EFF -> -24 | K40: =K37-CONSTR_EFF -> -23 | L40: =L37-CONSTR_EFF -> -22 | ... KF40: =KF37-CONSTR_EFF -> 258
B41: Operating year (within O1–O10) | C41: no. | E41: =IF(AND(E40>=1,E40<=12*OPS_YEARS),ROUNDUP(E40/12,0),0) -> 0 | F41: =IF(AND(F40>=1,F40<=12*OPS_YEARS),ROUNDUP(F40/12,0),0) -> 0 | G41: =IF(AND(G40>=1,G40<=12*OPS_YEARS),ROUNDUP(G40/12,0),0) -> 0 | H41: =IF(AND(H40>=1,H40<=12*OPS_YEARS),ROUNDUP(H40/12,0),0) -> 0 | I41: =IF(AND(I40>=1,I40<=12*OPS_YEARS),ROUNDUP(I40/12,0),0) -> 0 | J41: =IF(AND(J40>=1,J40<=12*OPS_YEARS),ROUNDUP(J40/12,0),0) -> 0 | K41: =IF(AND(K40>=1,K40<=12*OPS_YEARS),ROUNDUP(K40/12,0),0) -> 0 | L41: =IF(AND(L40>=1,L40<=12*OPS_YEARS),ROUNDUP(L40/12,0),0) -> 0 | ... KF41: =IF(AND(KF40>=1,KF40<=12*OPS_YEARS),ROUNDUP(KF40/12,0),0) -> 0
B42: Loan year after completion | C42: no. | E42: =IF(E40>=1,ROUNDUP(E40/12,0),0) -> 0 | F42: =IF(F40>=1,ROUNDUP(F40/12,0),0) -> 0 | G42: =IF(G40>=1,ROUNDUP(G40/12,0),0) -> 0 | H42: =IF(H40>=1,ROUNDUP(H40/12,0),0) -> 0 | I42: =IF(I40>=1,ROUNDUP(I40/12,0),0) -> 0 | J42: =IF(J40>=1,ROUNDUP(J40/12,0),0) -> 0 | K42: =IF(K40>=1,ROUNDUP(K40/12,0),0) -> 0 | L42: =IF(L40>=1,ROUNDUP(L40/12,0),0) -> 0 | ... KF42: =IF(KF40>=1,ROUNDUP(KF40/12,0),0) -> 22
B43: Annual period index (1–14, 0 = beyond horizon) | C43: no. | E43: =IF(E37<=CONSTR_EFF,ROUNDUP(E37/12,0),IF(E41>0,4+E41,0)) -> 1 | F43: =IF(F37<=CONSTR_EFF,ROUNDUP(F37/12,0),IF(F41>0,4+F41,0)) -> 1 | G43: =IF(G37<=CONSTR_EFF,ROUNDUP(G37/12,0),IF(G41>0,4+G41,0)) -> 1 | H43: =IF(H37<=CONSTR_EFF,ROUNDUP(H37/12,0),IF(H41>0,4+H41,0)) -> 1 | I43: =IF(I37<=CONSTR_EFF,ROUNDUP(I37/12,0),IF(I41>0,4+I41,0)) -> 1 | J43: =IF(J37<=CONSTR_EFF,ROUNDUP(J37/12,0),IF(J41>0,4+J41,0)) -> 1 | K43: =IF(K37<=CONSTR_EFF,ROUNDUP(K37/12,0),IF(K41>0,4+K41,0)) -> 1 | L43: =IF(L37<=CONSTR_EFF,ROUNDUP(L37/12,0),IF(L41>0,4+L41,0)) -> 1 | ... KF43: =IF(KF37<=CONSTR_EFF,ROUNDUP(KF37/12,0),IF(KF41>0,4+KF41,0)) -> 0

Sheet 21_Area
B1: 21 · Area programme | T1: =HYPERLINK("#'00_Start'!A1","◂ Start") -> ◂ Start
B2: የቦታና የወለል ስፋት ፕሮግራም
B3: =PROJ_NAME&" | Scenario: "&SCEN_NAME&" | Mode: "&MODE_NAME -> SAMPLE B — B+G+8 mixed-use building, Addis Ababa | Scenario: Base | Mode: 3 Mixed
B10: Floors (from Inputs block 3) | C10: ፎቆች
B11: Floor | E11: Basement 2 | F11: Basement 1 | G11: Ground floor | H11: Floor 1 | I11: Floor 2 | J11: Floor 3 | K11: Floor 4 | L11: Floor 5 | M11: Floor 6 | N11: Floor 7 | O11: Floor 8 | P11: Floor 9 | Q11: Floor 10 | R11: Floor 11 | S11: Floor 12 | T11: Floor 13
B12: Gross floor area | C12: m² | D12: =SUM(E12:T12) -> 6400 | E12: =FL_A1 -> 0 | F12: =FL_A2 -> 900 | G12: =FL_A3 -> 650 | H12: =FL_A4 -> 650 | I12: =FL_A5 -> 600 | J12: =FL_A6 -> 600 | K12: =FL_A7 -> 600 | L12: =FL_A8 -> 600 | M12: =FL_A9 -> 600 | N12: =FL_A10 -> 600 | O12: =FL_A11 -> 600 | P12: =FL_A12 -> 0 | Q12: =FL_A13 -> 0 | R12: =FL_A14 -> 0 | S12: =FL_A15 -> 0 | T12: =FL_A16 -> 0
B13: Use | E13: =FL_U1 -> Parking | F13: =FL_U2 -> Parking | G13: =FL_U3 -> Retail | H13: =FL_U4 -> Retail | I13: =FL_U5 -> Residential | J13: =FL_U6 -> Residential | K13: =FL_U7 -> Residential | L13: =FL_U8 -> Residential | M13: =FL_U9 -> Residential | N13: =FL_U10 -> Residential | O13: =FL_U11 -> Residential | P13: =FL_U12 -> Residential | Q13: =FL_U13 -> Residential | R13: =FL_U14 -> Residential | S13: =FL_U15 -> Residential | T13: =FL_U16 -> Residential
B14: Basement flag | C14: flag | E14: 1 | F14: 1 | G14: 0 | H14: 0 | I14: 0 | J14: 0 | K14: 0 | L14: 0 | M14: 0 | N14: 0 | O14: 0 | P14: 0 | Q14: 0 | R14: 0 | S14: 0 | T14: 0
B15: Floor built flag | C15: flag | D15: =SUM(E15:T15) -> 10 | E15: =IF(E12>0,1,0) -> 0 | F15: =IF(F12>0,1,0) -> 1 | G15: =IF(G12>0,1,0) -> 1 | H15: =IF(H12>0,1,0) -> 1 | I15: =IF(I12>0,1,0) -> 1 | J15: =IF(J12>0,1,0) -> 1 | K15: =IF(K12>0,1,0) -> 1 | L15: =IF(L12>0,1,0) -> 1 | ... T15: =IF(T12>0,1,0) -> 0
B17: Building summary | C17: የሕንፃ ማጠቃለያ
B18: Gross floor area (GFA) | C18: m² | D18: =SUM(E12:T12) -> 6400
B19: Basement gross area | C19: m² | D19: =SUMPRODUCT(E12:T12,E14:T14) -> 900
B20: Above-ground gross area | C20: m² | D20: =GFA-GFA_BASE -> 5500
B21: Above-ground floors built | C21: no. | D21: =SUM(G15:T15) -> 9
B22: Basement levels built | C22: no. | D22: =SUM(E15:F15) -> 1
B23: Building configuration | D23: =IF(N_BASE>0,"B"&N_BASE&"+","")&"G+"&MAX(0,N_ABOVE-1) -> B1+G+8
B24: Ground-floor footprint | C24: m² | D24: =G12 -> 650
B25: Actual FAR (above-ground GFA ÷ plot) | C25: x | D25: =IF(PLOT_AREA>0,GFA_ABOVE/PLOT_AREA,0) -> 5.5
B26: Building type matches floors entered (1 = yes) | C26: flag | D26: =IF(AND(IF(BLDG_TYPE=5,1,IF(N_ABOVE=BLDG_TYPE,1,0))=1,IF(BASEMENT_YN=1,N_BASE>0,N_BASE=0)),1,0) -> 1
B28: By use – areas and disposition (IAS 2 sold · IAS 40 let · IAS 16 owner-occupied) | C28: በአገልግሎት
B29: Use | E29: Residential | F29: Retail | G29: Office | H29: Parking | I29: Other
B30: Gross area | C30: m² | D30: =SUM(E30:I30) -> 6400 | E30: =SUMIF($E$13:$T$13,E29,$E$12:$T$12) -> 4200 | F30: =SUMIF($E$13:$T$13,F29,$E$12:$T$12) -> 1300 | G30: =SUMIF($E$13:$T$13,G29,$E$12:$T$12) -> 0 | H30: =SUMIF($E$13:$T$13,H29,$E$12:$T$12) -> 900 | I30: =SUMIF($E$13:$T$13,I29,$E$12:$T$12) -> 0
B31: Net-to-gross efficiency | C31: % | E31: =EFF_RES -> 0.8 | F31: =EFF_RET -> 0.85 | G31: =EFF_OFF -> 0.82 | H31: =EFF_PAR -> 0 | I31: =EFF_OTH -> 0
B32: Net saleable / lettable area | C32: m² | D32: =SUM(E32:I32) -> 4465 | E32: =E30*E31 -> 3360 | F32: =F30*F31 -> 1105 | G32: =G30*G31 -> 0 | H32: =H30*H31 -> 0 | I32: =I30*I31 -> 0
B33: Share sold (IAS 2) | C33: % | E33: =CHOOSE(PROJECT_MODE+1,0,1-OWNUSE_PCT,0,SOLD_RES) -> 1 | F33: =CHOOSE(PROJECT_MODE+1,0,1-OWNUSE_PCT,0,SOLD_RET) -> 0 | G33: =CHOOSE(PROJECT_MODE+1,0,1-OWNUSE_PCT,0,SOLD_OFF) -> 0 | H33: =CHOOSE(PROJECT_MODE+1,0,1-OWNUSE_PCT,0,SOLD_PAR) -> 0 | I33: =CHOOSE(PROJECT_MODE+1,0,1-OWNUSE_PCT,0,SOLD_OTH) -> 0
B34: Share owner-occupied (IAS 16) | C34: % | E34: =CHOOSE(PROJECT_MODE+1,1-HOME_RENT_SH,OWNUSE_PCT,OWNUSE_PCT,OWNUSE_PCT*(1-E33)) -> 0 | F34: =CHOOSE(PROJECT_MODE+1,1-HOME_RENT_SH,OWNUSE_PCT,OWNUSE_PCT,OWNUSE_PCT*(1-F33)) -> 0 | G34: =CHOOSE(PROJECT_MODE+1,1-HOME_RENT_SH,OWNUSE_PCT,OWNUSE_PCT,OWNUSE_PCT*(1-G33)) -> 0 | H34: =CHOOSE(PROJECT_MODE+1,1-HOME_RENT_SH,OWNUSE_PCT,OWNUSE_PCT,OWNUSE_PCT*(1-H33)) -> 0 | I34: =CHOOSE(PROJECT_MODE+1,1-HOME_RENT_SH,OWNUSE_PCT,OWNUSE_PCT,OWNUSE_PCT*(1-I33)) -> 0
B35: Share let (IAS 40) | C35: % | E35: =1-E33-E34 -> 0 | F35: =1-F33-F34 -> 1 | G35: =1-G33-G34 -> 1 | H35: =1-H33-H34 -> 1 | I35: =1-I33-I34 -> 1
B36: Saleable area | C36: m² | D36: =SUM(E36:I36) -> 3360 | E36: =E32*E33 -> 3360 | F36: =F32*F33 -> 0 | G36: =G32*G33 -> 0 | H36: =H32*H33 -> 0 | I36: =I32*I33 -> 0
B37: Lettable area | C37: m² | D37: =SUM(E37:I37) -> 1105 | E37: =E32*E35 -> 0 | F37: =F32*F35 -> 1105 | G37: =G32*G35 -> 0 | H37: =H32*H35 -> 0 | I37: =I32*I35 -> 0
B38: Owner-occupied area | C38: m² | D38: =SUM(E38:I38) -> 0 | E38: =E32*E34 -> 0 | F38: =F32*F34 -> 0 | G38: =G32*G34 -> 0 | H38: =H32*H34 -> 0 | I38: =I32*I34 -> 0
B39: Sale price (today) | C39: ETB/m² | E39: =PRICE_RES -> 125000 | F39: =PRICE_RET -> 180000 | G39: =PRICE_OFF -> 110000 | H39: =PRICE_PAR -> 0 | I39: =PRICE_OTH -> 0
B40: Rent (today) | C40: ETB/m²/mo | E40: =RENT_RES -> 650 | F40: =RENT_RET -> 2000 | G40: =RENT_OFF -> 900 | H40: =RENT_PAR -> 0 | I40: =RENT_OTH -> 0
B41: Sales value (today's prices) | C41: ETB | D41: =SUM(E41:I41) -> 420000000 | E41: =E36*E39 -> 420000000 | F41: =F36*F39 -> 0 | G41: =G36*G39 -> 0 | H41: =H36*H39 -> 0 | I41: =I36*I39 -> 0
B42: Potential rent p.a. (today's prices) | C42: ETB | D42: =SUM(E42:I42) -> 26520000 | E42: =E37*E40*12 -> 0 | F42: =F37*F40*12 -> 26520000 | G42: =G37*G40*12 -> 0 | H42: =H37*H40*12 -> 0 | I42: =I37*I40*12 -> 0
B44: Area totals and allocation shares | C44: ጠቅላላ ስፋትና የወጪ ድልድል
B45: Net area (all uses) | C45: m² | D45: =$D$32 -> 4465
B46: Mode 0: share of house rented out | C46: % | D46: =IF(AND(RENT_HOME_F=1,NET_AREA>0),MIN(1,RENT_HOME_AREA/NET_AREA),0) -> 0
B47: Saleable area | C47: m² | D47: =$D$36 -> 3360
B48: Lettable area | C48: m² | D48: =$D$37 -> 1105
B49: Owner-occupied area | C49: m² | D49: =$D$38 -> 0
B50: Cost share → inventory (IAS 2) | C50: % | D50: =IF(NET_AREA>0,SALE_AREA/NET_AREA,0) -> 0.7525196
B51: Cost share → investment property (IAS 40) | C51: % | D51: =IF(NET_AREA>0,LET_AREA/NET_AREA,0) -> 0.2474804
B52: Cost share → owner-occupied PPE (IAS 16) | C52: % | D52: =IF(NET_AREA>0,OWN_AREA/NET_AREA,1) -> 0
B53: Cost share retained (IAS 40 + IAS 16) | C53: % | D53: =IP_SH+PPE_SH -> 0.2474804
B54: Sales value at today's prices | C54: ETB | D54: =$D$41 -> 420000000
B55: Blended sale price (today, after scenario & flex) | C55: ETB/m² | D55: =IF(SALE_AREA>0,SALEVAL_TODAY/SALE_AREA,0)*D_PRICE_F -> 125000
B56: Potential rent p.a. (today's prices, before scenario) | C56: ETB | D56: =IF(PROJECT_MODE=0,IF(RENT_HOME_F=1,RENT_HOME_MONTHLY*12,0),$D$42) -> 26520000
B57: Area reconciliation difference (uses vs floors) | C57: m² | D57: =$D$30-GFA -> 0
B58: Share reconciliation (should be 100%) | C58: % | D58: =INV_SH+IP_SH+PPE_SH -> 1

Sheet 22_Capex
B1: 22 · Capex – elemental BOQ, soft costs, land | L1: =HYPERLINK("#'00_Start'!A1","◂ Start") -> ◂ Start
B2: የካፒታል ወጪ – የግንባታ ዝርዝር
B3: =PROJ_NAME&" | Scenario: "&SCEN_NAME&" | Mode: "&MODE_NAME -> SAMPLE B — B+G+8 mixed-use building, Addis Ababa | Scenario: Base | Mode: 3 Mixed
B10: Cost drivers | C10: የወጪ መወሰኛዎች
B11: Finish level (1 Basic · 2 Standard · 3 Premium) | C11: code | D11: =FINISH -> 2
B12: Location factor | C12: x | D12: =IF(LOC_TYPE=1,LOCF_ADDIS,LOCF_REG) -> 1
B13: Storey factor (superstructure) | C13: x | D13: =1+STOREY_UPLIFT*MAX(0,N_ABOVE-4) -> 1.1
B14: Construction cost factor (scenario × flex) | C14: x | D14: =D_COST_F -> 1
B16: Elemental cost plan (budget-date prices) | C16: የግንባታ ወጪ ዝርዝር (በበጀት ቀን ዋጋ)
B17: Element | C17: Unit | D17: Budget (ETB) | E17: Library rate | F17: Location | G17: Storey | H17: Area m² | I17: Rate × area | J17: Method | K17: Lump sum | L17: Pre-flex
B18: Preliminaries · ቅድመ-ሥራዎች | C18: ETB | D18: =L18*D_COST_F -> 10240000 | E18: =INDEX(RATE_LIB,1,FIN_IX) -> 1600 | F18: =LOCF -> 1 | G18: 1 | H18: =GFA -> 6400 | I18: =E18*F18*G18*H18 -> 10240000 | J18: =METH_PRELIM -> 1 | K18: =LUMP_PRELIM -> 0 | L18: =IF(J18=2,K18,I18) -> 10240000
B19: Substructure · የመሠረት ሥራ | C19: ETB | D19: =L19*D_COST_F -> 24320000 | E19: =INDEX(RATE_LIB,2,FIN_IX) -> 3800 | F19: =LOCF -> 1 | G19: 1 | H19: =GFA -> 6400 | I19: =E19*F19*G19*H19 -> 24320000 | J19: =METH_SUBSTR -> 1 | K19: =LUMP_SUBSTR -> 0 | L19: =IF(J19=2,K19,I19) -> 24320000
B20: Superstructure (frame) · ከመሬት በላይ መዋቅር (ፍሬም) | C20: ETB | D20: =L20*D_COST_F -> 54912000 | E20: =INDEX(RATE_LIB,3,FIN_IX) -> 7800 | F20: =LOCF -> 1 | G20: =STOREY_F -> 1.1 | H20: =GFA -> 6400 | I20: =E20*F20*G20*H20 -> 54912000 | J20: =METH_SUPER -> 1 | K20: =LUMP_SUPER -> 0 | L20: =IF(J20=2,K20,I20) -> 54912000
B21: Envelope (walls, windows, roof) · ግድግዳ፣ መስኮትና ጣሪያ | C21: ETB | D21: =L21*D_COST_F -> 30720000 | E21: =INDEX(RATE_LIB,4,FIN_IX) -> 4800 | F21: =LOCF -> 1 | G21: 1 | H21: =GFA -> 6400 | I21: =E21*F21*G21*H21 -> 30720000 | J21: =METH_ENVEL -> 1 | K21: =LUMP_ENVEL -> 0 | L21: =IF(J21=2,K21,I21) -> 30720000
B22: Internal works (partitions, doors) · የውስጥ ሥራዎች (ክፍልፋይ፣ በር) | C22: ETB | D22: =L22*D_COST_F -> 15360000 | E22: =INDEX(RATE_LIB,5,FIN_IX) -> 2400 | F22: =LOCF -> 1 | G22: 1 | H22: =GFA -> 6400 | I22: =E22*F22*G22*H22 -> 15360000 | J22: =METH_INTERN -> 1 | K22: =LUMP_INTERN -> 0 | L22: =IF(J22=2,K22,I22) -> 15360000
B23: Finishes · የማጠናቀቂያ ሥራዎች | C23: ETB | D23: =L23*D_COST_F -> 35840000 | E23: =INDEX(RATE_LIB,6,FIN_IX) -> 5600 | F23: =LOCF -> 1 | G23: 1 | H23: =GFA -> 6400 | I23: =E23*F23*G23*H23 -> 35840000 | J23: =METH_FINISH -> 1 | K23: =LUMP_FINISH -> 0 | L23: =IF(J23=2,K23,I23) -> 35840000
B24: MEP (electrical, mechanical, plumbing) · ኤሌክትሪክ፣ ሜካኒካልና ቧንቧ | C24: ETB | D24: =L24*D_COST_F -> 28160000 | E24: =INDEX(RATE_LIB,7,FIN_IX) -> 4400 | F24: =LOCF -> 1 | G24: 1 | H24: =GFA -> 6400 | I24: =E24*F24*G24*H24 -> 28160000 | J24: =METH_MEP -> 1 | K24: =LUMP_MEP -> 0 | L24: =IF(J24=2,K24,I24) -> 28160000
B25: External works · የውጭ ሥራዎች | C25: ETB | D25: =L25*D_COST_F -> 7680000 | E25: =INDEX(RATE_LIB,8,FIN_IX) -> 1200 | F25: =LOCF -> 1 | G25: 1 | H25: =GFA -> 6400 | I25: =E25*F25*G25*H25 -> 7680000 | J25: =METH_EXTW -> 1 | K25: =LUMP_EXTW -> 0 | L25: =IF(J25=2,K25,I25) -> 7680000
B26: Specialist systems (lifts, fire, CCTV) · ልዩ ሲስተሞች (ሊፍት፣ እሳት፣ ካሜራ) | C26: ETB | D26: =L26*D_COST_F -> 45000000 | E26: =INDEX(RATE_LIB,9,FIN_IX) -> 400 | F26: =LOCF -> 1 | G26: 1 | H26: =GFA -> 6400 | I26: =E26*F26*G26*H26 -> 2560000 | J26: =METH_SPEC -> 2 | K26: =LUMP_SPEC -> 45000000 | L26: =IF(J26=2,K26,I26) -> 45000000
B27: Basement extra (excavation, retaining, waterproofing) | C27: ETB | D27: =GFA_BASE*BASEMENT_RATE*LOCF*D_COST_F -> 10800000
B28: Compound wall | C28: ETB | D28: =COMPOUND_YN*COMPOUND_LEN*COMPOUND_RATE*D_COST_F -> 2400000
B29: Septic tank(s) | C29: ETB | D29: =SEPTIC_YN*SEPTIC_QTY*SEPTIC_RATE*D_COST_F -> 0
B30: Water tank(s) | C30: ETB | D30: =WTANK_YN*WTANK_QTY*WTANK_RATE*D_COST_F -> 1000000
B31: Paving / landscaping | C31: ETB | D31: =EXT_M2*EXT_RATE*D_COST_F -> 1125000
B32: HARD COST AT BUDGET-DATE PRICES | C32: ETB | D32: =SUM(D18:D26)+BASE_X+X_COMPOUND+X_SEPTIC+X_WTANK+X_PAVE -> 267557000
B34: Total development cost (TDC) | C34: ጠቅላላ የልማት ወጪ
B35: Hard cost escalated (S-curve × escalation) | C35: ETB | D35: ='23_Construction'!$D$20 -> 3.1932235e+08
B36: of which escalation | C36: ETB | D36: =HARD_ESC_TOT-HARD_BASE -> 51765349
B37: Contingency | C37: ETB | D37: ='23_Construction'!$D$21 -> 25545788
B38: Design fees | C38: ETB | D38: ='23_Construction'!$D$22 -> 13377850
B39: Supervision | C39: ETB | D39: ='23_Construction'!$D$23 -> 9579670.5
B40: Permits & fees | C40: ETB | D40: ='23_Construction'!$D$24 -> 2500000
B41: FF&E / furniture | C41: ETB | D41: ='23_Construction'!$D$25 -> 6000000
B42: CONSTRUCTION COST (excl. land & finance) | C42: ETB | D42: =HARD_ESC_TOT+CONT_TOT+DESIGN_TOT+SUPERV_TOT+PERMIT_TOT+FFE_TOT -> 3.7632566e+08
B43: Land | C43: ETB | D43: ='23_Construction'!$D$26 -> 150000000
B44: Arrangement fee (IAS 23) | C44: ETB | D44: ='23_Construction'!$D$27 -> 3979766.1
B45: Commitment fees (IAS 23) | C45: ETB | D45: ='23_Construction'!$D$28 -> 2819326.3
B46: Interest during construction – capitalised (IAS 23) | C46: ETB | D46: ='23_Construction'!$D$29 -> 17535682
B47: Finance costs capitalised | C47: ETB | D47: =ARR_TOT+COMMIT_TOT+IDC_TOT -> 24334774
B48: TOTAL DEVELOPMENT COST (TDC) | C48: ETB | D48: =CONSTR_COST+LAND_TOT+FIN_CAP -> 5.5066043e+08
B49: Check: TDC vs monthly capex accrual | C49: ETB | D49: =TDC-'23_Construction'!$D$30 -> 0
B50: TDC per gross m² | C50: ETB/m² | D50: =IF(GFA>0,TDC/GFA,0) -> 86040.692
B51: TDC per net m² | C51: ETB/m² | D51: =IF(NET_AREA>0,TDC/NET_AREA,0) -> 123328.2
B52: Construction cost per gross m² | C52: ETB/m² | D52: =IF(GFA>0,CONSTR_COST/GFA,0) -> 58800.884
B53: Memo: TDC in USD | C53: USD | D53: =IF(FX_USD>0,TDC/FX_USD,0) -> 3552647.9
B55: Allocation of TDC (IAS 2 / IAS 40 / IAS 16) | C55: የወጪ ድልድል
B56: Inventory – units for sale (IAS 2) | C56: ETB | D56: =TDC*INV_SH -> 4.1438277e+08
B57: Investment property – let (IAS 40, cost model) | C57: ETB | D57: =TDC*IP_SH -> 1.3627767e+08
B58: Owner-occupied (IAS 16) | C58: ETB | D58: =TDC*PPE_SH -> 0
B59: Allocation difference (should be 0) | C59: ETB | D59: =TDC-TDC_INV-TDC_IP-TDC_PPE -> 0
B61: Depreciation components of retained assets | C61: የእርጅና ቅናሽ ክፍሎች
B62: Land fraction of TDC | C62: % | D62: =IF(TDC>0,LAND_TOT/TDC,0) -> 0.27240018
B63: FF&E fraction of TDC | C63: % | D63: =IF(TDC>0,FFE_TOT/TDC,0) -> 0.010896007
B64: Systems share of hard cost (MEP + specialist) | C64: % | D64: =IF(HARD_BASE>0,(EL_MEP+EL_SPEC)/HARD_BASE,0) -> 0.27343706
B65: Systems fraction of TDC | C65: % | D65: =(1-LAND_FR-FFE_FR)*SYS_SH -> 0.19597339
B66: Structure fraction of TDC | C66: % | D66: =1-LAND_FR-FFE_FR-SYS_FR -> 0.52073043
B67: Retained cost (IAS 40 + IAS 16) | C67: ETB | D67: =TDC*RET_SH -> 1.3627767e+08
B68: Depreciable base – structure | C68: ETB | D68: =RET_COST*STR_FR -> 70963927
B69: Depreciable base – systems | C69: ETB | D69: =RET_COST*SYS_FR -> 26706795
B70: Depreciable base – FF&E | C70: ETB | D70: =RET_COST*FFE_FR -> 1484882.4
B71: Land (not depreciated) | C71: ETB | D71: =RET_COST*LAND_FR -> 37122060
B73: Cost breakdown for charts (sums to TDC) | C73: የወጪ ክፍፍል
B74: Substructure & basement | C74: ETB | D74: =EL_SUBSTR+BASE_X -> 35120000
B75: Frame & envelope | C75: ETB | D75: =EL_SUPER+EL_ENVEL -> 85632000
B76: Internal works & finishes | C76: ETB | D76: =EL_INTERN+EL_FINISH -> 51200000
B77: MEP & specialist systems | C77: ETB | D77: =EL_MEP+EL_SPEC -> 73160000
B78: Preliminaries & external works | C78: ETB | D78: =EL_PRELIM+EL_EXTW+X_COMPOUND+X_SEPTIC+X_WTANK+X_PAVE -> 22445000
B79: Escalation & contingency | C79: ETB | D79: =ESC_AMT+CONT_TOT -> 77311137
B80: Fees & permits | C80: ETB | D80: =DESIGN_TOT+SUPERV_TOT+PERMIT_TOT -> 25457520
B81: Furniture & FF&E | C81: ETB | D81: =FFE_TOT -> 6000000
B82: Land | C82: ETB | D82: =LAND_TOT -> 150000000
B83: Finance costs (fees + IDC) | C83: ETB | D83: =FIN_CAP -> 24334774
B84: Total (= TDC) | C84: ETB | D84: =SUM(D74:D83) -> 5.5066043e+08
B86: Contractor payment stages (construction cost incl. escalation & contingency) | C86: ለኮንትራክተር የክፍያ ደረጃዎች
B87: 1 Mobilisation & site set-up | C87: ETB | D87: =IF(HARD_BASE>0,(EL_PRELIM)/HARD_BASE,0)*(HARD_ESC_TOT+CONT_TOT) -> 13198869
B88: 2 Foundation / substructure | C88: ETB | D88: =IF(HARD_BASE>0,(EL_SUBSTR+BASE_X)/HARD_BASE,0)*(HARD_ESC_TOT+CONT_TOT) -> 45267995
B89: 3 Frame (columns, beams, slabs) | C89: ETB | D89: =IF(HARD_BASE>0,(EL_SUPER)/HARD_BASE,0)*(HARD_ESC_TOT+CONT_TOT) -> 70778934
B90: 4 Walls, windows & roof | C90: ETB | D90: =IF(HARD_BASE>0,(EL_ENVEL)/HARD_BASE,0)*(HARD_ESC_TOT+CONT_TOT) -> 39596606
B91: 5 MEP & internal works | C91: ETB | D91: =IF(HARD_BASE>0,(EL_MEP+EL_INTERN+EL_SPEC)/HARD_BASE,0)*(HARD_ESC_TOT+CONT_TOT) -> 1.1409803e+08
B92: 6 Finishes & external works | C92: ETB | D92: =IF(HARD_BASE>0,(EL_FINISH+EL_EXTW+X_COMPOUND+X_SEPTIC+X_WTANK+X_PAVE)/HARD_BASE,0)*(HARD_ESC_TOT+CONT_TOT) -> 61927700
B93: Total contractor payments | C93: ETB | D93: =SUM(D87:D92) -> 3.4486814e+08

Sheet 23_Construction
B1: 23 · Construction – monthly S-curve, funding waterfall, presales | R1: =HYPERLINK("#'00_Start'!A1","◂ Start") -> ◂ Start
B2: የግንባታ ወርሃዊ ወጪ፣ የገንዘብ ምንጭና ቅድመ-ሽያጭ
B3: =PROJ_NAME&" | Scenario: "&SCEN_NAME&" | Mode: "&MODE_NAME -> SAMPLE B — B+G+8 mixed-use building, Addis Ababa | Scenario: Base | Mode: 3 Mixed
B6: Month | D6: Total | E6: ="M"&'20_Timeline'!E37 -> M1 | F6: ="M"&'20_Timeline'!F37 -> M2 | G6: ="M"&'20_Timeline'!G37 -> M3 | H6: ="M"&'20_Timeline'!H37 -> M4 | I6: ="M"&'20_Timeline'!I37 -> M5 | J6: ="M"&'20_Timeline'!J37 -> M6 | K6: ="M"&'20_Timeline'!K37 -> M7 | L6: ="M"&'20_Timeline'!L37 -> M8 | ... AZ6: ="M"&'20_Timeline'!AZ37 -> M48
B7: Month start | E7: ='20_Timeline'!E38 -> 46388 | F7: ='20_Timeline'!F38 -> 46419 | G7: ='20_Timeline'!G38 -> 46447 | H7: ='20_Timeline'!H38 -> 46478 | I7: ='20_Timeline'!I38 -> 46508 | J7: ='20_Timeline'!J38 -> 46539 | K7: ='20_Timeline'!K38 -> 46569 | L7: ='20_Timeline'!L38 -> 46600 | ... AZ7: ='20_Timeline'!AZ38 -> 47818
B8: Annual period | E8: =IF('20_Timeline'!E43=0,"–",INDEX('20_Timeline'!$E$12:$R$12,'20_Timeline'!E43)) -> C1 | F8: =IF('20_Timeline'!F43=0,"–",INDEX('20_Timeline'!$E$12:$R$12,'20_Timeline'!F43)) -> C1 | G8: =IF('20_Timeline'!G43=0,"–",INDEX('20_Timeline'!$E$12:$R$12,'20_Timeline'!G43)) -> C1 | H8: =IF('20_Timeline'!H43=0,"–",INDEX('20_Timeline'!$E$12:$R$12,'20_Timeline'!H43)) -> C1 | I8: =IF('20_Timeline'!I43=0,"–",INDEX('20_Timeline'!$E$12:$R$12,'20_Timeline'!I43)) -> C1 | J8: =IF('20_Timeline'!J43=0,"–",INDEX('20_Timeline'!$E$12:$R$12,'20_Timeline'!J43)) -> C1 | K8: =IF('20_Timeline'!K43=0,"–",INDEX('20_Timeline'!$E$12:$R$12,'20_Timeline'!K43)) -> C1 | L8: =IF('20_Timeline'!L43=0,"–",INDEX('20_Timeline'!$E$12:$R$12,'20_Timeline'!L43)) -> C1 | ... AZ8: =IF('20_Timeline'!AZ43=0,"–",INDEX('20_Timeline'!$E$12:$R$12,'20_Timeline'!AZ43)) -> O2
B10: Timing | C10: ጊዜ
B11: Construction month flag | C11: flag | D11: =SUM(E11:AZ11) -> 30 | E11: ='20_Timeline'!E39 -> 1 | F11: ='20_Timeline'!F39 -> 1 | G11: ='20_Timeline'!G39 -> 1 | H11: ='20_Timeline'!H39 -> 1 | I11: ='20_Timeline'!I39 -> 1 | J11: ='20_Timeline'!J39 -> 1 | K11: ='20_Timeline'!K39 -> 1 | L11: ='20_Timeline'!L39 -> 1 | ... AZ11: ='20_Timeline'!AZ39 -> 0
B12: Annual period index | C12: no. | E12: ='20_Timeline'!E43 -> 1 | F12: ='20_Timeline'!F43 -> 1 | G12: ='20_Timeline'!G43 -> 1 | H12: ='20_Timeline'!H43 -> 1 | I12: ='20_Timeline'!I43 -> 1 | J12: ='20_Timeline'!J43 -> 1 | K12: ='20_Timeline'!K43 -> 1 | L12: ='20_Timeline'!L43 -> 1 | ... AZ12: ='20_Timeline'!AZ43 -> 6
B13: Spend profile (S-curve) and escalation | C13: የወጪ ስርጭትና የዋጋ ጭማሪ
B14: User % profile (input row – used if profile = User %) | C14: % | D14: =SUM(E14:AZ14) -> 0 | E14: 0 | F14: 0 | G14: 0 | H14: 0 | I14: 0 | J14: 0 | K14: 0 | L14: 0 | M14: 0 | N14: 0 | O14: 0 | P14: 0 | Q14: 0 | R14: 0 | S14: 0 | T14: 0 | U14: 0 | V14: 0 | W14: 0 | X14: 0 | Y14: 0 | Z14: 0 | AA14: 0 | AB14: 0 | AC14: 0 | AD14: 0 | AE14: 0 | AF14: 0 | AG14: 0 | AH14: 0 | AI14: 0 | AJ14: 0 | AK14: 0 | AL14: 0 | AM14: 0 | AN14: 0 | AO14: 0 | AP14: 0 | AQ14: 0 | AR14: 0 | AS14: 0 | AT14: 0 | AU14: 0 | AV14: 0 | AW14: 0 | AX14: 0 | AY14: 0 | AZ14: 0
B15: Rapha Construction Cost Index (input row, optional) | C15: index | E15: 0 | F15: 0 | G15: 0 | H15: 0 | I15: 0 | J15: 0 | K15: 0 | L15: 0 | M15: 0 | N15: 0 | O15: 0 | P15: 0 | Q15: 0 | R15: 0 | S15: 0 | T15: 0 | U15: 0 | V15: 0 | W15: 0 | X15: 0 | Y15: 0 | Z15: 0 | AA15: 0 | AB15: 0 | AC15: 0 | AD15: 0 | AE15: 0 | AF15: 0 | AG15: 0 | AH15: 0 | AI15: 0 | AJ15: 0 | AK15: 0 | AL15: 0 | AM15: 0 | AN15: 0 | AO15: 0 | AP15: 0 | AQ15: 0 | AR15: 0 | AS15: 0 | AT15: 0 | AU15: 0 | AV15: 0 | AW15: 0 | AX15: 0 | AY15: 0 | AZ15: 0
B16: Cumulative progress | C16: % | E16: =IF('20_Timeline'!E37>=CONSTR_EFF,1,IF(SCURVE_TYPE=1,('20_Timeline'!E37/CONSTR_EFF)^SCURVE_A/(('20_Timeline'!E37/CONSTR_EFF)^SCURVE_A+(1-'20_Timeline'!E37/CONSTR_EFF)^SCURVE_A),IF(OR(SCURVE_TYPE=2,USER_TOT<=0),'20_Timeline'!E37/CONSTR_EFF,SUM($E$14:E14)/USER_TOT))) -> 0.0011876485 | F16: =IF('20_Timeline'!F37>=CONSTR_EFF,1,IF(SCURVE_TYPE=1,('20_Timeline'!F37/CONSTR_EFF)^SCURVE_A/(('20_Timeline'!F37/CONSTR_EFF)^SCURVE_A+(1-'20_Timeline'!F37/CONSTR_EFF)^SCURVE_A),IF(OR(SCURVE_TYPE=2,USER_TOT<=0),'20_Timeline'!F37/CONSTR_EFF,SUM($E$14:F14)/USER_TOT))) -> 0.0050761421 | G16: =IF('20_Timeline'!G37>=CONSTR_EFF,1,IF(SCURVE_TYPE=1,('20_Timeline'!G37/CONSTR_EFF)^SCURVE_A/(('20_Timeline'!G37/CONSTR_EFF)^SCURVE_A+(1-'20_Timeline'!G37/CONSTR_EFF)^SCURVE_A),IF(OR(SCURVE_TYPE=2,USER_TOT<=0),'20_Timeline'!G37/CONSTR_EFF,SUM($E$14:G14)/USER_TOT))) -> 0.012195122 | H16: =IF('20_Timeline'!H37>=CONSTR_EFF,1,IF(SCURVE_TYPE=1,('20_Timeline'!H37/CONSTR_EFF)^SCURVE_A/(('20_Timeline'!H37/CONSTR_EFF)^SCURVE_A+(1-'20_Timeline'!H37/CONSTR_EFF)^SCURVE_A),IF(OR(SCURVE_TYPE=2,USER_TOT<=0),'20_Timeline'!H37/CONSTR_EFF,SUM($E$14:H14)/USER_TOT))) -> 0.023121387 | I16: =IF('20_Timeline'!I37>=CONSTR_EFF,1,IF(SCURVE_TYPE=1,('20_Timeline'!I37/CONSTR_EFF)^SCURVE_A/(('20_Timeline'!I37/CONSTR_EFF)^SCURVE_A+(1-'20_Timeline'!I37/CONSTR_EFF)^SCURVE_A),IF(OR(SCURVE_TYPE=2,USER_TOT<=0),'20_Timeline'!I37/CONSTR_EFF,SUM($E$14:I14)/USER_TOT))) -> 0.038461538 | J16: =IF('20_Timeline'!J37>=CONSTR_EFF,1,IF(SCURVE_TYPE=1,('20_Timeline'!J37/CONSTR_EFF)^SCURVE_A/(('20_Timeline'!J37/CONSTR_EFF)^SCURVE_A+(1-'20_Timeline'!J37/CONSTR_EFF)^SCURVE_A),IF(OR(SCURVE_TYPE=2,USER_TOT<=0),'20_Timeline'!J37/CONSTR_EFF,SUM($E$14:J14)/USER_TOT))) -> 0.058823529 | K16: =IF('20_Timeline'!K37>=CONSTR_EFF,1,IF(SCURVE_TYPE=1,('20_Timeline'!K37/CONSTR_EFF)^SCURVE_A/(('20_Timeline'!K37/CONSTR_EFF)^SCURVE_A+(1-'20_Timeline'!K37/CONSTR_EFF)^SCURVE_A),IF(OR(SCURVE_TYPE=2,USER_TOT<=0),'20_Timeline'!K37/CONSTR_EFF,SUM($E$14:K14)/USER_TOT))) -> 0.084775087 | L16: =IF('20_Timeline'!L37>=CONSTR_EFF,1,IF(SCURVE_TYPE=1,('20_Timeline'!L37/CONSTR_EFF)^SCURVE_A/(('20_Timeline'!L37/CONSTR_EFF)^SCURVE_A+(1-'20_Timeline'!L37/CONSTR_EFF)^SCURVE_A),IF(OR(SCURVE_TYPE=2,USER_TOT<=0),'20_Timeline'!L37/CONSTR_EFF,SUM($E$14:L14)/USER_TOT))) -> 0.11678832 | ... AZ16: =IF('20_Timeline'!AZ37>=CONSTR_EFF,1,IF(SCURVE_TYPE=1,('20_Timeline'!AZ37/CONSTR_EFF)^SCURVE_A/(('20_Timeline'!AZ37/CONSTR_EFF)^SCURVE_A+(1-'20_Timeline'!AZ37/CONSTR_EFF)^SCURVE_A),IF(OR(SCURVE_TYPE=2,USER_TOT<=0),'20_Timeline'!AZ37/CONSTR_EFF,SUM($E$14:AZ14)/USER_TOT))) -> 1
B17: Monthly progress | C17: % | D17: =SUM(E17:AZ17) -> 1 | E17: =E16-0 -> 0.0011876485 | F17: =F16-E16 -> 0.0038884937 | G17: =G16-F16 -> 0.0071189798 | H17: =H16-G16 -> 0.010926265 | I17: =I16-H16 -> 0.015340151 | J17: =J16-I16 -> 0.020361991 | K17: =K16-J16 -> 0.025951557 | L17: =L16-K16 -> 0.032013235 | M17: =M16-L16 -> 0.038384093 | ... AZ17: =AZ16-AY16 -> 0
B18: Escalation factor | C18: x | E18: =IF(AND(INDEX_USE=1,INDEX_BASE>0,E15>0),E15/INDEX_BASE,(1+ESC_EFF)^(('20_Timeline'!E37-0.5)/12)) -> 1.0058404 | F18: =IF(AND(INDEX_USE=1,INDEX_BASE>0,F15>0),F15/INDEX_BASE,(1+ESC_EFF)^(('20_Timeline'!F37-0.5)/12)) -> 1.0176237 | G18: =IF(AND(INDEX_USE=1,INDEX_BASE>0,G15>0),G15/INDEX_BASE,(1+ESC_EFF)^(('20_Timeline'!G37-0.5)/12)) -> 1.0295451 | H18: =IF(AND(INDEX_USE=1,INDEX_BASE>0,H15>0),H15/INDEX_BASE,(1+ESC_EFF)^(('20_Timeline'!H37-0.5)/12)) -> 1.0416062 | I18: =IF(AND(INDEX_USE=1,INDEX_BASE>0,I15>0),I15/INDEX_BASE,(1+ESC_EFF)^(('20_Timeline'!I37-0.5)/12)) -> 1.0538085 | J18: =IF(AND(INDEX_USE=1,INDEX_BASE>0,J15>0),J15/INDEX_BASE,(1+ESC_EFF)^(('20_Timeline'!J37-0.5)/12)) -> 1.0661538 | K18: =IF(AND(INDEX_USE=1,INDEX_BASE>0,K15>0),K15/INDEX_BASE,(1+ESC_EFF)^(('20_Timeline'!K37-0.5)/12)) -> 1.0786437 | L18: =IF(AND(INDEX_USE=1,INDEX_BASE>0,L15>0),L15/INDEX_BASE,(1+ESC_EFF)^(('20_Timeline'!L37-0.5)/12)) -> 1.0912799 | ... AZ18: =IF(AND(INDEX_USE=1,INDEX_BASE>0,AZ15>0),AZ15/INDEX_BASE,(1+ESC_EFF)^(('20_Timeline'!AZ37-0.5)/12)) -> 1.7388507
B19: Development cost accrual (IAS 2 / 16 / 40 / 23) | C19: የልማት ወጪ
B20: Hard cost (escalated) | C20: ETB | D20: =SUM(E20:AZ20) -> 3.1932235e+08 | E20: =HARD_BASE*E17*E18 -> 319619.53 | F20: =HARD_BASE*F17*F18 -> 1058729.3 | G20: =HARD_BASE*G17*G18 -> 1961008.4 | H20: =HARD_BASE*H17*H18 -> 3045030.2 | I20: =HARD_BASE*I17*I18 -> 4325214.5 | J20: =HARD_BASE*J17*J18 -> 5808398.5 | K20: =HARD_BASE*K17*K18 -> 7489584.7 | L20: =HARD_BASE*L17*L18 -> 9347210.6 | ... AZ20: =HARD_BASE*AZ17*AZ18 -> 0
B21: Contingency | C21: ETB | D21: =SUM(E21:AZ21) -> 25545788 | E21: =E20*CONT_PCT -> 25569.562 | F21: =F20*CONT_PCT -> 84698.346 | G21: =G20*CONT_PCT -> 156880.68 | H21: =H20*CONT_PCT -> 243602.41 | I21: =I20*CONT_PCT -> 346017.16 | J21: =J20*CONT_PCT -> 464671.88 | K21: =K20*CONT_PCT -> 599166.77 | L21: =L20*CONT_PCT -> 747776.85 | ... AZ21: =AZ20*CONT_PCT -> 0
B22: Design fees | C22: ETB | D22: =SUM(E22:AZ22) -> 13377850 | E22: =DESIGN_PCT*HARD_BASE*(IF('20_Timeline'!E37=1,DESIGN_UPFRONT,0)+(1-DESIGN_UPFRONT)*E17) -> 6696869.1 | F22: =DESIGN_PCT*HARD_BASE*(IF('20_Timeline'!F37=1,DESIGN_UPFRONT,0)+(1-DESIGN_UPFRONT)*F17) -> 26009.843 | G22: =DESIGN_PCT*HARD_BASE*(IF('20_Timeline'!G37=1,DESIGN_UPFRONT,0)+(1-DESIGN_UPFRONT)*G17) -> 47618.322 | H22: =DESIGN_PCT*HARD_BASE*(IF('20_Timeline'!H37=1,DESIGN_UPFRONT,0)+(1-DESIGN_UPFRONT)*H17) -> 73084.969 | I22: =DESIGN_PCT*HARD_BASE*(IF('20_Timeline'!I37=1,DESIGN_UPFRONT,0)+(1-DESIGN_UPFRONT)*I17) -> 102609.12 | J22: =DESIGN_PCT*HARD_BASE*(IF('20_Timeline'!J37=1,DESIGN_UPFRONT,0)+(1-DESIGN_UPFRONT)*J17) -> 136199.83 | K22: =DESIGN_PCT*HARD_BASE*(IF('20_Timeline'!K37=1,DESIGN_UPFRONT,0)+(1-DESIGN_UPFRONT)*K17) -> 173588.02 | L22: =DESIGN_PCT*HARD_BASE*(IF('20_Timeline'!L37=1,DESIGN_UPFRONT,0)+(1-DESIGN_UPFRONT)*L17) -> 214134.13 | ... AZ22: =DESIGN_PCT*HARD_BASE*(IF('20_Timeline'!AZ37=1,DESIGN_UPFRONT,0)+(1-DESIGN_UPFRONT)*AZ17) -> 0
B23: Supervision | C23: ETB | D23: =SUM(E23:AZ23) -> 9579670.5 | E23: =SUPERV_PCT*E20 -> 9588.5858 | F23: =SUPERV_PCT*F20 -> 31761.88 | G23: =SUPERV_PCT*G20 -> 58830.253 | H23: =SUPERV_PCT*H20 -> 91350.905 | I23: =SUPERV_PCT*I20 -> 129756.43 | J23: =SUPERV_PCT*J20 -> 174251.95 | K23: =SUPERV_PCT*K20 -> 224687.54 | L23: =SUPERV_PCT*L20 -> 280416.32 | ... AZ23: =SUPERV_PCT*AZ20 -> 0
B24: Permits & fees | C24: ETB | D24: =SUM(E24:AZ24) -> 2500000 | E24: =PERMITS -> 2500000 | F24: 0 | G24: 0 | H24: 0 | I24: 0 | J24: 0 | K24: 0 | L24: 0 | M24: 0 | N24: 0 | O24: 0 | P24: 0 | Q24: 0 | R24: 0 | S24: 0 | T24: 0 | U24: 0 | V24: 0 | W24: 0 | X24: 0 | Y24: 0 | Z24: 0 | AA24: 0 | AB24: 0 | AC24: 0 | AD24: 0 | AE24: 0 | AF24: 0 | AG24: 0 | AH24: 0 | AI24: 0 | AJ24: 0 | AK24: 0 | AL24: 0 | AM24: 0 | AN24: 0 | AO24: 0 | AP24: 0 | AQ24: 0 | AR24: 0 | AS24: 0 | AT24: 0 | AU24: 0 | AV24: 0 | AW24: 0 | AX24: 0 | AY24: 0 | AZ24: 0
B25: FF&E / furniture | C25: ETB | D25: =SUM(E25:AZ25) -> 6000000 | E25: =IF('20_Timeline'!E37=CONSTR_EFF,FFE,0) -> 0 | F25: =IF('20_Timeline'!F37=CONSTR_EFF,FFE,0) -> 0 | G25: =IF('20_Timeline'!G37=CONSTR_EFF,FFE,0) -> 0 | H25: =IF('20_Timeline'!H37=CONSTR_EFF,FFE,0) -> 0 | I25: =IF('20_Timeline'!I37=CONSTR_EFF,FFE,0) -> 0 | J25: =IF('20_Timeline'!J37=CONSTR_EFF,FFE,0) -> 0 | K25: =IF('20_Timeline'!K37=CONSTR_EFF,FFE,0) -> 0 | L25: =IF('20_Timeline'!L37=CONSTR_EFF,FFE,0) -> 0 | ... AZ25: =IF('20_Timeline'!AZ37=CONSTR_EFF,FFE,0) -> 0
B26: Land (recognised month 1) | C26: ETB | D26: =SUM(E26:AZ26) -> 150000000 | E26: =LAND_VALUE -> 150000000 | F26: 0 | G26: 0 | H26: 0 | I26: 0 | J26: 0 | K26: 0 | L26: 0 | M26: 0 | N26: 0 | O26: 0 | P26: 0 | Q26: 0 | R26: 0 | S26: 0 | T26: 0 | U26: 0 | V26: 0 | W26: 0 | X26: 0 | Y26: 0 | Z26: 0 | AA26: 0 | AB26: 0 | AC26: 0 | AD26: 0 | AE26: 0 | AF26: 0 | AG26: 0 | AH26: 0 | AI26: 0 | AJ26: 0 | AK26: 0 | AL26: 0 | AM26: 0 | AN26: 0 | AO26: 0 | AP26: 0 | AQ26: 0 | AR26: 0 | AS26: 0 | AT26: 0 | AU26: 0 | AV26: 0 | AW26: 0 | AX26: 0 | AY26: 0 | AZ26: 0
B27: Arrangement fee (on IDC-excluded facility) | C27: ETB | D27: =SUM(E27:AZ27) -> 3979766.1 | E27: =ARR_FEE*DEBT_CAP -> 3979766.1 | F27: 0 | G27: 0 | H27: 0 | I27: 0 | J27: 0 | K27: 0 | L27: 0 | M27: 0 | N27: 0 | O27: 0 | P27: 0 | Q27: 0 | R27: 0 | S27: 0 | T27: 0 | U27: 0 | V27: 0 | W27: 0 | X27: 0 | Y27: 0 | Z27: 0 | AA27: 0 | AB27: 0 | AC27: 0 | AD27: 0 | AE27: 0 | AF27: 0 | AG27: 0 | AH27: 0 | AI27: 0 | AJ27: 0 | AK27: 0 | AL27: 0 | AM27: 0 | AN27: 0 | AO27: 0 | AP27: 0 | AQ27: 0 | AR27: 0 | AS27: 0 | AT27: 0 | AU27: 0 | AV27: 0 | AW27: 0 | AX27: 0 | AY27: 0 | AZ27: 0
B28: Commitment fee on undrawn facility | C28: ETB | D28: =SUM(E28:AZ28) -> 2819326.3 | E28: =IF('20_Timeline'!E37<=CONSTR_EFF,MAX(0,DEBT_CAP-0)*COMMIT_FEE/12,0) -> 110549.06 | F28: =IF('20_Timeline'!F37<=CONSTR_EFF,MAX(0,DEBT_CAP-E71)*COMMIT_FEE/12,0) -> 110549.06 | G28: =IF('20_Timeline'!G37<=CONSTR_EFF,MAX(0,DEBT_CAP-F71)*COMMIT_FEE/12,0) -> 110549.06 | H28: =IF('20_Timeline'!H37<=CONSTR_EFF,MAX(0,DEBT_CAP-G71)*COMMIT_FEE/12,0) -> 110549.06 | I28: =IF('20_Timeline'!I37<=CONSTR_EFF,MAX(0,DEBT_CAP-H71)*COMMIT_FEE/12,0) -> 110549.06 | J28: =IF('20_Timeline'!J37<=CONSTR_EFF,MAX(0,DEBT_CAP-I71)*COMMIT_FEE/12,0) -> 110549.06 | K28: =IF('20_Timeline'!K37<=CONSTR_EFF,MAX(0,DEBT_CAP-J71)*COMMIT_FEE/12,0) -> 110549.06 | L28: =IF('20_Timeline'!L37<=CONSTR_EFF,MAX(0,DEBT_CAP-K71)*COMMIT_FEE/12,0) -> 110549.06 | M28: =IF('20_Timeline'!M37<=CONSTR_EFF,MAX(0,DEBT_CAP-L71)*COMMIT_FEE/12,0) -> 110549.06 | ... AZ28: =IF('20_Timeline'!AZ37<=CONSTR_EFF,MAX(0,DEBT_CAP-AY71)*COMMIT_FEE/12,0) -> 0
B29: Interest during construction (from loan schedule) | C29: ETB | D29: =SUM(E29:AZ29) -> 17535682 | E29: ='27_Loan'!E66 -> 0 | F29: ='27_Loan'!F66 -> 0 | G29: ='27_Loan'!G66 -> 0 | H29: ='27_Loan'!H66 -> 0 | I29: ='27_Loan'!I66 -> 0 | J29: ='27_Loan'!J66 -> 0 | K29: ='27_Loan'!K66 -> 0 | L29: ='27_Loan'!L66 -> 0 | ... AZ29: ='27_Loan'!AZ66 -> 0
B30: Total capex accrual | C30: ETB | D30: =SUM(E30:AZ30) -> 5.5066043e+08 | E30: =E20+E21+E22+E23+E24+E25+E26+E27+E28+E29 -> 1.6364196e+08 | F30: =F20+F21+F22+F23+F24+F25+F26+F27+F28+F29 -> 1311748.5 | G30: =G20+G21+G22+G23+G24+G25+G26+G27+G28+G29 -> 2334886.7 | H30: =H20+H21+H22+H23+H24+H25+H26+H27+H28+H29 -> 3563617.5 | I30: =I20+I21+I22+I23+I24+I25+I26+I27+I28+I29 -> 5014146.2 | J30: =J20+J21+J22+J23+J24+J25+J26+J27+J28+J29 -> 6694071.2 | K30: =K20+K21+K22+K23+K24+K25+K26+K27+K28+K29 -> 8597576.1 | L30: =L20+L21+L22+L23+L24+L25+L26+L27+L28+L29 -> 10700087 | ... AZ30: =AZ20+AZ21+AZ22+AZ23+AZ24+AZ25+AZ26+AZ27+AZ28+AZ29 -> 0
B31: Cumulative capex accrual | C31: ETB | D31: =AZ31 -> 5.5066043e+08 | E31: =0+E30 -> 1.6364196e+08 | F31: =E31+F30 -> 1.6495371e+08 | G31: =F31+G30 -> 1.672886e+08 | H31: =G31+H30 -> 1.7085221e+08 | I31: =H31+I30 -> 1.7586636e+08 | J31: =I31+J30 -> 1.8256043e+08 | K31: =J31+K30 -> 1.9115801e+08 | L31: =K31+L30 -> 2.018581e+08 | M31: =L31+M30 -> 2.1481131e+08 | ... AZ31: =AY31+AZ30 -> 5.5066043e+08
B32: Cash needed during construction | C32: ለግንባታ የሚያስፈልግ ጥሬ ገንዘብ
B33: Retention withheld from contractor | C33: ETB | D33: =SUM(E33:AZ33) -> 15966117 | E33: =RETENTION*E20 -> 15980.976 | F33: =RETENTION*F20 -> 52936.467 | G33: =RETENTION*G20 -> 98050.422 | H33: =RETENTION*H20 -> 152251.51 | I33: =RETENTION*I20 -> 216260.72 | J33: =RETENTION*J20 -> 290419.92 | K33: =RETENTION*K20 -> 374479.23 | L33: =RETENTION*L20 -> 467360.53 | ... AZ33: =RETENTION*AZ20 -> 0
B34: Land cash (lease down payment) | C34: ETB | D34: =SUM(E34:AZ34) -> 15000000 | E34: =IF(LAND_TYPE=1,LAND_VALUE*LEASE_DP,0) -> 15000000 | F34: 0 | G34: 0 | H34: 0 | I34: 0 | J34: 0 | K34: 0 | L34: 0 | M34: 0 | N34: 0 | O34: 0 | P34: 0 | Q34: 0 | R34: 0 | S34: 0 | T34: 0 | U34: 0 | V34: 0 | W34: 0 | X34: 0 | Y34: 0 | Z34: 0 | AA34: 0 | AB34: 0 | AC34: 0 | AD34: 0 | AE34: 0 | AF34: 0 | AG34: 0 | AH34: 0 | AI34: 0 | AJ34: 0 | AK34: 0 | AL34: 0 | AM34: 0 | AN34: 0 | AO34: 0 | AP34: 0 | AQ34: 0 | AR34: 0 | AS34: 0 | AT34: 0 | AU34: 0 | AV34: 0 | AW34: 0 | AX34: 0 | AY34: 0 | AZ34: 0
B35: Development cash paid (excl. finance costs) | C35: ETB | D35: =SUM(E35:AZ35) -> 3.7535954e+08 | E35: =E34+E20-E33+E21+E22+E23+E24+E25 -> 24535666 | F35: =F34+F20-F33+F21+F22+F23+F24+F25 -> 1148262.9 | G35: =G34+G20-G33+G21+G22+G23+G24+G25 -> 2126287.3 | H35: =H34+H20-H33+H21+H22+H23+H24+H25 -> 3300816.9 | I35: =I34+I20-I33+I21+I22+I23+I24+I25 -> 4687336.5 | J35: =J34+J20-J33+J21+J22+J23+J24+J25 -> 6293102.2 | K35: =K34+K20-K33+K21+K22+K23+K24+K25 -> 8112547.8 | L35: =L34+L20-L33+L21+L22+L23+L24+L25 -> 10122177 | ... AZ35: =AZ34+AZ20-AZ33+AZ21+AZ22+AZ23+AZ24+AZ25 -> 0
B36: Input VAT on capex (commercial modes; reclaimable) | C36: ETB | D36: =SUM(E36:AZ36) -> 39251694 | E36: =IF(PROJECT_MODE=0,0,1)*VAT_R*VAT_CAPEX_PCT*(E20+E21+E22+E23+E25) -> 740422.91 | F36: =IF(PROJECT_MODE=0,0,1)*VAT_R*VAT_CAPEX_PCT*(F20+F21+F22+F23+F25) -> 126125.94 | G36: =IF(PROJECT_MODE=0,0,1)*VAT_R*VAT_CAPEX_PCT*(G20+G21+G22+G23+G25) -> 233555.46 | H36: =IF(PROJECT_MODE=0,0,1)*VAT_R*VAT_CAPEX_PCT*(H20+H21+H22+H23+H25) -> 362572.19 | I36: =IF(PROJECT_MODE=0,0,1)*VAT_R*VAT_CAPEX_PCT*(I20+I21+I22+I23+I25) -> 514877.7 | J36: =IF(PROJECT_MODE=0,0,1)*VAT_R*VAT_CAPEX_PCT*(J20+J21+J22+J23+J25) -> 691269.82 | K36: =IF(PROJECT_MODE=0,0,1)*VAT_R*VAT_CAPEX_PCT*(K20+K21+K22+K23+K25) -> 891137.84 | L36: =IF(PROJECT_MODE=0,0,1)*VAT_R*VAT_CAPEX_PCT*(L20+L21+L22+L23+L25) -> 1111901.5 | ... AZ36: =IF(PROJECT_MODE=0,0,1)*VAT_R*VAT_CAPEX_PCT*(AZ20+AZ21+AZ22+AZ23+AZ25) -> 0
B37: Land lease instalment (during construction) | C37: ETB | D37: =SUM(E37:AZ37) -> 9000000 | E37: =E11*'27_Loan'!E84 -> 0 | F37: =F11*'27_Loan'!F84 -> 0 | G37: =G11*'27_Loan'!G84 -> 0 | H37: =H11*'27_Loan'!H84 -> 0 | I37: =I11*'27_Loan'!I84 -> 0 | J37: =J11*'27_Loan'!J84 -> 0 | K37: =K11*'27_Loan'!K84 -> 0 | L37: =L11*'27_Loan'!L84 -> 0 | ... AZ37: =AZ11*'27_Loan'!AZ84 -> 0
B38: Land lease interest (during construction) | C38: ETB | D38: =SUM(E38:AZ38) -> 18585000 | E38: =E11*'27_Loan'!E85 -> 0 | F38: =F11*'27_Loan'!F85 -> 0 | G38: =G11*'27_Loan'!G85 -> 0 | H38: =H11*'27_Loan'!H85 -> 0 | I38: =I11*'27_Loan'!I85 -> 0 | J38: =J11*'27_Loan'!J85 -> 0 | K38: =K11*'27_Loan'!K85 -> 0 | L38: =L11*'27_Loan'!L85 -> 0 | ... AZ38: =AZ11*'27_Loan'!AZ85 -> 0
B39: Funding need excl. finance costs | C39: ETB | D39: =SUM(E39:AZ39) -> 4.4219623e+08 | E39: =E11*(E35+E36+E37+E38) -> 25276089 | F39: =F11*(F35+F36+F37+F38) -> 1274388.9 | G39: =G11*(G35+G36+G37+G38) -> 2359842.7 | H39: =H11*(H35+H36+H37+H38) -> 3663389.1 | I39: =I11*(I35+I36+I37+I38) -> 5202214.2 | J39: =J11*(J35+J36+J37+J38) -> 6984372 | K39: =K11*(K35+K36+K37+K38) -> 9003685.6 | L39: =L11*(L35+L36+L37+L38) -> 11234079 | ... AZ39: =AZ11*(AZ35+AZ36+AZ37+AZ38) -> 0
B40: Finance costs paid in cash (fees) | C40: ETB | D40: =SUM(E40:AZ40) -> 6799092.4 | E40: =E27+E28 -> 4090315.2 | F40: =F27+F28 -> 110549.06 | G40: =G27+G28 -> 110549.06 | H40: =H27+H28 -> 110549.06 | I40: =I27+I28 -> 110549.06 | J40: =J27+J28 -> 110549.06 | K40: =K27+K28 -> 110549.06 | L40: =L27+L28 -> 110549.06 | ... AZ40: =AZ27+AZ28 -> 0
B41: TOTAL FUNDING NEED | C41: ETB | D41: =SUM(E41:AZ41) -> 4.4899533e+08 | E41: =E39+E40 -> 29366404 | F41: =F39+F40 -> 1384937.9 | G41: =G39+G40 -> 2470391.8 | H41: =H39+H40 -> 3773938.2 | I41: =I39+I40 -> 5312763.2 | J41: =J39+J40 -> 7094921.1 | K41: =K39+K40 -> 9114234.7 | L41: =L39+L40 -> 11344628 | ... AZ41: =AZ39+AZ40 -> 0
B42: Cumulative funding need | C42: ETB | D42: =MAX(E42:AZ42) -> 4.4899533e+08 | E42: =0+E41 -> 29366404 | F42: =E42+F41 -> 30751342 | G42: =F42+G41 -> 33221734 | H42: =G42+H41 -> 36995672 | I42: =H42+I41 -> 42308435 | J42: =I42+J41 -> 49403356 | K42: =J42+K41 -> 58517591 | L42: =K42+L41 -> 69862219 | M42: =L42+M41 -> 83596980 | ... AZ42: =AY42+AZ41 -> 4.4899533e+08
B43: Presales (contracts signed during construction) | C43: ቅድመ-ሽያጭ
B44: Construction year (presale band) | C44: no. | E44: =ROUNDUP('20_Timeline'!E37/12,0) -> 1 | F44: =ROUNDUP('20_Timeline'!F37/12,0) -> 1 | G44: =ROUNDUP('20_Timeline'!G37/12,0) -> 1 | H44: =ROUNDUP('20_Timeline'!H37/12,0) -> 1 | I44: =ROUNDUP('20_Timeline'!I37/12,0) -> 1 | J44: =ROUNDUP('20_Timeline'!J37/12,0) -> 1 | K44: =ROUNDUP('20_Timeline'!K37/12,0) -> 1 | L44: =ROUNDUP('20_Timeline'!L37/12,0) -> 1 | ... AZ44: =ROUNDUP('20_Timeline'!AZ37/12,0) -> 4
B45: Construction months in this band | C45: no. | E45: =MAX(1,MIN(12,CONSTR_EFF-12*(E44-1))) -> 12 | F45: =MAX(1,MIN(12,CONSTR_EFF-12*(F44-1))) -> 12 | G45: =MAX(1,MIN(12,CONSTR_EFF-12*(G44-1))) -> 12 | H45: =MAX(1,MIN(12,CONSTR_EFF-12*(H44-1))) -> 12 | I45: =MAX(1,MIN(12,CONSTR_EFF-12*(I44-1))) -> 12 | J45: =MAX(1,MIN(12,CONSTR_EFF-12*(J44-1))) -> 12 | K45: =MAX(1,MIN(12,CONSTR_EFF-12*(K44-1))) -> 12 | L45: =MAX(1,MIN(12,CONSTR_EFF-12*(L44-1))) -> 12 | ... AZ45: =MAX(1,MIN(12,CONSTR_EFF-12*(AZ44-1))) -> 1
B46: Area presold | C46: m² | D46: =SUM(E46:AZ46) -> 2352 | E46: =E11*SALE_AREA*INDEX(PS_EFF,E44)/E45 -> 70 | F46: =F11*SALE_AREA*INDEX(PS_EFF,F44)/F45 -> 70 | G46: =G11*SALE_AREA*INDEX(PS_EFF,G44)/G45 -> 70 | H46: =H11*SALE_AREA*INDEX(PS_EFF,H44)/H45 -> 70 | I46: =I11*SALE_AREA*INDEX(PS_EFF,I44)/I45 -> 70 | J46: =J11*SALE_AREA*INDEX(PS_EFF,J44)/J45 -> 70 | K46: =K11*SALE_AREA*INDEX(PS_EFF,K44)/K45 -> 70 | L46: =L11*SALE_AREA*INDEX(PS_EFF,L44)/L45 -> 70 | ... AZ46: =AZ11*SALE_AREA*INDEX(PS_EFF,AZ44)/AZ45 -> 0
B47: Sale price (escalated) | C47: ETB/m² | E47: =BLEND_PRICE*(1+PESC_EFF)^(('20_Timeline'!E37-1)/12) -> 125000 | F47: =BLEND_PRICE*(1+PESC_EFF)^(('20_Timeline'!F37-1)/12) -> 125996.77 | G47: =BLEND_PRICE*(1+PESC_EFF)^(('20_Timeline'!G37-1)/12) -> 127001.48 | H47: =BLEND_PRICE*(1+PESC_EFF)^(('20_Timeline'!H37-1)/12) -> 128014.21 | I47: =BLEND_PRICE*(1+PESC_EFF)^(('20_Timeline'!I37-1)/12) -> 129035.01 | J47: =BLEND_PRICE*(1+PESC_EFF)^(('20_Timeline'!J37-1)/12) -> 130063.96 | K47: =BLEND_PRICE*(1+PESC_EFF)^(('20_Timeline'!K37-1)/12) -> 131101.11 | L47: =BLEND_PRICE*(1+PESC_EFF)^(('20_Timeline'!L37-1)/12) -> 132146.52 | ... AZ47: =BLEND_PRICE*(1+PESC_EFF)^(('20_Timeline'!AZ37-1)/12) -> 181564.68
B48: Contract value signed (net of default allowance) | C48: ETB | D48: =SUM(E48:AZ48) -> 3.2743786e+08 | E48: =E46*E47*(1-DEFAULT_EFF) -> 8575000 | F48: =F46*F47*(1-DEFAULT_EFF) -> 8643378.3 | G48: =G46*G47*(1-DEFAULT_EFF) -> 8712301.8 | H48: =H46*H47*(1-DEFAULT_EFF) -> 8781774.9 | I48: =I46*I47*(1-DEFAULT_EFF) -> 8851802 | J48: =J46*J47*(1-DEFAULT_EFF) -> 8922387.5 | K48: =K46*K47*(1-DEFAULT_EFF) -> 8993535.9 | L48: =L46*L47*(1-DEFAULT_EFF) -> 9065251.6 | ... AZ48: =AZ46*AZ47*(1-DEFAULT_EFF) -> 0
B49: Cumulative contract value | C49: ETB | D49: =AZ49 -> 3.2743786e+08 | E49: =0+E48 -> 8575000 | F49: =E49+F48 -> 17218378 | G49: =F49+G48 -> 25930680 | H49: =G49+H48 -> 34712455 | I49: =H49+I48 -> 43564257 | J49: =I49+J48 -> 52486644 | K49: =J49+K48 -> 61480180 | L49: =K49+L48 -> 70545432 | M49: =L49+M48 -> 79682971 | ... AZ49: =AY49+AZ48 -> 3.2743786e+08
B50: Cumulative area presold | C50: m² | D50: =AZ50 -> 2352 | E50: =0+E46 -> 70 | F50: =E50+F46 -> 140 | G50: =F50+G46 -> 210 | H50: =G50+H46 -> 280 | I50: =H50+I46 -> 350 | J50: =I50+J46 -> 420 | K50: =J50+K46 -> 490 | L50: =K50+L46 -> 560 | M50: =L50+M46 -> 630 | ... AZ50: =AY50+AZ46 -> 2352
B51: Collections – down payments | C51: ETB | D51: =SUM(E51:AZ51) -> 98231357 | E51: =PAY_DP*E48 -> 2572500 | F51: =PAY_DP*F48 -> 2593013.5 | G51: =PAY_DP*G48 -> 2613690.5 | H51: =PAY_DP*H48 -> 2634532.5 | I51: =PAY_DP*I48 -> 2655540.6 | J51: =PAY_DP*J48 -> 2676716.3 | K51: =PAY_DP*K48 -> 2698060.8 | L51: =PAY_DP*L48 -> 2719575.5 | ... AZ51: =PAY_DP*AZ48 -> 0
B52: Cumulative milestone instalments due | C52: ETB | D52: =AZ52 -> 1.3097514e+08 | E52: =PAY_INST*E49*E16 -> 4073.6342 | F52: =PAY_INST*F49*F16 -> 34961.174 | G52: =PAY_INST*G49*G16 -> 126491.12 | H52: =PAY_INST*H49*H16 -> 321040.05 | I52: =PAY_INST*I49*I16 -> 670219.34 | J52: =PAY_INST*J49*J16 -> 1234979.9 | K52: =PAY_INST*K49*K16 -> 2084795 | L52: =PAY_INST*L49*L16 -> 3295553 | ... AZ52: =PAY_INST*AZ49*AZ16 -> 1.3097514e+08
B53: Collections – milestone instalments | C53: ETB | D53: =SUM(E53:AZ53) -> 1.3097514e+08 | E53: =E52-0 -> 4073.6342 | F53: =F52-E52 -> 30887.54 | G53: =G52-F52 -> 91529.948 | H53: =H52-G52 -> 194548.92 | I53: =I52-H52 -> 349179.29 | J53: =J52-I52 -> 564760.53 | K53: =K52-J52 -> 849815.17 | L53: =L52-K52 -> 1210758 | M53: =M52-L52 -> 1650286.6 | ... AZ53: =AZ52-AY52 -> 0
B54: Collections – balance at handover | C54: ETB | D54: =SUM(E54:AZ54) -> 98231357 | E54: =IF('20_Timeline'!E37=CONSTR_EFF,(1-PAY_DP-PAY_INST)*E49,0) -> 0 | F54: =IF('20_Timeline'!F37=CONSTR_EFF,(1-PAY_DP-PAY_INST)*F49,0) -> 0 | G54: =IF('20_Timeline'!G37=CONSTR_EFF,(1-PAY_DP-PAY_INST)*G49,0) -> 0 | H54: =IF('20_Timeline'!H37=CONSTR_EFF,(1-PAY_DP-PAY_INST)*H49,0) -> 0 | I54: =IF('20_Timeline'!I37=CONSTR_EFF,(1-PAY_DP-PAY_INST)*I49,0) -> 0 | J54: =IF('20_Timeline'!J37=CONSTR_EFF,(1-PAY_DP-PAY_INST)*J49,0) -> 0 | K54: =IF('20_Timeline'!K37=CONSTR_EFF,(1-PAY_DP-PAY_INST)*K49,0) -> 0 | L54: =IF('20_Timeline'!L37=CONSTR_EFF,(1-PAY_DP-PAY_INST)*L49,0) -> 0 | ... AZ54: =IF('20_Timeline'!AZ37=CONSTR_EFF,(1-PAY_DP-PAY_INST)*AZ49,0) -> 0
B55: Total presale collections | C55: ETB | D55: =SUM(E55:AZ55) -> 3.2743786e+08 | E55: =E51+E53+E54 -> 2576573.6 | F55: =F51+F53+F54 -> 2623901 | G55: =G51+G53+G54 -> 2705220.5 | H55: =H51+H53+H54 -> 2829081.4 | I55: =I51+I53+I54 -> 3004719.9 | J55: =J51+J53+J54 -> 3241476.8 | K55: =K51+K53+K54 -> 3547875.9 | L55: =L51+L53+L54 -> 3930333.5 | ... AZ55: =AZ51+AZ53+AZ54 -> 0
B56: Cumulative revenue recognised (IFRS 15) | C56: ETB | D56: =AZ56 -> 3.2743786e+08 | E56: =IF(REV_POLICY=2,E49*E16,IF('20_Timeline'!E37>=CONSTR_EFF,E49,0)) -> 0 | F56: =IF(REV_POLICY=2,F49*F16,IF('20_Timeline'!F37>=CONSTR_EFF,F49,0)) -> 0 | G56: =IF(REV_POLICY=2,G49*G16,IF('20_Timeline'!G37>=CONSTR_EFF,G49,0)) -> 0 | H56: =IF(REV_POLICY=2,H49*H16,IF('20_Timeline'!H37>=CONSTR_EFF,H49,0)) -> 0 | I56: =IF(REV_POLICY=2,I49*I16,IF('20_Timeline'!I37>=CONSTR_EFF,I49,0)) -> 0 | J56: =IF(REV_POLICY=2,J49*J16,IF('20_Timeline'!J37>=CONSTR_EFF,J49,0)) -> 0 | K56: =IF(REV_POLICY=2,K49*K16,IF('20_Timeline'!K37>=CONSTR_EFF,K49,0)) -> 0 | L56: =IF(REV_POLICY=2,L49*L16,IF('20_Timeline'!L37>=CONSTR_EFF,L49,0)) -> 0 | ... AZ56: =IF(REV_POLICY=2,AZ49*AZ16,IF('20_Timeline'!AZ37>=CONSTR_EFF,AZ49,0)) -> 3.2743786e+08
B57: Presale revenue recognised | C57: ETB | D57: =SUM(E57:AZ57) -> 3.2743786e+08 | E57: =E56-0 -> 0 | F57: =F56-E56 -> 0 | G57: =G56-F56 -> 0 | H57: =H56-G56 -> 0 | I57: =I56-H56 -> 0 | J57: =J56-I56 -> 0 | K57: =K56-J56 -> 0 | L57: =L56-K56 -> 0 | M57: =M56-L56 -> 0 | ... AZ57: =AZ56-AY56 -> 0
B58: Cumulative cost of sales released (IAS 2) | C58: ETB | D58: =AZ58 -> 2.9006794e+08 | E58: =IF(SALE_AREA>0,TDC_INV*E50/SALE_AREA*IF(REV_POLICY=2,E16,IF('20_Timeline'!E37>=CONSTR_EFF,1,0)),0) -> 0 | F58: =IF(SALE_AREA>0,TDC_INV*F50/SALE_AREA*IF(REV_POLICY=2,F16,IF('20_Timeline'!F37>=CONSTR_EFF,1,0)),0) -> 0 | G58: =IF(SALE_AREA>0,TDC_INV*G50/SALE_AREA*IF(REV_POLICY=2,G16,IF('20_Timeline'!G37>=CONSTR_EFF,1,0)),0) -> 0 | H58: =IF(SALE_AREA>0,TDC_INV*H50/SALE_AREA*IF(REV_POLICY=2,H16,IF('20_Timeline'!H37>=CONSTR_EFF,1,0)),0) -> 0 | I58: =IF(SALE_AREA>0,TDC_INV*I50/SALE_AREA*IF(REV_POLICY=2,I16,IF('20_Timeline'!I37>=CONSTR_EFF,1,0)),0) -> 0 | J58: =IF(SALE_AREA>0,TDC_INV*J50/SALE_AREA*IF(REV_POLICY=2,J16,IF('20_Timeline'!J37>=CONSTR_EFF,1,0)),0) -> 0 | K58: =IF(SALE_AREA>0,TDC_INV*K50/SALE_AREA*IF(REV_POLICY=2,K16,IF('20_Timeline'!K37>=CONSTR_EFF,1,0)),0) -> 0 | L58: =IF(SALE_AREA>0,TDC_INV*L50/SALE_AREA*IF(REV_POLICY=2,L16,IF('20_Timeline'!L37>=CONSTR_EFF,1,0)),0) -> 0 | ... AZ58: =IF(SALE_AREA>0,TDC_INV*AZ50/SALE_AREA*IF(REV_POLICY=2,AZ16,IF('20_Timeline'!AZ37>=CONSTR_EFF,1,0)),0) -> 2.9006794e+08
B59: Presale cost of sales | C59: ETB | D59: =SUM(E59:AZ59) -> 2.9006794e+08 | E59: =E58-0 -> 0 | F59: =F58-E58 -> 0 | G59: =G58-F58 -> 0 | H59: =H58-G58 -> 0 | I59: =I58-H58 -> 0 | J59: =J58-I58 -> 0 | K59: =K58-J58 -> 0 | L59: =L58-K58 -> 0 | M59: =M58-L58 -> 0 | ... AZ59: =AZ58-AY58 -> 0
B60: Funding waterfall: (1) presales → (2) equity → (3) debt → (4) top-up / gap | C60: የገንዘብ ምንጭ ቅደም ተከተል
B61: Presale cash usable for construction | C61: ETB | D61: =SUM(E61:AZ61) -> 2.6195029e+08 | E61: =E11*IF(PRESALE_USE=1,PRESALE_USE_PCT,0)*E55 -> 2061258.9 | F61: =F11*IF(PRESALE_USE=1,PRESALE_USE_PCT,0)*F55 -> 2099120.8 | G61: =G11*IF(PRESALE_USE=1,PRESALE_USE_PCT,0)*G55 -> 2164176.4 | H61: =H11*IF(PRESALE_USE=1,PRESALE_USE_PCT,0)*H55 -> 2263265.1 | I61: =I11*IF(PRESALE_USE=1,PRESALE_USE_PCT,0)*I55 -> 2403775.9 | J61: =J11*IF(PRESALE_USE=1,PRESALE_USE_PCT,0)*J55 -> 2593181.4 | K61: =K11*IF(PRESALE_USE=1,PRESALE_USE_PCT,0)*K55 -> 2838300.7 | L61: =L11*IF(PRESALE_USE=1,PRESALE_USE_PCT,0)*L55 -> 3144266.8 | ... AZ61: =AZ11*IF(PRESALE_USE=1,PRESALE_USE_PCT,0)*AZ55 -> 0
B62: Presale pool – opening | C62: ETB | E62: =0 -> 0 | F62: =E64 -> 0 | G62: =F64 -> 714182.88 | H62: =G64 -> 407967.48 | I62: =H64 -> 0 | J62: =I64 -> 0 | K62: =J64 -> 0 | L62: =K64 -> 0 | M62: =L64 -> 0 | ... AZ62: =AY64 -> 1.0544766e+08
B63: (1) Presale cash used | C63: ETB | D63: =SUM(E63:AZ63) -> 1.5650262e+08 | E63: =MIN(E41,E62+E61) -> 2061258.9 | F63: =MIN(F41,F62+F61) -> 1384937.9 | G63: =MIN(G41,G62+G61) -> 2470391.8 | H63: =MIN(H41,H62+H61) -> 2671232.6 | I63: =MIN(I41,I62+I61) -> 2403775.9 | J63: =MIN(J41,J62+J61) -> 2593181.4 | K63: =MIN(K41,K62+K61) -> 2838300.7 | L63: =MIN(L41,L62+L61) -> 3144266.8 | ... AZ63: =MIN(AZ41,AZ62+AZ61) -> 0
B64: Presale pool – closing | C64: ETB | D64: =AZ64 -> 1.0544766e+08 | E64: =E62+E61-E63 -> 0 | F64: =F62+F61-F63 -> 714182.88 | G64: =G62+G61-G63 -> 407967.48 | H64: =H62+H61-H63 -> 0 | I64: =I62+I61-I63 -> 0 | J64: =J62+J61-J63 -> 0 | K64: =K62+K61-K63 -> 0 | L64: =L62+L61-L63 -> 0 | ... AZ64: =AZ62+AZ61-AZ63 -> 1.0544766e+08
B65: Need after presales | C65: ETB | D65: =SUM(E65:AZ65) -> 2.9249271e+08 | E65: =E41-E63 -> 27305145 | F65: =F41-F63 -> 0 | G65: =G41-G63 -> 0 | H65: =H41-H63 -> 1102705.6 | I65: =I41-I63 -> 2908987.3 | J65: =J41-J63 -> 4501739.6 | K65: =K41-K63 -> 6275933.9 | L65: =L41-L63 -> 8200361.1 | ... AZ65: =AZ41-AZ63 -> 0
B66: (2) Equity draw | C66: ETB | D66: =SUM(E66:AZ66) -> 1.7687849e+08 | E66: =MIN(E65*IF(DRAW_ORDER=1,1,EQ_SHARE),MAX(0,EQ_COMMIT-0)) -> 27305145 | F66: =MIN(F65*IF(DRAW_ORDER=1,1,EQ_SHARE),MAX(0,EQ_COMMIT-E70)) -> 0 | G66: =MIN(G65*IF(DRAW_ORDER=1,1,EQ_SHARE),MAX(0,EQ_COMMIT-F70)) -> 0 | H66: =MIN(H65*IF(DRAW_ORDER=1,1,EQ_SHARE),MAX(0,EQ_COMMIT-G70)) -> 1102705.6 | I66: =MIN(I65*IF(DRAW_ORDER=1,1,EQ_SHARE),MAX(0,EQ_COMMIT-H70)) -> 2908987.3 | J66: =MIN(J65*IF(DRAW_ORDER=1,1,EQ_SHARE),MAX(0,EQ_COMMIT-I70)) -> 4501739.6 | K66: =MIN(K65*IF(DRAW_ORDER=1,1,EQ_SHARE),MAX(0,EQ_COMMIT-J70)) -> 6275933.9 | L66: =MIN(L65*IF(DRAW_ORDER=1,1,EQ_SHARE),MAX(0,EQ_COMMIT-K70)) -> 8200361.1 | M66: =MIN(M65*IF(DRAW_ORDER=1,1,EQ_SHARE),MAX(0,EQ_COMMIT-L70)) -> 10221523 | ... AZ66: =MIN(AZ65*IF(DRAW_ORDER=1,1,EQ_SHARE),MAX(0,EQ_COMMIT-AY70)) -> 0
B67: (3) Debt draw | C67: ETB | D67: =SUM(E67:AZ67) -> 1.1561421e+08 | E67: =MIN(E65-E66,MAX(0,DEBT_CAP-0)) -> 0 | F67: =MIN(F65-F66,MAX(0,DEBT_CAP-E71)) -> 0 | G67: =MIN(G65-G66,MAX(0,DEBT_CAP-F71)) -> 0 | H67: =MIN(H65-H66,MAX(0,DEBT_CAP-G71)) -> 0 | I67: =MIN(I65-I66,MAX(0,DEBT_CAP-H71)) -> 0 | J67: =MIN(J65-J66,MAX(0,DEBT_CAP-I71)) -> 0 | K67: =MIN(K65-K66,MAX(0,DEBT_CAP-J71)) -> 0 | L67: =MIN(L65-L66,MAX(0,DEBT_CAP-K71)) -> 0 | M67: =MIN(M65-M66,MAX(0,DEBT_CAP-L71)) -> 0 | ... AZ67: =MIN(AZ65-AZ66,MAX(0,DEBT_CAP-AY71)) -> 0
B68: (2b) Equity – pro-rata balance | C68: ETB | D68: =SUM(E68:AZ68) -> 0 | E68: =IF(DRAW_ORDER=2,MIN(E65-E66-E67,MAX(0,EQ_COMMIT-0-E66)),0) -> 0 | F68: =IF(DRAW_ORDER=2,MIN(F65-F66-F67,MAX(0,EQ_COMMIT-E70-F66)),0) -> 0 | G68: =IF(DRAW_ORDER=2,MIN(G65-G66-G67,MAX(0,EQ_COMMIT-F70-G66)),0) -> 0 | H68: =IF(DRAW_ORDER=2,MIN(H65-H66-H67,MAX(0,EQ_COMMIT-G70-H66)),0) -> 0 | I68: =IF(DRAW_ORDER=2,MIN(I65-I66-I67,MAX(0,EQ_COMMIT-H70-I66)),0) -> 0 | J68: =IF(DRAW_ORDER=2,MIN(J65-J66-J67,MAX(0,EQ_COMMIT-I70-J66)),0) -> 0 | K68: =IF(DRAW_ORDER=2,MIN(K65-K66-K67,MAX(0,EQ_COMMIT-J70-K66)),0) -> 0 | L68: =IF(DRAW_ORDER=2,MIN(L65-L66-L67,MAX(0,EQ_COMMIT-K70-L66)),0) -> 0 | M68: =IF(DRAW_ORDER=2,MIN(M65-M66-M67,MAX(0,EQ_COMMIT-L70-M66)),0) -> 0 | ... AZ68: =IF(DRAW_ORDER=2,MIN(AZ65-AZ66-AZ67,MAX(0,EQ_COMMIT-AY70-AZ66)),0) -> 0
B69: (4) Sponsor top-up / funding gap | C69: ETB | D69: =SUM(E69:AZ69) -> 0 | E69: =E65-E66-E67-E68 -> 0 | F69: =F65-F66-F67-F68 -> 0 | G69: =G65-G66-G67-G68 -> 0 | H69: =H65-H66-H67-H68 -> 0 | I69: =I65-I66-I67-I68 -> 0 | J69: =J65-J66-J67-J68 -> 0 | K69: =K65-K66-K67-K68 -> 0 | L69: =L65-L66-L67-L68 -> 0 | ... AZ69: =AZ65-AZ66-AZ67-AZ68 -> 0
B70: Cumulative committed equity drawn | C70: ETB | D70: =AZ70 -> 1.7687849e+08 | E70: =0+E66+E68 -> 27305145 | F70: =E70+F66+F68 -> 27305145 | G70: =F70+G66+G68 -> 27305145 | H70: =G70+H66+H68 -> 28407851 | I70: =H70+I66+I68 -> 31316838 | J70: =I70+J66+J68 -> 35818577 | K70: =J70+K66+K68 -> 42094511 | L70: =K70+L66+L68 -> 50294873 | M70: =L70+M66+M68 -> 60516395 | ... AZ70: =AY70+AZ66+AZ68 -> 1.7687849e+08
B71: Cumulative debt drawn | C71: ETB | D71: =AZ71 -> 1.1561421e+08 | E71: =0+E67 -> 0 | F71: =E71+F67 -> 0 | G71: =F71+G67 -> 0 | H71: =G71+H67 -> 0 | I71: =H71+I67 -> 0 | J71: =I71+J67 -> 0 | K71: =J71+K67 -> 0 | L71: =K71+L67 -> 0 | M71: =L71+M67 -> 0 | ... AZ71: =AY71+AZ67 -> 1.1561421e+08
B72: Total equity in (incl. top-up) | C72: ETB | D72: =SUM(E72:AZ72) -> 1.7687849e+08 | E72: =E66+E68+E69 -> 27305145 | F72: =F66+F68+F69 -> 0 | G72: =G66+G68+G69 -> 0 | H72: =H66+H68+H69 -> 1102705.6 | I72: =I66+I68+I69 -> 2908987.3 | J72: =J66+J68+J69 -> 4501739.6 | K72: =K66+K68+K69 -> 6275933.9 | L72: =L66+L68+L69 -> 8200361.1 | ... AZ72: =AZ66+AZ68+AZ69 -> 0
B73: Presale cash held (pool + escrow), cumulative | C73: ETB | D73: =AZ73 -> 1.7093524e+08 | E73: =0+E55-E63 -> 515314.73 | F73: =E73+F55-F63 -> 1754277.8 | G73: =F73+G55-G63 -> 1989106.5 | H73: =G73+H55-H63 -> 2146955.3 | I73: =H73+I55-I63 -> 2747899.3 | J73: =I73+J55-J63 -> 3396194.6 | K73: =J73+K55-K63 -> 4105769.8 | L73: =K73+L55-L63 -> 4891836.5 | M73: =L73+M55-M63 -> 5770146.2 | ... AZ73: =AY73+AZ55-AZ63 -> 1.7093524e+08
B74: Sources − uses (should be 0) | C74: ETB | D74: =SUM(E74:AZ74) -> 0 | E74: =E63+E72+E67-E41 -> 0 | F74: =F63+F72+F67-F41 -> 0 | G74: =G63+G72+G67-G41 -> 0 | H74: =H63+H72+H67-H41 -> 0 | I74: =I63+I72+I67-I41 -> 0 | J74: =J63+J72+J67-J41 -> 0 | K74: =K63+K72+K67-K41 -> 0 | L74: =L63+L72+L67-L41 -> 0 | ... AZ74: =AZ63+AZ72+AZ67-AZ41 -> 0
B76: Funding scalars | C76: የገንዘብ ማጠቃለያ
B77: User profile total (construction months) | C77: % | D77: =SUMPRODUCT(E14:AZ14,E11:AZ11) -> 0
B78: Funding base (need excl. IDC & finance fees) | C78: ETB | D78: =$D$39 -> 4.4219623e+08
B79: Equity commitment | C79: ETB | D79: =IF(PROJECT_MODE=0,SAVINGS+FAMILY,EQ_PCT*FUND_BASE) -> 1.7687849e+08
B80: Debt facility (cap) | C80: ETB | D80: =IF(PROJECT_MODE=0,HOME_LOAN,IF(LOAN_CAP>0,MIN(LOAN_CAP,(1-EQ_PCT)*FUND_BASE),(1-EQ_PCT)*FUND_BASE)) -> 2.6531774e+08
B81: Equity share for pro-rata draws | C81: % | D81: =IF(EQ_COMMIT+DEBT_CAP>0,EQ_COMMIT/(EQ_COMMIT+DEBT_CAP),1) -> 0.4
B82: Peak cumulative funding requirement | C82: ETB | D82: =$D$42 -> 4.4899533e+08
B83: Equity drawn (committed) | C83: ETB | D83: =$D$70 -> 1.7687849e+08
B84: Debt drawn | C84: ETB | D84: =$D$71 -> 1.1561421e+08
B85: Sponsor top-up / funding gap | C85: ETB | D85: =$D$69 -> 0
B86: Presale cash used for construction | C86: ETB | D86: =$D$63 -> 1.5650262e+08
B87: Handover collections at completion | C87: ETB | D87: =$D$54 -> 98231357
B88: Total retention withheld | C88: ETB | D88: =$D$33 -> 15966117
B89: Land paid in cash in month 1 | C89: ETB | D89: =$D$34 -> 15000000
B90: Sources − uses (should be 0) | C90: ETB | D90: =$D$74 -> 0

Sheet 24_Revenue
B1: 24 · Revenue – sales, rent, other income | R1: =HYPERLINK("#'00_Start'!A1","◂ Start") -> ◂ Start
B2: ገቢ – ሽያጭ፣ ኪራይና ሌሎች
B3: =PROJ_NAME&" | Scenario: "&SCEN_NAME&" | Mode: "&MODE_NAME -> SAMPLE B — B+G+8 mixed-use building, Addis Ababa | Scenario: Base | Mode: 3 Mixed
B5: =IF(PROJECT_MODE=0,"Not needed for personal projects — switch mode to Commercial (1–3) on the Start sheet to see profitability. · ለግል ፕሮጀክት አያስፈልግም — ትርፋማነትን ለማየት በመጀመሪያ ገጽ ላይ ዓይነቱን ወደ ንግድ (1–3) ይቀይሩ።","")
B6: Period | D6: Total | E6: ='20_Timeline'!E12 -> C1 | F6: ='20_Timeline'!F12 -> C2 | G6: ='20_Timeline'!G12 -> C3 | H6: ='20_Timeline'!H12 -> C4 | I6: ='20_Timeline'!I12 -> O1 | J6: ='20_Timeline'!J12 -> O2 | K6: ='20_Timeline'!K12 -> O3 | L6: ='20_Timeline'!L12 -> O4 | ... R6: ='20_Timeline'!R12 -> O10
B7: Period end (Gregorian) | E7: ='20_Timeline'!E22 -> 46752 | F7: ='20_Timeline'!F22 -> 47118 | G7: ='20_Timeline'!G22 -> 47299 | H7: ='20_Timeline'!H22 -> 47299 | I7: ='20_Timeline'!I22 -> 47664 | J7: ='20_Timeline'!J22 -> 48029 | K7: ='20_Timeline'!K22 -> 48395 | L7: ='20_Timeline'!L22 -> 48760 | ... R7: ='20_Timeline'!R22 -> 50951
B8: Ethiopian calendar year | E8: ='20_Timeline'!E26 -> EC 2020 | F8: ='20_Timeline'!F26 -> EC 2021 | G8: ='20_Timeline'!G26 -> EC 2021 | H8: ='20_Timeline'!H26 -> EC 2021 | I8: ='20_Timeline'!I26 -> EC 2022 | J8: ='20_Timeline'!J26 -> EC 2023 | K8: ='20_Timeline'!K26 -> EC 2024 | L8: ='20_Timeline'!L26 -> EC 2025 | ... R8: ='20_Timeline'!R26 -> EC 2031
B10: Presale bands (effective after scenario, capped at 100%) | C10: የቅድመ-ሽያጭ ድርሻ
B11: Presale band 1 – raw | C11: % | D11: =PRESALE_1*D_PRESALE_F*IF('20_Timeline'!E15>0,1,0) -> 0.25
B12: Presale band 2 – raw | C12: % | D12: =PRESALE_2*D_PRESALE_F*IF('20_Timeline'!F15>0,1,0) -> 0.25
B13: Presale band 3 – raw | C13: % | D13: =PRESALE_3*D_PRESALE_F*IF('20_Timeline'!G15>0,1,0) -> 0.2
B14: Presale band 4 – raw | C14: % | D14: =PRESALE_4*D_PRESALE_F*IF('20_Timeline'!H15>0,1,0) -> 0
B15: Presales raw total | C15: % | D15: =SUM(D11:D14) -> 0.7
B16: Presale band 1 – effective | C16: % | D16: =D11*IF(D15>1,1/D15,1) -> 0.25
B17: Presale band 2 – effective | C17: % | D17: =D12*IF(D15>1,1/D15,1) -> 0.25
B18: Presale band 3 – effective | C18: % | D18: =D13*IF(D15>1,1/D15,1) -> 0.2
B19: Presale band 4 – effective | C19: % | D19: =D14*IF(D15>1,1/D15,1) -> 0
B20: Total presold share | C20: % | D20: =SUM(PS_EFF) -> 0.7
B21: Unsold area at completion | C21: m² | D21: =SALE_AREA*(1-PRESOLD) -> 1008
B22: Absorption O1 – effective | C22: % | D22: =MIN(1,ABS_1*ABS_F) -> 0.6
B23: Absorption O2 – effective | C23: % | D23: =MIN(1,ABS_2*ABS_F) -> 0.4
B24: Absorption O3 – effective | C24: % | D24: =MIN(1,ABS_3*ABS_F) -> 0
B25: Absorption O4 – effective | C25: % | D25: =MIN(1,ABS_4*ABS_F) -> 0
B27: Sales – presales (from monthly sheet) | C27: ቅድመ-ሽያጭ
B28: Area presold | C28: m² | D28: =SUM(E28:R28) -> 2352 | E28: =SUMIFS('23_Construction'!$E$46:$AZ$46,'23_Construction'!$E$12:$AZ$12,'20_Timeline'!E11) -> 840 | F28: =SUMIFS('23_Construction'!$E$46:$AZ$46,'23_Construction'!$E$12:$AZ$12,'20_Timeline'!F11) -> 840 | G28: =SUMIFS('23_Construction'!$E$46:$AZ$46,'23_Construction'!$E$12:$AZ$12,'20_Timeline'!G11) -> 672 | H28: =SUMIFS('23_Construction'!$E$46:$AZ$46,'23_Construction'!$E$12:$AZ$12,'20_Timeline'!H11) -> 0 | I28: =SUMIFS('23_Construction'!$E$46:$AZ$46,'23_Construction'!$E$12:$AZ$12,'20_Timeline'!I11) -> 0 | J28: =SUMIFS('23_Construction'!$E$46:$AZ$46,'23_Construction'!$E$12:$AZ$12,'20_Timeline'!J11) -> 0 | K28: =SUMIFS('23_Construction'!$E$46:$AZ$46,'23_Construction'!$E$12:$AZ$12,'20_Timeline'!K11) -> 0 | L28: =SUMIFS('23_Construction'!$E$46:$AZ$46,'23_Construction'!$E$12:$AZ$12,'20_Timeline'!L11) -> 0 | ... R28: =SUMIFS('23_Construction'!$E$46:$AZ$46,'23_Construction'!$E$12:$AZ$12,'20_Timeline'!R11) -> 0
B29: Contract value signed | C29: ETB | D29: =SUM(E29:R29) -> 3.2743786e+08 | E29: =SUMIFS('23_Construction'!$E$48:$AZ$48,'23_Construction'!$E$12:$AZ$12,'20_Timeline'!E11) -> 1.075351e+08 | F29: =SUMIFS('23_Construction'!$E$48:$AZ$48,'23_Construction'!$E$12:$AZ$12,'20_Timeline'!F11) -> 1.1828861e+08 | G29: =SUMIFS('23_Construction'!$E$48:$AZ$48,'23_Construction'!$E$12:$AZ$12,'20_Timeline'!G11) -> 1.0161414e+08 | H29: =SUMIFS('23_Construction'!$E$48:$AZ$48,'23_Construction'!$E$12:$AZ$12,'20_Timeline'!H11) -> 0 | I29: =SUMIFS('23_Construction'!$E$48:$AZ$48,'23_Construction'!$E$12:$AZ$12,'20_Timeline'!I11) -> 0 | J29: =SUMIFS('23_Construction'!$E$48:$AZ$48,'23_Construction'!$E$12:$AZ$12,'20_Timeline'!J11) -> 0 | K29: =SUMIFS('23_Construction'!$E$48:$AZ$48,'23_Construction'!$E$12:$AZ$12,'20_Timeline'!K11) -> 0 | L29: =SUMIFS('23_Construction'!$E$48:$AZ$48,'23_Construction'!$E$12:$AZ$12,'20_Timeline'!L11) -> 0 | ... R29: =SUMIFS('23_Construction'!$E$48:$AZ$48,'23_Construction'!$E$12:$AZ$12,'20_Timeline'!R11) -> 0
B30: Presale collections | C30: ETB | D30: =SUM(E30:R30) -> 3.2743786e+08 | E30: =SUMIFS('23_Construction'!$E$55:$AZ$55,'23_Construction'!$E$12:$AZ$12,'20_Timeline'!E11) -> 45495620 | F30: =SUMIFS('23_Construction'!$E$55:$AZ$55,'23_Construction'!$E$12:$AZ$12,'20_Timeline'!F11) -> 1.0726748e+08 | G30: =SUMIFS('23_Construction'!$E$55:$AZ$55,'23_Construction'!$E$12:$AZ$12,'20_Timeline'!G11) -> 1.7467476e+08 | H30: =SUMIFS('23_Construction'!$E$55:$AZ$55,'23_Construction'!$E$12:$AZ$12,'20_Timeline'!H11) -> 0 | I30: =SUMIFS('23_Construction'!$E$55:$AZ$55,'23_Construction'!$E$12:$AZ$12,'20_Timeline'!I11) -> 0 | J30: =SUMIFS('23_Construction'!$E$55:$AZ$55,'23_Construction'!$E$12:$AZ$12,'20_Timeline'!J11) -> 0 | K30: =SUMIFS('23_Construction'!$E$55:$AZ$55,'23_Construction'!$E$12:$AZ$12,'20_Timeline'!K11) -> 0 | L30: =SUMIFS('23_Construction'!$E$55:$AZ$55,'23_Construction'!$E$12:$AZ$12,'20_Timeline'!L11) -> 0 | ... R30: =SUMIFS('23_Construction'!$E$55:$AZ$55,'23_Construction'!$E$12:$AZ$12,'20_Timeline'!R11) -> 0
B31: Presale revenue recognised | C31: ETB | D31: =SUM(E31:R31) -> 3.2743786e+08 | E31: =SUMIFS('23_Construction'!$E$57:$AZ$57,'23_Construction'!$E$12:$AZ$12,'20_Timeline'!E11) -> 0 | F31: =SUMIFS('23_Construction'!$E$57:$AZ$57,'23_Construction'!$E$12:$AZ$12,'20_Timeline'!F11) -> 0 | G31: =SUMIFS('23_Construction'!$E$57:$AZ$57,'23_Construction'!$E$12:$AZ$12,'20_Timeline'!G11) -> 3.2743786e+08 | H31: =SUMIFS('23_Construction'!$E$57:$AZ$57,'23_Construction'!$E$12:$AZ$12,'20_Timeline'!H11) -> 0 | I31: =SUMIFS('23_Construction'!$E$57:$AZ$57,'23_Construction'!$E$12:$AZ$12,'20_Timeline'!I11) -> 0 | J31: =SUMIFS('23_Construction'!$E$57:$AZ$57,'23_Construction'!$E$12:$AZ$12,'20_Timeline'!J11) -> 0 | K31: =SUMIFS('23_Construction'!$E$57:$AZ$57,'23_Construction'!$E$12:$AZ$12,'20_Timeline'!K11) -> 0 | L31: =SUMIFS('23_Construction'!$E$57:$AZ$57,'23_Construction'!$E$12:$AZ$12,'20_Timeline'!L11) -> 0 | ... R31: =SUMIFS('23_Construction'!$E$57:$AZ$57,'23_Construction'!$E$12:$AZ$12,'20_Timeline'!R11) -> 0
B32: Presale cost of sales | C32: ETB | D32: =SUM(E32:R32) -> 2.9006794e+08 | E32: =SUMIFS('23_Construction'!$E$59:$AZ$59,'23_Construction'!$E$12:$AZ$12,'20_Timeline'!E11) -> 0 | F32: =SUMIFS('23_Construction'!$E$59:$AZ$59,'23_Construction'!$E$12:$AZ$12,'20_Timeline'!F11) -> 0 | G32: =SUMIFS('23_Construction'!$E$59:$AZ$59,'23_Construction'!$E$12:$AZ$12,'20_Timeline'!G11) -> 2.9006794e+08 | H32: =SUMIFS('23_Construction'!$E$59:$AZ$59,'23_Construction'!$E$12:$AZ$12,'20_Timeline'!H11) -> 0 | I32: =SUMIFS('23_Construction'!$E$59:$AZ$59,'23_Construction'!$E$12:$AZ$12,'20_Timeline'!I11) -> 0 | J32: =SUMIFS('23_Construction'!$E$59:$AZ$59,'23_Construction'!$E$12:$AZ$12,'20_Timeline'!J11) -> 0 | K32: =SUMIFS('23_Construction'!$E$59:$AZ$59,'23_Construction'!$E$12:$AZ$12,'20_Timeline'!K11) -> 0 | L32: =SUMIFS('23_Construction'!$E$59:$AZ$59,'23_Construction'!$E$12:$AZ$12,'20_Timeline'!L11) -> 0 | ... R32: =SUMIFS('23_Construction'!$E$59:$AZ$59,'23_Construction'!$E$12:$AZ$12,'20_Timeline'!R11) -> 0
B33: Sales – after completion (point in time, cash on sale) | C33: ከግንባታ በኋላ ሽያጭ
B34: Area sold | C34: m² | D34: =SUM(E34:R34) -> 1008 | E34: 0 | F34: 0 | G34: 0 | H34: 0 | I34: =MIN(UNSOLD_AREA,UNSOLD_AREA*$D$22) -> 604.8 | J34: =MIN(I35,UNSOLD_AREA*$D$23) -> 403.2 | K34: =MIN(J35,UNSOLD_AREA*$D$24) -> 0 | L34: =MIN(K35,UNSOLD_AREA*$D$25) -> 0 | M34: =L35 -> 0 | N34: 0 | O34: 0 | P34: 0 | Q34: 0 | R34: 0
B35: Unsold area remaining | C35: m² | D35: =R35 -> 0 | E35: 0 | F35: 0 | G35: 0 | H35: 0 | I35: =UNSOLD_AREA-I34 -> 403.2 | J35: =I35-J34 -> 0 | K35: =J35-K34 -> 0 | L35: =K35-L34 -> 0 | M35: =L35-M34 -> 0 | N35: =M35-N34 -> 0 | O35: =N35-O34 -> 0 | P35: =O35-P34 -> 0 | Q35: =P35-Q34 -> 0 | R35: =Q35-R34 -> 0
B36: Sale price (escalated) | C36: ETB/m² | E36: 0 | F36: 0 | G36: 0 | H36: 0 | I36: =BLEND_PRICE*(1+PESC_EFF)^(CONSTR_EFF/12+'20_Timeline'!I14-0.5) -> 166375 | J36: =BLEND_PRICE*(1+PESC_EFF)^(CONSTR_EFF/12+'20_Timeline'!J14-0.5) -> 183012.5 | K36: =BLEND_PRICE*(1+PESC_EFF)^(CONSTR_EFF/12+'20_Timeline'!K14-0.5) -> 201313.75 | L36: =BLEND_PRICE*(1+PESC_EFF)^(CONSTR_EFF/12+'20_Timeline'!L14-0.5) -> 221445.12 | M36: =BLEND_PRICE*(1+PESC_EFF)^(CONSTR_EFF/12+'20_Timeline'!M14-0.5) -> 243589.64 | N36: =BLEND_PRICE*(1+PESC_EFF)^(CONSTR_EFF/12+'20_Timeline'!N14-0.5) -> 267948.6 | O36: =BLEND_PRICE*(1+PESC_EFF)^(CONSTR_EFF/12+'20_Timeline'!O14-0.5) -> 294743.46 | P36: =BLEND_PRICE*(1+PESC_EFF)^(CONSTR_EFF/12+'20_Timeline'!P14-0.5) -> 324217.81 | ... R36: =BLEND_PRICE*(1+PESC_EFF)^(CONSTR_EFF/12+'20_Timeline'!R14-0.5) -> 392303.55
B37: Sales revenue = collections | C37: ETB | D37: =SUM(E37:R37) -> 1.7092596e+08 | E37: =E34*E36*(1-DEFAULT_EFF) -> 0 | F37: =F34*F36*(1-DEFAULT_EFF) -> 0 | G37: =G34*G36*(1-DEFAULT_EFF) -> 0 | H37: =H34*H36*(1-DEFAULT_EFF) -> 0 | I37: =I34*I36*(1-DEFAULT_EFF) -> 98611128 | J37: =J34*J36*(1-DEFAULT_EFF) -> 72314827 | K37: =K34*K36*(1-DEFAULT_EFF) -> 0 | L37: =L34*L36*(1-DEFAULT_EFF) -> 0 | ... R37: =R34*R36*(1-DEFAULT_EFF) -> 0
B38: Cost of sales | C38: ETB | D38: =SUM(E38:R38) -> 1.2431483e+08 | E38: =IF(SALE_AREA>0,TDC_INV*E34/SALE_AREA,0) -> 0 | F38: =IF(SALE_AREA>0,TDC_INV*F34/SALE_AREA,0) -> 0 | G38: =IF(SALE_AREA>0,TDC_INV*G34/SALE_AREA,0) -> 0 | H38: =IF(SALE_AREA>0,TDC_INV*H34/SALE_AREA,0) -> 0 | I38: =IF(SALE_AREA>0,TDC_INV*I34/SALE_AREA,0) -> 74588898 | J38: =IF(SALE_AREA>0,TDC_INV*J34/SALE_AREA,0) -> 49725932 | K38: =IF(SALE_AREA>0,TDC_INV*K34/SALE_AREA,0) -> 0 | L38: =IF(SALE_AREA>0,TDC_INV*L34/SALE_AREA,0) -> 0 | ... R38: =IF(SALE_AREA>0,TDC_INV*R34/SALE_AREA,0) -> 0
B39: Sales totals and contract balances (IFRS 15) | C39: የሽያጭ ድምር
B40: Sales revenue recognised | C40: ETB | D40: =SUM(E40:R40) -> 4.9836381e+08 | E40: =E31+E37 -> 0 | F40: =F31+F37 -> 0 | G40: =G31+G37 -> 3.2743786e+08 | H40: =H31+H37 -> 0 | I40: =I31+I37 -> 98611128 | J40: =J31+J37 -> 72314827 | K40: =K31+K37 -> 0 | L40: =L31+L37 -> 0 | ... R40: =R31+R37 -> 0
B41: Sales cash collected | C41: ETB | D41: =SUM(E41:R41) -> 4.9836381e+08 | E41: =E30+E37 -> 45495620 | F41: =F30+F37 -> 1.0726748e+08 | G41: =G30+G37 -> 1.7467476e+08 | H41: =H30+H37 -> 0 | I41: =I30+I37 -> 98611128 | J41: =J30+J37 -> 72314827 | K41: =K30+K37 -> 0 | L41: =L30+L37 -> 0 | ... R41: =R30+R37 -> 0
B42: Cost of sales (IAS 2) | C42: ETB | D42: =SUM(E42:R42) -> 4.1438277e+08 | E42: =E32+E38 -> 0 | F42: =F32+F38 -> 0 | G42: =G32+G38 -> 2.9006794e+08 | H42: =H32+H38 -> 0 | I42: =I32+I38 -> 74588898 | J42: =J32+J38 -> 49725932 | K42: =K32+K38 -> 0 | L42: =L32+L38 -> 0 | ... R42: =R32+R38 -> 0
B43: Contract value signed in period | C43: ETB | D43: =SUM(E43:R43) -> 4.9836381e+08 | E43: =E29+E37 -> 1.075351e+08 | F43: =F29+F37 -> 1.1828861e+08 | G43: =G29+G37 -> 1.0161414e+08 | H43: =H29+H37 -> 0 | I43: =I29+I37 -> 98611128 | J43: =J29+J37 -> 72314827 | K43: =K29+K37 -> 0 | L43: =L29+L37 -> 0 | ... R43: =R29+R37 -> 0
B44: Sales commission | C44: ETB | D44: =SUM(E44:R44) -> 9967276.2 | E44: =COMM_PCT*E40 -> 0 | F44: =COMM_PCT*F40 -> 0 | G44: =COMM_PCT*G40 -> 6548757.1 | H44: =COMM_PCT*H40 -> 0 | I44: =COMM_PCT*I40 -> 1972222.6 | J44: =COMM_PCT*J40 -> 1446296.5 | K44: =COMM_PCT*K40 -> 0 | L44: =COMM_PCT*L40 -> 0 | ... R44: =COMM_PCT*R40 -> 0
B45: Marketing | C45: ETB | D45: =SUM(E45:R45) -> 4983638.1 | E45: =MKT_PCT*E43 -> 1075351 | F45: =MKT_PCT*F43 -> 1182886.1 | G45: =MKT_PCT*G43 -> 1016141.4 | H45: =MKT_PCT*H43 -> 0 | I45: =MKT_PCT*I43 -> 986111.28 | J45: =MKT_PCT*J43 -> 723148.27 | K45: =MKT_PCT*K43 -> 0 | L45: =MKT_PCT*L43 -> 0 | ... R45: =MKT_PCT*R43 -> 0
B46: Cumulative collections | C46: ETB | D46: =R46 -> 4.9836381e+08 | E46: =0+E41 -> 45495620 | F46: =E46+F41 -> 1.527631e+08 | G46: =F46+G41 -> 3.2743786e+08 | H46: =G46+H41 -> 3.2743786e+08 | I46: =H46+I41 -> 4.2604898e+08 | J46: =I46+J41 -> 4.9836381e+08 | K46: =J46+K41 -> 4.9836381e+08 | L46: =K46+L41 -> 4.9836381e+08 | M46: =L46+M41 -> 4.9836381e+08 | ... R46: =Q46+R41 -> 4.9836381e+08
B47: Cumulative revenue | C47: ETB | D47: =R47 -> 4.9836381e+08 | E47: =0+E40 -> 0 | F47: =E47+F40 -> 0 | G47: =F47+G40 -> 3.2743786e+08 | H47: =G47+H40 -> 3.2743786e+08 | I47: =H47+I40 -> 4.2604898e+08 | J47: =I47+J40 -> 4.9836381e+08 | K47: =J47+K40 -> 4.9836381e+08 | L47: =K47+L40 -> 4.9836381e+08 | M47: =L47+M40 -> 4.9836381e+08 | ... R47: =Q47+R40 -> 4.9836381e+08
B48: Contract balance (+ liability / − asset) | C48: ETB | D48: =R48 -> 0 | E48: =E46-E47 -> 45495620 | F48: =F46-F47 -> 1.527631e+08 | G48: =G46-G47 -> 0 | H48: =H46-H47 -> 0 | I48: =I46-I47 -> 0 | J48: =J46-J47 -> 0 | K48: =K46-K47 -> 0 | L48: =L46-L47 -> 0 | ... R48: =R46-R47 -> 0
B49: Contract liability | C49: ETB | D49: =R49 -> 0 | E49: =MAX(0,E48) -> 45495620 | F49: =MAX(0,F48) -> 1.527631e+08 | G49: =MAX(0,G48) -> 0 | H49: =MAX(0,H48) -> 0 | I49: =MAX(0,I48) -> 0 | J49: =MAX(0,J48) -> 0 | K49: =MAX(0,K48) -> 0 | L49: =MAX(0,L48) -> 0 | ... R49: =MAX(0,R48) -> 0
B50: Contract asset | C50: ETB | D50: =R50 -> 0 | E50: =MAX(0,-E48) -> 0 | F50: =MAX(0,-F48) -> 0 | G50: =MAX(0,-G48) -> 0 | H50: =MAX(0,-H48) -> 0 | I50: =MAX(0,-I48) -> 0 | J50: =MAX(0,-J48) -> 0 | K50: =MAX(0,-K48) -> 0 | L50: =MAX(0,-L48) -> 0 | ... R50: =MAX(0,-R48) -> 0
B51: Sales collections in operating year (for sweep) | C51: ETB | D51: =SUM(E51:R51) -> 1.7092596e+08 | E51: 0 | F51: 0 | G51: 0 | H51: 0 | I51: =I41 -> 98611128 | J51: =J41 -> 72314827 | K51: =K41 -> 0 | L51: =L41 -> 0 | M51: =M41 -> 0 | N51: =N41 -> 0 | O51: =O41 -> 0 | P51: =P41 -> 0 | ... R51: =R41 -> 0
B52: Rent (IFRS 16 lessor) | C52: ኪራይ
B53: Gross potential rent | C53: ETB | D53: =SUM(E53:R53) -> 4.6569144e+08 | E53: 0 | F53: 0 | G53: 0 | H53: 0 | I53: =GPR_TODAY*D_RENT_F*(1+RESC_EFF)^(CONSTR_EFF/12+'20_Timeline'!I14-1) -> 32146442 | J53: =GPR_TODAY*D_RENT_F*(1+RESC_EFF)^(CONSTR_EFF/12+'20_Timeline'!J14-1) -> 34718157 | K53: =GPR_TODAY*D_RENT_F*(1+RESC_EFF)^(CONSTR_EFF/12+'20_Timeline'!K14-1) -> 37495610 | L53: =GPR_TODAY*D_RENT_F*(1+RESC_EFF)^(CONSTR_EFF/12+'20_Timeline'!L14-1) -> 40495258 | M53: =GPR_TODAY*D_RENT_F*(1+RESC_EFF)^(CONSTR_EFF/12+'20_Timeline'!M14-1) -> 43734879 | N53: =GPR_TODAY*D_RENT_F*(1+RESC_EFF)^(CONSTR_EFF/12+'20_Timeline'!N14-1) -> 47233669 | O53: =GPR_TODAY*D_RENT_F*(1+RESC_EFF)^(CONSTR_EFF/12+'20_Timeline'!O14-1) -> 51012363 | P53: =GPR_TODAY*D_RENT_F*(1+RESC_EFF)^(CONSTR_EFF/12+'20_Timeline'!P14-1) -> 55093352 | ... R53: =GPR_TODAY*D_RENT_F*(1+RESC_EFF)^(CONSTR_EFF/12+'20_Timeline'!R14-1) -> 64260886
B54: Occupancy | C54: % | E54: 0 | F54: 0 | G54: 0 | H54: 0 | I54: =MIN(1,MAX(0,(CHOOSE(MIN('20_Timeline'!I14,3),OCC_O1,OCC_O2,OCC_STAB)+D_OCC_ADD)*D_OCC_F)) -> 0.6 | J54: =MIN(1,MAX(0,(CHOOSE(MIN('20_Timeline'!J14,3),OCC_O1,OCC_O2,OCC_STAB)+D_OCC_ADD)*D_OCC_F)) -> 0.8 | K54: =MIN(1,MAX(0,(CHOOSE(MIN('20_Timeline'!K14,3),OCC_O1,OCC_O2,OCC_STAB)+D_OCC_ADD)*D_OCC_F)) -> 0.92 | L54: =MIN(1,MAX(0,(CHOOSE(MIN('20_Timeline'!L14,3),OCC_O1,OCC_O2,OCC_STAB)+D_OCC_ADD)*D_OCC_F)) -> 0.92 | M54: =MIN(1,MAX(0,(CHOOSE(MIN('20_Timeline'!M14,3),OCC_O1,OCC_O2,OCC_STAB)+D_OCC_ADD)*D_OCC_F)) -> 0.92 | N54: =MIN(1,MAX(0,(CHOOSE(MIN('20_Timeline'!N14,3),OCC_O1,OCC_O2,OCC_STAB)+D_OCC_ADD)*D_OCC_F)) -> 0.92 | O54: =MIN(1,MAX(0,(CHOOSE(MIN('20_Timeline'!O14,3),OCC_O1,OCC_O2,OCC_STAB)+D_OCC_ADD)*D_OCC_F)) -> 0.92 | P54: =MIN(1,MAX(0,(CHOOSE(MIN('20_Timeline'!P14,3),OCC_O1,OCC_O2,OCC_STAB)+D_OCC_ADD)*D_OCC_F)) -> 0.92 | ... R54: =MIN(1,MAX(0,(CHOOSE(MIN('20_Timeline'!R14,3),OCC_O1,OCC_O2,OCC_STAB)+D_OCC_ADD)*D_OCC_F)) -> 0.92
B55: Rental income | C55: ETB | D55: =SUM(E55:R55) -> 4.1398308e+08 | E55: =E53*E54 -> 0 | F55: =F53*F54 -> 0 | G55: =G53*G54 -> 0 | H55: =H53*H54 -> 0 | I55: =I53*I54 -> 19287865 | J55: =J53*J54 -> 27774526 | K55: =K53*K54 -> 34495961 | L55: =L53*L54 -> 37255638 | ... R55: =R53*R54 -> 59120015
B56: Key money received | C56: ETB | D56: =SUM(E56:R56) -> 9643932.5 | E56: 0 | F56: 0 | G56: 0 | H56: 0 | I56: =IF(PROJECT_MODE=0,0,KEY_MONTHS*I55/12) -> 9643932.5 | J56: 0 | K56: 0 | L56: 0 | M56: 0 | N56: 0 | O56: 0 | P56: 0 | Q56: 0 | R56: 0
B57: Key money released to income | C57: ETB | D57: =SUM(E57:R57) -> 9643932.5 | E57: 0 | F57: 0 | G57: 0 | H57: 0 | I57: =IF('20_Timeline'!I14<=MAX(1,KEY_AMORT_Y),$D$56/MAX(1,KEY_AMORT_Y),0) -> 1928786.5 | J57: =IF('20_Timeline'!J14<=MAX(1,KEY_AMORT_Y),$D$56/MAX(1,KEY_AMORT_Y),0) -> 1928786.5 | K57: =IF('20_Timeline'!K14<=MAX(1,KEY_AMORT_Y),$D$56/MAX(1,KEY_AMORT_Y),0) -> 1928786.5 | L57: =IF('20_Timeline'!L14<=MAX(1,KEY_AMORT_Y),$D$56/MAX(1,KEY_AMORT_Y),0) -> 1928786.5 | M57: =IF('20_Timeline'!M14<=MAX(1,KEY_AMORT_Y),$D$56/MAX(1,KEY_AMORT_Y),0) -> 1928786.5 | N57: =IF('20_Timeline'!N14<=MAX(1,KEY_AMORT_Y),$D$56/MAX(1,KEY_AMORT_Y),0) -> 0 | O57: =IF('20_Timeline'!O14<=MAX(1,KEY_AMORT_Y),$D$56/MAX(1,KEY_AMORT_Y),0) -> 0 | P57: =IF('20_Timeline'!P14<=MAX(1,KEY_AMORT_Y),$D$56/MAX(1,KEY_AMORT_Y),0) -> 0 | ... R57: =IF('20_Timeline'!R14<=MAX(1,KEY_AMORT_Y),$D$56/MAX(1,KEY_AMORT_Y),0) -> 0
B58: Deferred key money (liability) | C58: ETB | D58: =R58 -> 0 | E58: =0+E56-E57 -> 0 | F58: =E58+F56-F57 -> 0 | G58: =F58+G56-G57 -> 0 | H58: =G58+H56-H57 -> 0 | I58: =H58+I56-I57 -> 7715146 | J58: =I58+J56-J57 -> 5786359.5 | K58: =J58+K56-K57 -> 3857573 | L58: =K58+L56-L57 -> 1928786.5 | M58: =L58+M56-M57 -> 0 | ... R58: =Q58+R56-R57 -> 0
B59: Service charge recoveries | C59: ETB | D59: =SUM(E59:R59) -> 37258477 | E59: =SC_RECOV*'25_Opex'!E12 -> 0 | F59: =SC_RECOV*'25_Opex'!F12 -> 0 | G59: =SC_RECOV*'25_Opex'!G12 -> 0 | H59: =SC_RECOV*'25_Opex'!H12 -> 0 | I59: =SC_RECOV*'25_Opex'!I12 -> 1735907.9 | J59: =SC_RECOV*'25_Opex'!J12 -> 2499707.3 | K59: =SC_RECOV*'25_Opex'!K12 -> 3104636.5 | L59: =SC_RECOV*'25_Opex'!L12 -> 3353007.4 | ... R59: =SC_RECOV*'25_Opex'!R12 -> 5320801.3
B60: Other income | C60: ETB | D60: =SUM(E60:R60) -> 9562454.8 | E60: 0 | F60: 0 | G60: 0 | H60: 0 | I60: =IF(PROJECT_MODE=0,0,OTHER_INC*(1+OPEX_ESC)^('20_Timeline'!I14-1)) -> 600000 | J60: =IF(PROJECT_MODE=0,0,OTHER_INC*(1+OPEX_ESC)^('20_Timeline'!J14-1)) -> 660000 | K60: =IF(PROJECT_MODE=0,0,OTHER_INC*(1+OPEX_ESC)^('20_Timeline'!K14-1)) -> 726000 | L60: =IF(PROJECT_MODE=0,0,OTHER_INC*(1+OPEX_ESC)^('20_Timeline'!L14-1)) -> 798600 | M60: =IF(PROJECT_MODE=0,0,OTHER_INC*(1+OPEX_ESC)^('20_Timeline'!M14-1)) -> 878460 | N60: =IF(PROJECT_MODE=0,0,OTHER_INC*(1+OPEX_ESC)^('20_Timeline'!N14-1)) -> 966306 | O60: =IF(PROJECT_MODE=0,0,OTHER_INC*(1+OPEX_ESC)^('20_Timeline'!O14-1)) -> 1062936.6 | P60: =IF(PROJECT_MODE=0,0,OTHER_INC*(1+OPEX_ESC)^('20_Timeline'!P14-1)) -> 1169230.3 | ... R60: =IF(PROJECT_MODE=0,0,OTHER_INC*(1+OPEX_ESC)^('20_Timeline'!R14-1)) -> 1414768.6
B61: TOTAL REVENUE | C61: ETB | D61: =SUM(E61:R61) -> 9.6881176e+08 | E61: =E40+E55+E57+E59+E60 -> 0 | F61: =F40+F55+F57+F59+F60 -> 0 | G61: =G40+G55+G57+G59+G60 -> 3.2743786e+08 | H61: =H40+H55+H57+H59+H60 -> 0 | I61: =I40+I55+I57+I59+I60 -> 1.2216369e+08 | J61: =J40+J55+J57+J59+J60 -> 1.0517785e+08 | K61: =K40+K55+K57+K59+K60 -> 40255384 | L61: =L40+L55+L57+L59+L60 -> 43336032 | ... R61: =R40+R55+R57+R59+R60 -> 65855585
B62: Net operating income of let property (NOI) | C62: ETB | D62: =SUM(E62:R62) -> 3.6526901e+08 | E62: =E55+E59+E60-'25_Opex'!E12-'25_Opex'!E13-'25_Opex'!E14-'25_Opex'!E15-'25_Opex'!E16-'25_Opex'!E19 -> 0 | F62: =F55+F59+F60-'25_Opex'!F12-'25_Opex'!F13-'25_Opex'!F14-'25_Opex'!F15-'25_Opex'!F16-'25_Opex'!F19 -> 0 | G62: =G55+G59+G60-'25_Opex'!G12-'25_Opex'!G13-'25_Opex'!G14-'25_Opex'!G15-'25_Opex'!G16-'25_Opex'!G19 -> 0 | H62: =H55+H59+H60-'25_Opex'!H12-'25_Opex'!H13-'25_Opex'!H14-'25_Opex'!H15-'25_Opex'!H16-'25_Opex'!H19 -> 0 | I62: =I55+I59+I60-'25_Opex'!I12-'25_Opex'!I13-'25_Opex'!I14-'25_Opex'!I15-'25_Opex'!I16-'25_Opex'!I19 -> 16966925 | J62: =J55+J59+J60-'25_Opex'!J12-'25_Opex'!J13-'25_Opex'!J14-'25_Opex'!J15-'25_Opex'!J16-'25_Opex'!J19 -> 24500125 | K62: =K55+K59+K60-'25_Opex'!K12-'25_Opex'!K13-'25_Opex'!K14-'25_Opex'!K15-'25_Opex'!K16-'25_Opex'!K19 -> 30460282 | L62: =L55+L59+L60-'25_Opex'!L12-'25_Opex'!L13-'25_Opex'!L14-'25_Opex'!L15-'25_Opex'!L16-'25_Opex'!L19 -> 32892283 | ... R62: =R55+R59+R60-'25_Opex'!R12-'25_Opex'!R13-'25_Opex'!R14-'25_Opex'!R15-'25_Opex'!R16-'25_Opex'!R19 -> 52146933

Sheet 25_Opex
B1: 25 · Operating costs | R1: =HYPERLINK("#'00_Start'!A1","◂ Start") -> ◂ Start
B2: የሥራ ማስኬጃ ወጪዎች
B3: =PROJ_NAME&" | Scenario: "&SCEN_NAME&" | Mode: "&MODE_NAME -> SAMPLE B — B+G+8 mixed-use building, Addis Ababa | Scenario: Base | Mode: 3 Mixed
B5: =IF(PROJECT_MODE=0,"Not needed for personal projects — switch mode to Commercial (1–3) on the Start sheet to see profitability. · ለግል ፕሮጀክት አያስፈልግም — ትርፋማነትን ለማየት በመጀመሪያ ገጽ ላይ ዓይነቱን ወደ ንግድ (1–3) ይቀይሩ።","")
B6: Period | D6: Total | E6: ='20_Timeline'!E12 -> C1 | F6: ='20_Timeline'!F12 -> C2 | G6: ='20_Timeline'!G12 -> C3 | H6: ='20_Timeline'!H12 -> C4 | I6: ='20_Timeline'!I12 -> O1 | J6: ='20_Timeline'!J12 -> O2 | K6: ='20_Timeline'!K12 -> O3 | L6: ='20_Timeline'!L12 -> O4 | ... R6: ='20_Timeline'!R12 -> O10
B7: Period end (Gregorian) | E7: ='20_Timeline'!E22 -> 46752 | F7: ='20_Timeline'!F22 -> 47118 | G7: ='20_Timeline'!G22 -> 47299 | H7: ='20_Timeline'!H22 -> 47299 | I7: ='20_Timeline'!I22 -> 47664 | J7: ='20_Timeline'!J22 -> 48029 | K7: ='20_Timeline'!K22 -> 48395 | L7: ='20_Timeline'!L22 -> 48760 | ... R7: ='20_Timeline'!R22 -> 50951
B8: Ethiopian calendar year | E8: ='20_Timeline'!E26 -> EC 2020 | F8: ='20_Timeline'!F26 -> EC 2021 | G8: ='20_Timeline'!G26 -> EC 2021 | H8: ='20_Timeline'!H26 -> EC 2021 | I8: ='20_Timeline'!I26 -> EC 2022 | J8: ='20_Timeline'!J26 -> EC 2023 | K8: ='20_Timeline'!K26 -> EC 2024 | L8: ='20_Timeline'!L26 -> EC 2025 | ... R8: ='20_Timeline'!R26 -> EC 2031
B10: Operating costs (positive = cost) | C10: ወጪዎች
B11: Opex escalation index (from today) | C11: x | E11: 0 | F11: 0 | G11: 0 | H11: 0 | I11: =(1+OPEX_ESC)^(CONSTR_EFF/12+'20_Timeline'!I14-1) -> 1.2690587 | J11: =(1+OPEX_ESC)^(CONSTR_EFF/12+'20_Timeline'!J14-1) -> 1.3959646 | K11: =(1+OPEX_ESC)^(CONSTR_EFF/12+'20_Timeline'!K14-1) -> 1.535561 | L11: =(1+OPEX_ESC)^(CONSTR_EFF/12+'20_Timeline'!L14-1) -> 1.6891171 | M11: =(1+OPEX_ESC)^(CONSTR_EFF/12+'20_Timeline'!M14-1) -> 1.8580289 | N11: =(1+OPEX_ESC)^(CONSTR_EFF/12+'20_Timeline'!N14-1) -> 2.0438317 | O11: =(1+OPEX_ESC)^(CONSTR_EFF/12+'20_Timeline'!O14-1) -> 2.2482149 | P11: =(1+OPEX_ESC)^(CONSTR_EFF/12+'20_Timeline'!P14-1) -> 2.4730364 | ... R11: =(1+OPEX_ESC)^(CONSTR_EFF/12+'20_Timeline'!R14-1) -> 2.992374
B12: Property operating costs | C12: ETB | D12: =SUM(E12:R12) -> 62097462 | E12: 0 | F12: 0 | G12: 0 | H12: 0 | I12: =IF(OPEX_METHOD=1,OPEX_PCT*'24_Revenue'!I55,OPEX_M2*LET_AREA*I11)*D_OPEX_F -> 2893179.8 | J12: =IF(OPEX_METHOD=1,OPEX_PCT*'24_Revenue'!J55,OPEX_M2*LET_AREA*J11)*D_OPEX_F -> 4166178.9 | K12: =IF(OPEX_METHOD=1,OPEX_PCT*'24_Revenue'!K55,OPEX_M2*LET_AREA*K11)*D_OPEX_F -> 5174394.1 | L12: =IF(OPEX_METHOD=1,OPEX_PCT*'24_Revenue'!L55,OPEX_M2*LET_AREA*L11)*D_OPEX_F -> 5588345.7 | M12: =IF(OPEX_METHOD=1,OPEX_PCT*'24_Revenue'!M55,OPEX_M2*LET_AREA*M11)*D_OPEX_F -> 6035413.3 | N12: =IF(OPEX_METHOD=1,OPEX_PCT*'24_Revenue'!N55,OPEX_M2*LET_AREA*N11)*D_OPEX_F -> 6518246.4 | O12: =IF(OPEX_METHOD=1,OPEX_PCT*'24_Revenue'!O55,OPEX_M2*LET_AREA*O11)*D_OPEX_F -> 7039706.1 | P12: =IF(OPEX_METHOD=1,OPEX_PCT*'24_Revenue'!P55,OPEX_M2*LET_AREA*P11)*D_OPEX_F -> 7602882.6 | ... R12: =IF(OPEX_METHOD=1,OPEX_PCT*'24_Revenue'!R55,OPEX_M2*LET_AREA*R11)*D_OPEX_F -> 8868002.2
B13: Management fee | C13: ETB | D13: =SUM(E13:R13) -> 12419492 | E13: =MGMT_PCT*'24_Revenue'!E55 -> 0 | F13: =MGMT_PCT*'24_Revenue'!F55 -> 0 | G13: =MGMT_PCT*'24_Revenue'!G55 -> 0 | H13: =MGMT_PCT*'24_Revenue'!H55 -> 0 | I13: =MGMT_PCT*'24_Revenue'!I55 -> 578635.95 | J13: =MGMT_PCT*'24_Revenue'!J55 -> 833235.77 | K13: =MGMT_PCT*'24_Revenue'!K55 -> 1034878.8 | L13: =MGMT_PCT*'24_Revenue'!L55 -> 1117669.1 | ... R13: =MGMT_PCT*'24_Revenue'!R55 -> 1773600.4
B14: Insurance | C14: ETB | D14: =SUM(E14:R14) -> 2397514.5 | E14: 0 | F14: 0 | G14: 0 | H14: 0 | I14: =INS_PCT*HARD_ESC_TOT*RET_SH*I11*D_OPEX_F -> 150432.99 | J14: =INS_PCT*HARD_ESC_TOT*RET_SH*J11*D_OPEX_F -> 165476.29 | K14: =INS_PCT*HARD_ESC_TOT*RET_SH*K11*D_OPEX_F -> 182023.92 | L14: =INS_PCT*HARD_ESC_TOT*RET_SH*L11*D_OPEX_F -> 200226.32 | M14: =INS_PCT*HARD_ESC_TOT*RET_SH*M11*D_OPEX_F -> 220248.95 | N14: =INS_PCT*HARD_ESC_TOT*RET_SH*N11*D_OPEX_F -> 242273.84 | O14: =INS_PCT*HARD_ESC_TOT*RET_SH*O11*D_OPEX_F -> 266501.23 | P14: =INS_PCT*HARD_ESC_TOT*RET_SH*P11*D_OPEX_F -> 293151.35 | ... R14: =INS_PCT*HARD_ESC_TOT*RET_SH*R11*D_OPEX_F -> 354713.13
B15: Property tax | C15: ETB | D15: =SUM(E15:R15) -> 2349156.3 | E15: 0 | F15: 0 | G15: 0 | H15: 0 | I15: =PROPTAX_PCT*(HARD_ESC_TOT+LAND_TOT)*RET_SH*I11 -> 147398.74 | J15: =PROPTAX_PCT*(HARD_ESC_TOT+LAND_TOT)*RET_SH*J11 -> 162138.61 | K15: =PROPTAX_PCT*(HARD_ESC_TOT+LAND_TOT)*RET_SH*K11 -> 178352.47 | L15: =PROPTAX_PCT*(HARD_ESC_TOT+LAND_TOT)*RET_SH*L11 -> 196187.72 | M15: =PROPTAX_PCT*(HARD_ESC_TOT+LAND_TOT)*RET_SH*M11 -> 215806.49 | N15: =PROPTAX_PCT*(HARD_ESC_TOT+LAND_TOT)*RET_SH*N11 -> 237387.14 | O15: =PROPTAX_PCT*(HARD_ESC_TOT+LAND_TOT)*RET_SH*O11 -> 261125.85 | P15: =PROPTAX_PCT*(HARD_ESC_TOT+LAND_TOT)*RET_SH*P11 -> 287238.44 | ... R15: =PROPTAX_PCT*(HARD_ESC_TOT+LAND_TOT)*RET_SH*R11 -> 347558.51
B16: Maintenance reserve | C16: ETB | D16: =SUM(E16:R16) -> 7991715 | E16: 0 | F16: 0 | G16: 0 | H16: 0 | I16: =MAINT_PCT*HARD_ESC_TOT*RET_SH*I11*D_OPEX_F -> 501443.32 | J16: =MAINT_PCT*HARD_ESC_TOT*RET_SH*J11*D_OPEX_F -> 551587.65 | K16: =MAINT_PCT*HARD_ESC_TOT*RET_SH*K11*D_OPEX_F -> 606746.41 | L16: =MAINT_PCT*HARD_ESC_TOT*RET_SH*L11*D_OPEX_F -> 667421.05 | M16: =MAINT_PCT*HARD_ESC_TOT*RET_SH*M11*D_OPEX_F -> 734163.16 | N16: =MAINT_PCT*HARD_ESC_TOT*RET_SH*N11*D_OPEX_F -> 807579.48 | O16: =MAINT_PCT*HARD_ESC_TOT*RET_SH*O11*D_OPEX_F -> 888337.42 | P16: =MAINT_PCT*HARD_ESC_TOT*RET_SH*P11*D_OPEX_F -> 977171.17 | ... R16: =MAINT_PCT*HARD_ESC_TOT*RET_SH*R11*D_OPEX_F -> 1182377.1
B17: Marketing | C17: ETB | D17: =SUM(E17:R17) -> 4983638.1 | E17: ='24_Revenue'!E45 -> 1075351 | F17: ='24_Revenue'!F45 -> 1182886.1 | G17: ='24_Revenue'!G45 -> 1016141.4 | H17: ='24_Revenue'!H45 -> 0 | I17: ='24_Revenue'!I45 -> 986111.28 | J17: ='24_Revenue'!J45 -> 723148.27 | K17: ='24_Revenue'!K45 -> 0 | L17: ='24_Revenue'!L45 -> 0 | ... R17: ='24_Revenue'!R45 -> 0
B18: Owner overheads | C18: ETB | D18: =SUM(E18:R18) -> 24270633 | E18: 0 | F18: 0 | G18: 0 | H18: 0 | I18: =IF(PROJECT_MODE=0,0,OVERHEAD*I11*D_OPEX_F) -> 1522870.4 | J18: =IF(PROJECT_MODE=0,0,OVERHEAD*J11*D_OPEX_F) -> 1675157.5 | K18: =IF(PROJECT_MODE=0,0,OVERHEAD*K11*D_OPEX_F) -> 1842673.2 | L18: =IF(PROJECT_MODE=0,0,OVERHEAD*L11*D_OPEX_F) -> 2026940.6 | M18: =IF(PROJECT_MODE=0,0,OVERHEAD*M11*D_OPEX_F) -> 2229634.6 | N18: =IF(PROJECT_MODE=0,0,OVERHEAD*N11*D_OPEX_F) -> 2452598.1 | O18: =IF(PROJECT_MODE=0,0,OVERHEAD*O11*D_OPEX_F) -> 2697857.9 | P18: =IF(PROJECT_MODE=0,0,OVERHEAD*P11*D_OPEX_F) -> 2967643.7 | ... R18: =IF(PROJECT_MODE=0,0,OVERHEAD*R11*D_OPEX_F) -> 3590848.9
B19: Bad debts | C19: ETB | D19: =SUM(E19:R19) -> 8279661.6 | E19: =BAD_DEBT*'24_Revenue'!E55 -> 0 | F19: =BAD_DEBT*'24_Revenue'!F55 -> 0 | G19: =BAD_DEBT*'24_Revenue'!G55 -> 0 | H19: =BAD_DEBT*'24_Revenue'!H55 -> 0 | I19: =BAD_DEBT*'24_Revenue'!I55 -> 385757.3 | J19: =BAD_DEBT*'24_Revenue'!J55 -> 555490.51 | K19: =BAD_DEBT*'24_Revenue'!K55 -> 689919.22 | L19: =BAD_DEBT*'24_Revenue'!L55 -> 745112.76 | ... R19: =BAD_DEBT*'24_Revenue'!R55 -> 1182400.3
B20: TOTAL OPERATING COSTS | C20: ETB | D20: =SUM(E20:R20) -> 1.2478927e+08 | E20: =E12+E13+E14+E15+E16+E17+E18+E19 -> 1075351 | F20: =F12+F13+F14+F15+F16+F17+F18+F19 -> 1182886.1 | G20: =G12+G13+G14+G15+G16+G17+G18+G19 -> 1016141.4 | H20: =H12+H13+H14+H15+H16+H17+H18+H19 -> 0 | I20: =I12+I13+I14+I15+I16+I17+I18+I19 -> 7165829.8 | J20: =J12+J13+J14+J15+J16+J17+J18+J19 -> 8832413.5 | K20: =K12+K13+K14+K15+K16+K17+K18+K19 -> 9708988.2 | L20: =L12+L13+L14+L15+L16+L17+L18+L19 -> 10541903 | ... R20: =R12+R13+R14+R15+R16+R17+R18+R19 -> 17299501
B21: Opex base carrying input VAT | C21: ETB | D21: =SUM(E21:R21) -> 43746154 | E21: =OPEX_VAT_PCT*(E12+E13+E16+E17) -> 537675.51 | F21: =OPEX_VAT_PCT*(F12+F13+F16+F17) -> 591443.06 | G21: =OPEX_VAT_PCT*(G12+G13+G16+G17) -> 508070.72 | H21: =OPEX_VAT_PCT*(H12+H13+H16+H17) -> 0 | I21: =OPEX_VAT_PCT*(I12+I13+I16+I17) -> 2479685.2 | J21: =OPEX_VAT_PCT*(J12+J13+J16+J17) -> 3137075.3 | K21: =OPEX_VAT_PCT*(K12+K13+K16+K17) -> 3408009.7 | L21: =OPEX_VAT_PCT*(L12+L13+L16+L17) -> 3686717.9 | ... R21: =OPEX_VAT_PCT*(R12+R13+R16+R17) -> 5911989.9

Sheet 26_Assets
B1: 26 · Assets & depreciation (IAS 2 / 16 / 40) | R1: =HYPERLINK("#'00_Start'!A1","◂ Start") -> ◂ Start
B2: ንብረትና የእርጅና ቅናሽ
B3: =PROJ_NAME&" | Scenario: "&SCEN_NAME&" | Mode: "&MODE_NAME -> SAMPLE B — B+G+8 mixed-use building, Addis Ababa | Scenario: Base | Mode: 3 Mixed
B5: =IF(PROJECT_MODE=0,"Not needed for personal projects — switch mode to Commercial (1–3) on the Start sheet to see profitability. · ለግል ፕሮጀክት አያስፈልግም — ትርፋማነትን ለማየት በመጀመሪያ ገጽ ላይ ዓይነቱን ወደ ንግድ (1–3) ይቀይሩ።","")
B6: Period | D6: Total | E6: ='20_Timeline'!E12 -> C1 | F6: ='20_Timeline'!F12 -> C2 | G6: ='20_Timeline'!G12 -> C3 | H6: ='20_Timeline'!H12 -> C4 | I6: ='20_Timeline'!I12 -> O1 | J6: ='20_Timeline'!J12 -> O2 | K6: ='20_Timeline'!K12 -> O3 | L6: ='20_Timeline'!L12 -> O4 | ... R6: ='20_Timeline'!R12 -> O10
B7: Period end (Gregorian) | E7: ='20_Timeline'!E22 -> 46752 | F7: ='20_Timeline'!F22 -> 47118 | G7: ='20_Timeline'!G22 -> 47299 | H7: ='20_Timeline'!H22 -> 47299 | I7: ='20_Timeline'!I22 -> 47664 | J7: ='20_Timeline'!J22 -> 48029 | K7: ='20_Timeline'!K22 -> 48395 | L7: ='20_Timeline'!L22 -> 48760 | ... R7: ='20_Timeline'!R22 -> 50951
B8: Ethiopian calendar year | E8: ='20_Timeline'!E26 -> EC 2020 | F8: ='20_Timeline'!F26 -> EC 2021 | G8: ='20_Timeline'!G26 -> EC 2021 | H8: ='20_Timeline'!H26 -> EC 2021 | I8: ='20_Timeline'!I26 -> EC 2022 | J8: ='20_Timeline'!J26 -> EC 2023 | K8: ='20_Timeline'!K26 -> EC 2024 | L8: ='20_Timeline'!L26 -> EC 2025 | ... R8: ='20_Timeline'!R26 -> EC 2031
B10: Capex accrual and allocation | C10: የወጪ ድልድል
B11: Capex accrual (incl. capitalised finance) | C11: ETB | D11: =SUM(E11:R11) -> 5.5066043e+08 | E11: =SUMIFS('23_Construction'!$E$30:$AZ$30,'23_Construction'!$E$12:$AZ$12,'20_Timeline'!E11) -> 2.6740067e+08 | F11: =SUMIFS('23_Construction'!$E$30:$AZ$30,'23_Construction'!$E$12:$AZ$12,'20_Timeline'!F11) -> 2.4331061e+08 | G11: =SUMIFS('23_Construction'!$E$30:$AZ$30,'23_Construction'!$E$12:$AZ$12,'20_Timeline'!G11) -> 39949156 | H11: =SUMIFS('23_Construction'!$E$30:$AZ$30,'23_Construction'!$E$12:$AZ$12,'20_Timeline'!H11) -> 0 | I11: =SUMIFS('23_Construction'!$E$30:$AZ$30,'23_Construction'!$E$12:$AZ$12,'20_Timeline'!I11) -> 0 | J11: =SUMIFS('23_Construction'!$E$30:$AZ$30,'23_Construction'!$E$12:$AZ$12,'20_Timeline'!J11) -> 0 | K11: =SUMIFS('23_Construction'!$E$30:$AZ$30,'23_Construction'!$E$12:$AZ$12,'20_Timeline'!K11) -> 0 | L11: =SUMIFS('23_Construction'!$E$30:$AZ$30,'23_Construction'!$E$12:$AZ$12,'20_Timeline'!L11) -> 0 | ... R11: =SUMIFS('23_Construction'!$E$30:$AZ$30,'23_Construction'!$E$12:$AZ$12,'20_Timeline'!R11) -> 0
B12: of which IDC (non-cash) | C12: ETB | D12: =SUM(E12:R12) -> 17535682 | E12: =SUMIFS('23_Construction'!$E$29:$AZ$29,'23_Construction'!$E$12:$AZ$12,'20_Timeline'!E11) -> 0 | F12: =SUMIFS('23_Construction'!$E$29:$AZ$29,'23_Construction'!$E$12:$AZ$12,'20_Timeline'!F11) -> 7972174.2 | G12: =SUMIFS('23_Construction'!$E$29:$AZ$29,'23_Construction'!$E$12:$AZ$12,'20_Timeline'!G11) -> 9563507.7 | H12: =SUMIFS('23_Construction'!$E$29:$AZ$29,'23_Construction'!$E$12:$AZ$12,'20_Timeline'!H11) -> 0 | I12: =SUMIFS('23_Construction'!$E$29:$AZ$29,'23_Construction'!$E$12:$AZ$12,'20_Timeline'!I11) -> 0 | J12: =SUMIFS('23_Construction'!$E$29:$AZ$29,'23_Construction'!$E$12:$AZ$12,'20_Timeline'!J11) -> 0 | K12: =SUMIFS('23_Construction'!$E$29:$AZ$29,'23_Construction'!$E$12:$AZ$12,'20_Timeline'!K11) -> 0 | L12: =SUMIFS('23_Construction'!$E$29:$AZ$29,'23_Construction'!$E$12:$AZ$12,'20_Timeline'!L11) -> 0 | ... R12: =SUMIFS('23_Construction'!$E$29:$AZ$29,'23_Construction'!$E$12:$AZ$12,'20_Timeline'!R11) -> 0
B13: Cumulative capex | C13: ETB | D13: =R13 -> 5.5066043e+08 | E13: =0+E11 -> 2.6740067e+08 | F13: =E13+F11 -> 5.1071128e+08 | G13: =F13+G11 -> 5.5066043e+08 | H13: =G13+H11 -> 5.5066043e+08 | I13: =H13+I11 -> 5.5066043e+08 | J13: =I13+J11 -> 5.5066043e+08 | K13: =J13+K11 -> 5.5066043e+08 | L13: =K13+L11 -> 5.5066043e+08 | M13: =L13+M11 -> 5.5066043e+08 | ... R13: =Q13+R11 -> 5.5066043e+08
B14: Additions – inventory (IAS 2) | C14: ETB | D14: =SUM(E14:R14) -> 4.1438277e+08 | E14: =INV_SH*E11 -> 2.0122424e+08 | F14: =INV_SH*F11 -> 1.83096e+08 | G14: =INV_SH*G11 -> 30062523 | H14: =INV_SH*H11 -> 0 | I14: =INV_SH*I11 -> 0 | J14: =INV_SH*J11 -> 0 | K14: =INV_SH*K11 -> 0 | L14: =INV_SH*L11 -> 0 | ... R14: =INV_SH*R11 -> 0
B15: Additions – investment property (IAS 40) | C15: ETB | D15: =SUM(E15:R15) -> 1.3627767e+08 | E15: =IP_SH*E11 -> 66176425 | F15: =IP_SH*F11 -> 60214608 | G15: =IP_SH*G11 -> 9886633.2 | H15: =IP_SH*H11 -> 0 | I15: =IP_SH*I11 -> 0 | J15: =IP_SH*J11 -> 0 | K15: =IP_SH*K11 -> 0 | L15: =IP_SH*L11 -> 0 | ... R15: =IP_SH*R11 -> 0
B16: Additions – owner-occupied (IAS 16) | C16: ETB | D16: =SUM(E16:R16) -> 0 | E16: =PPE_SH*E11 -> 0 | F16: =PPE_SH*F11 -> 0 | G16: =PPE_SH*G11 -> 0 | H16: =PPE_SH*H11 -> 0 | I16: =PPE_SH*I11 -> 0 | J16: =PPE_SH*J11 -> 0 | K16: =PPE_SH*K11 -> 0 | L16: =PPE_SH*L11 -> 0 | ... R16: =PPE_SH*R11 -> 0
B17: Accounting depreciation – components, straight line from O1 | C17: የሂሳብ እርጅና ቅናሽ
B18: Structure | C18: ETB | D18: =SUM(E18:R18) -> 14192785 | E18: 0 | F18: 0 | G18: 0 | H18: 0 | I18: =MIN(BASE_STR/MAX(1,LIFE_BLD),BASE_STR-H19) -> 1419278.5 | J18: =MIN(BASE_STR/MAX(1,LIFE_BLD),BASE_STR-I19) -> 1419278.5 | K18: =MIN(BASE_STR/MAX(1,LIFE_BLD),BASE_STR-J19) -> 1419278.5 | L18: =MIN(BASE_STR/MAX(1,LIFE_BLD),BASE_STR-K19) -> 1419278.5 | M18: =MIN(BASE_STR/MAX(1,LIFE_BLD),BASE_STR-L19) -> 1419278.5 | N18: =MIN(BASE_STR/MAX(1,LIFE_BLD),BASE_STR-M19) -> 1419278.5 | O18: =MIN(BASE_STR/MAX(1,LIFE_BLD),BASE_STR-N19) -> 1419278.5 | P18: =MIN(BASE_STR/MAX(1,LIFE_BLD),BASE_STR-O19) -> 1419278.5 | ... R18: =MIN(BASE_STR/MAX(1,LIFE_BLD),BASE_STR-Q19) -> 1419278.5
B19: cumulative | C19: ETB | D19: =R19 -> 14192785 | E19: =0+E18 -> 0 | F19: =E19+F18 -> 0 | G19: =F19+G18 -> 0 | H19: =G19+H18 -> 0 | I19: =H19+I18 -> 1419278.5 | J19: =I19+J18 -> 2838557.1 | K19: =J19+K18 -> 4257835.6 | L19: =K19+L18 -> 5677114.2 | M19: =L19+M18 -> 7096392.7 | ... R19: =Q19+R18 -> 14192785
B20: Systems (MEP, lifts) | C20: ETB | D20: =SUM(E20:R20) -> 13353398 | E20: 0 | F20: 0 | G20: 0 | H20: 0 | I20: =MIN(BASE_SYS/MAX(1,LIFE_SYS),BASE_SYS-H21) -> 1335339.8 | J20: =MIN(BASE_SYS/MAX(1,LIFE_SYS),BASE_SYS-I21) -> 1335339.8 | K20: =MIN(BASE_SYS/MAX(1,LIFE_SYS),BASE_SYS-J21) -> 1335339.8 | L20: =MIN(BASE_SYS/MAX(1,LIFE_SYS),BASE_SYS-K21) -> 1335339.8 | M20: =MIN(BASE_SYS/MAX(1,LIFE_SYS),BASE_SYS-L21) -> 1335339.8 | N20: =MIN(BASE_SYS/MAX(1,LIFE_SYS),BASE_SYS-M21) -> 1335339.8 | O20: =MIN(BASE_SYS/MAX(1,LIFE_SYS),BASE_SYS-N21) -> 1335339.8 | P20: =MIN(BASE_SYS/MAX(1,LIFE_SYS),BASE_SYS-O21) -> 1335339.8 | ... R20: =MIN(BASE_SYS/MAX(1,LIFE_SYS),BASE_SYS-Q21) -> 1335339.8
B21: cumulative | C21: ETB | D21: =R21 -> 13353398 | E21: =0+E20 -> 0 | F21: =E21+F20 -> 0 | G21: =F21+G20 -> 0 | H21: =G21+H20 -> 0 | I21: =H21+I20 -> 1335339.8 | J21: =I21+J20 -> 2670679.5 | K21: =J21+K20 -> 4006019.3 | L21: =K21+L20 -> 5341359.1 | M21: =L21+M20 -> 6676698.9 | ... R21: =Q21+R20 -> 13353398
B22: FF&E (life capped) | C22: ETB | D22: =SUM(E22:R22) -> 1484882.4 | E22: 0 | F22: 0 | G22: 0 | H22: 0 | I22: =MIN(BASE_FFE/MAX(1,MIN(LIFE_FFE,FFE_LIFE_CAP)),BASE_FFE-H23) -> 212126.06 | J22: =MIN(BASE_FFE/MAX(1,MIN(LIFE_FFE,FFE_LIFE_CAP)),BASE_FFE-I23) -> 212126.06 | K22: =MIN(BASE_FFE/MAX(1,MIN(LIFE_FFE,FFE_LIFE_CAP)),BASE_FFE-J23) -> 212126.06 | L22: =MIN(BASE_FFE/MAX(1,MIN(LIFE_FFE,FFE_LIFE_CAP)),BASE_FFE-K23) -> 212126.06 | M22: =MIN(BASE_FFE/MAX(1,MIN(LIFE_FFE,FFE_LIFE_CAP)),BASE_FFE-L23) -> 212126.06 | N22: =MIN(BASE_FFE/MAX(1,MIN(LIFE_FFE,FFE_LIFE_CAP)),BASE_FFE-M23) -> 212126.06 | O22: =MIN(BASE_FFE/MAX(1,MIN(LIFE_FFE,FFE_LIFE_CAP)),BASE_FFE-N23) -> 212126.06 | P22: =MIN(BASE_FFE/MAX(1,MIN(LIFE_FFE,FFE_LIFE_CAP)),BASE_FFE-O23) -> 0 | ... R22: =MIN(BASE_FFE/MAX(1,MIN(LIFE_FFE,FFE_LIFE_CAP)),BASE_FFE-Q23) -> 0
B23: cumulative | C23: ETB | D23: =R23 -> 1484882.4 | E23: =0+E22 -> 0 | F23: =E23+F22 -> 0 | G23: =F23+G22 -> 0 | H23: =G23+H22 -> 0 | I23: =H23+I22 -> 212126.06 | J23: =I23+J22 -> 424252.12 | K23: =J23+K22 -> 636378.18 | L23: =K23+L22 -> 848504.24 | M23: =L23+M22 -> 1060630.3 | ... R23: =Q23+R22 -> 1484882.4
B24: Total depreciation | C24: ETB | D24: =SUM(E24:R24) -> 29031066 | E24: =E18+E20+E22 -> 0 | F24: =F18+F20+F22 -> 0 | G24: =G18+G20+G22 -> 0 | H24: =H18+H20+H22 -> 0 | I24: =I18+I20+I22 -> 2966744.4 | J24: =J18+J20+J22 -> 2966744.4 | K24: =K18+K20+K22 -> 2966744.4 | L24: =L18+L20+L22 -> 2966744.4 | ... R24: =R18+R20+R22 -> 2754618.3
B25: Cumulative depreciation | C25: ETB | D25: =R25 -> 29031066 | E25: =0+E24 -> 0 | F25: =E25+F24 -> 0 | G25: =F25+G24 -> 0 | H25: =G25+H24 -> 0 | I25: =H25+I24 -> 2966744.4 | J25: =I25+J24 -> 5933488.8 | K25: =J25+K24 -> 8900233.1 | L25: =K25+L24 -> 11866978 | M25: =L25+M24 -> 14833722 | ... R25: =Q25+R24 -> 29031066
B26: allocated to investment property | C26: ETB | D26: =SUM(E26:R26) -> 29031066 | E26: =IF(RET_SH>0,E24*IP_SH/RET_SH,0) -> 0 | F26: =IF(RET_SH>0,F24*IP_SH/RET_SH,0) -> 0 | G26: =IF(RET_SH>0,G24*IP_SH/RET_SH,0) -> 0 | H26: =IF(RET_SH>0,H24*IP_SH/RET_SH,0) -> 0 | I26: =IF(RET_SH>0,I24*IP_SH/RET_SH,0) -> 2966744.4 | J26: =IF(RET_SH>0,J24*IP_SH/RET_SH,0) -> 2966744.4 | K26: =IF(RET_SH>0,K24*IP_SH/RET_SH,0) -> 2966744.4 | L26: =IF(RET_SH>0,L24*IP_SH/RET_SH,0) -> 2966744.4 | ... R26: =IF(RET_SH>0,R24*IP_SH/RET_SH,0) -> 2754618.3
B27: allocated to owner-occupied PPE | C27: ETB | D27: =SUM(E27:R27) -> 0 | E27: =E24-E26 -> 0 | F27: =F24-F26 -> 0 | G27: =G24-G26 -> 0 | H27: =H24-H26 -> 0 | I27: =I24-I26 -> 0 | J27: =J24-J26 -> 0 | K27: =K24-K26 -> 0 | L27: =L24-L26 -> 0 | ... R27: =R24-R26 -> 0
B28: Carrying amounts | C28: የመዝገብ ዋጋ
B29: Investment property (cost model) | C29: ETB | D29: =R29 -> 1.072466e+08 | E29: =IP_SH*E13-0-E26 -> 66176425 | F29: =IP_SH*F13-E30-F26 -> 1.2639103e+08 | G29: =IP_SH*G13-F30-G26 -> 1.3627767e+08 | H29: =IP_SH*H13-G30-H26 -> 1.3627767e+08 | I29: =IP_SH*I13-H30-I26 -> 1.3331092e+08 | J29: =IP_SH*J13-I30-J26 -> 1.3034418e+08 | K29: =IP_SH*K13-J30-K26 -> 1.2737743e+08 | L29: =IP_SH*L13-K30-L26 -> 1.2441069e+08 | M29: =IP_SH*M13-L30-M26 -> 1.2144394e+08 | ... R29: =IP_SH*R13-Q30-R26 -> 1.072466e+08
B30: cumulative depreciation IP | C30: ETB | D30: =R30 -> 29031066 | E30: =0+E26 -> 0 | F30: =E30+F26 -> 0 | G30: =F30+G26 -> 0 | H30: =G30+H26 -> 0 | I30: =H30+I26 -> 2966744.4 | J30: =I30+J26 -> 5933488.8 | K30: =J30+K26 -> 8900233.1 | L30: =K30+L26 -> 11866978 | M30: =L30+M26 -> 14833722 | ... R30: =Q30+R26 -> 29031066
B31: Owner-occupied PPE | C31: ETB | D31: =R31 -> 0 | E31: =PPE_SH*E13-0-E27 -> 0 | F31: =PPE_SH*F13-E32-F27 -> 0 | G31: =PPE_SH*G13-F32-G27 -> 0 | H31: =PPE_SH*H13-G32-H27 -> 0 | I31: =PPE_SH*I13-H32-I27 -> 0 | J31: =PPE_SH*J13-I32-J27 -> 0 | K31: =PPE_SH*K13-J32-K27 -> 0 | L31: =PPE_SH*L13-K32-L27 -> 0 | M31: =PPE_SH*M13-L32-M27 -> 0 | ... R31: =PPE_SH*R13-Q32-R27 -> 0
B32: cumulative depreciation PPE | C32: ETB | D32: =R32 -> 0 | E32: =0+E27 -> 0 | F32: =E32+F27 -> 0 | G32: =F32+G27 -> 0 | H32: =G32+H27 -> 0 | I32: =H32+I27 -> 0 | J32: =I32+J27 -> 0 | K32: =J32+K27 -> 0 | L32: =K32+L27 -> 0 | M32: =L32+M27 -> 0 | ... R32: =Q32+R27 -> 0
B33: Inventory (IAS 2) | C33: ETB | D33: =R33 -> 0 | E33: =INV_SH*E13-0-'24_Revenue'!E42 -> 2.0122424e+08 | F33: =INV_SH*F13-E34-'24_Revenue'!F42 -> 3.8432024e+08 | G33: =INV_SH*G13-F34-'24_Revenue'!G42 -> 1.2431483e+08 | H33: =INV_SH*H13-G34-'24_Revenue'!H42 -> 1.2431483e+08 | I33: =INV_SH*I13-H34-'24_Revenue'!I42 -> 49725932 | J33: =INV_SH*J13-I34-'24_Revenue'!J42 -> 0 | K33: =INV_SH*K13-J34-'24_Revenue'!K42 -> 0 | L33: =INV_SH*L13-K34-'24_Revenue'!L42 -> 0 | M33: =INV_SH*M13-L34-'24_Revenue'!M42 -> 0 | ... R33: =INV_SH*R13-Q34-'24_Revenue'!R42 -> 0
B34: cumulative cost of sales | C34: ETB | D34: =R34 -> 4.1438277e+08 | E34: =0+'24_Revenue'!E42 -> 0 | F34: =E34+'24_Revenue'!F42 -> 0 | G34: =F34+'24_Revenue'!G42 -> 2.9006794e+08 | H34: =G34+'24_Revenue'!H42 -> 2.9006794e+08 | I34: =H34+'24_Revenue'!I42 -> 3.6465683e+08 | J34: =I34+'24_Revenue'!J42 -> 4.1438277e+08 | K34: =J34+'24_Revenue'!K42 -> 4.1438277e+08 | L34: =K34+'24_Revenue'!L42 -> 4.1438277e+08 | M34: =L34+'24_Revenue'!M42 -> 4.1438277e+08 | ... R34: =Q34+'24_Revenue'!R42 -> 4.1438277e+08
B35: Depreciable base (excl. land) | C35: ETB | D35: =R35 -> 99155605 | E35: =BASE_STR+BASE_SYS+BASE_FFE -> 99155605 | F35: =BASE_STR+BASE_SYS+BASE_FFE -> 99155605 | G35: =BASE_STR+BASE_SYS+BASE_FFE -> 99155605 | H35: =BASE_STR+BASE_SYS+BASE_FFE -> 99155605 | I35: =BASE_STR+BASE_SYS+BASE_FFE -> 99155605 | J35: =BASE_STR+BASE_SYS+BASE_FFE -> 99155605 | K35: =BASE_STR+BASE_SYS+BASE_FFE -> 99155605 | L35: =BASE_STR+BASE_SYS+BASE_FFE -> 99155605 | ... R35: =BASE_STR+BASE_SYS+BASE_FFE -> 99155605
B36: IAS 36 impairment test (value in use vs carrying amount) | C36: የንብረት ዋጋ መቀነስ ፈተና
B37: Value in use (PV of NOI + exit value) | C37: ETB | E37: 0 | F37: 0 | G37: 0 | H37: 0 | I37: =(J37+'24_Revenue'!J62)/(1+DISC_EFF) -> 2.9281068e+08 | J37: =(K37+'24_Revenue'!K62)/(1+DISC_EFF) -> 3.2101647e+08 | K37: =(L37+'24_Revenue'!L62)/(1+DISC_EFF) -> 3.4833916e+08 | L37: =(M37+'24_Revenue'!M62)/(1+DISC_EFF) -> 3.7814792e+08 | M37: =(N37+'24_Revenue'!N62)/(1+DISC_EFF) -> 4.1069619e+08 | N37: =(O37+'24_Revenue'!O62)/(1+DISC_EFF) -> 4.4626751e+08 | O37: =(P37+'24_Revenue'!P62)/(1+DISC_EFF) -> 4.8517976e+08 | P37: =(Q37+'24_Revenue'!Q62)/(1+DISC_EFF) -> 5.2779002e+08 | Q37: =(R37+'24_Revenue'!R62)/(1+DISC_EFF) -> 5.7450011e+08 | R37: =TV_GROSS -> 6.257632e+08
B38: Carrying amount (IP + PPE) | C38: ETB | E38: =E29+E31 -> 66176425 | F38: =F29+F31 -> 1.2639103e+08 | G38: =G29+G31 -> 1.3627767e+08 | H38: =H29+H31 -> 1.3627767e+08 | I38: =I29+I31 -> 1.3331092e+08 | J38: =J29+J31 -> 1.3034418e+08 | K38: =K29+K31 -> 1.2737743e+08 | L38: =L29+L31 -> 1.2441069e+08 | ... R38: =R29+R31 -> 1.072466e+08
B39: Headroom | C39: ETB | D39: =MIN(E39:R39) -> 0 | E39: 0 | F39: 0 | G39: 0 | H39: 0 | I39: =I37-I38 -> 1.5949976e+08 | J39: =J37-J38 -> 1.906723e+08 | K39: =K37-K38 -> 2.2096172e+08 | L39: =L37-L38 -> 2.5373723e+08 | M39: =M37-M38 -> 2.8925224e+08 | N39: =N37-N38 -> 3.2779031e+08 | O39: =O37-O38 -> 3.6966931e+08 | P39: =P37-P38 -> 4.1503418e+08 | ... R39: =R37-R38 -> 5.185166e+08
B40: Impairment indicator (1 = review) | C40: flag | D40: =SUM(E40:R40) -> 0 | E40: 0 | F40: 0 | G40: 0 | H40: 0 | I40: =IF(AND(I38>1,I39<0),1,0) -> 0 | J40: =IF(AND(J38>1,J39<0),1,0) -> 0 | K40: =IF(AND(K38>1,K39<0),1,0) -> 0 | L40: =IF(AND(L38>1,L39<0),1,0) -> 0 | M40: =IF(AND(M38>1,M39<0),1,0) -> 0 | N40: =IF(AND(N38>1,N39<0),1,0) -> 0 | O40: =IF(AND(O38>1,O39<0),1,0) -> 0 | P40: =IF(AND(P38>1,P39<0),1,0) -> 0 | ... R40: =IF(AND(R38>1,R39<0),1,0) -> 0

Sheet 27_Loan
B1: 27 · Loan – amortization schedule | R1: =HYPERLINK("#'00_Start'!A1","◂ Start") -> ◂ Start
B2: የብድር ክፍያ ሰንጠረዥ
B3: =PROJ_NAME&" | Scenario: "&SCEN_NAME&" | Mode: "&MODE_NAME -> SAMPLE B — B+G+8 mixed-use building, Addis Ababa | Scenario: Base | Mode: 3 Mixed
B6: Month | D6: Total | E6: ="M"&'20_Timeline'!E37 -> M1 | F6: ="M"&'20_Timeline'!F37 -> M2 | G6: ="M"&'20_Timeline'!G37 -> M3 | H6: ="M"&'20_Timeline'!H37 -> M4 | I6: ="M"&'20_Timeline'!I37 -> M5 | J6: ="M"&'20_Timeline'!J37 -> M6 | K6: ="M"&'20_Timeline'!K37 -> M7 | L6: ="M"&'20_Timeline'!L37 -> M8 | ... KF6: ="M"&'20_Timeline'!KF37 -> M288
B7: Month start | E7: ='20_Timeline'!E38 -> 46388 | F7: ='20_Timeline'!F38 -> 46419 | G7: ='20_Timeline'!G38 -> 46447 | H7: ='20_Timeline'!H38 -> 46478 | I7: ='20_Timeline'!I38 -> 46508 | J7: ='20_Timeline'!J38 -> 46539 | K7: ='20_Timeline'!K38 -> 46569 | L7: ='20_Timeline'!L38 -> 46600 | ... KF7: ='20_Timeline'!KF38 -> 55123
B8: Annual period | E8: =IF('20_Timeline'!E43=0,"–",INDEX('20_Timeline'!$E$12:$R$12,'20_Timeline'!E43)) -> C1 | F8: =IF('20_Timeline'!F43=0,"–",INDEX('20_Timeline'!$E$12:$R$12,'20_Timeline'!F43)) -> C1 | G8: =IF('20_Timeline'!G43=0,"–",INDEX('20_Timeline'!$E$12:$R$12,'20_Timeline'!G43)) -> C1 | H8: =IF('20_Timeline'!H43=0,"–",INDEX('20_Timeline'!$E$12:$R$12,'20_Timeline'!H43)) -> C1 | I8: =IF('20_Timeline'!I43=0,"–",INDEX('20_Timeline'!$E$12:$R$12,'20_Timeline'!I43)) -> C1 | J8: =IF('20_Timeline'!J43=0,"–",INDEX('20_Timeline'!$E$12:$R$12,'20_Timeline'!J43)) -> C1 | K8: =IF('20_Timeline'!K43=0,"–",INDEX('20_Timeline'!$E$12:$R$12,'20_Timeline'!K43)) -> C1 | L8: =IF('20_Timeline'!L43=0,"–",INDEX('20_Timeline'!$E$12:$R$12,'20_Timeline'!L43)) -> C1 | ... KF8: =IF('20_Timeline'!KF43=0,"–",INDEX('20_Timeline'!$E$12:$R$12,'20_Timeline'!KF43)) -> –
B10: Annual roll-up (C1–C4, O1–O10) | C10: ዓመታዊ ማጠቃለያ
B11: Period | E11: C1 | F11: C2 | G11: C3 | H11: C4 | I11: O1 | J11: O2 | K11: O3 | L11: O4 | M11: O5 | N11: O6 | O11: O7 | P11: O8 | Q11: O9 | R11: O10
B12: Drawdowns | C12: ETB | D12: =SUM(E12:R12) -> 1.1561421e+08 | E12: =SUMIFS($E$64:$KF$64,$E$57:$KF$57,'20_Timeline'!E11) -> 0 | F12: =SUMIFS($E$64:$KF$64,$E$57:$KF$57,'20_Timeline'!F11) -> 1.0379867e+08 | G12: =SUMIFS($E$64:$KF$64,$E$57:$KF$57,'20_Timeline'!G11) -> 11815538 | H12: =SUMIFS($E$64:$KF$64,$E$57:$KF$57,'20_Timeline'!H11) -> 0 | I12: =SUMIFS($E$64:$KF$64,$E$57:$KF$57,'20_Timeline'!I11) -> 0 | J12: =SUMIFS($E$64:$KF$64,$E$57:$KF$57,'20_Timeline'!J11) -> 0 | K12: =SUMIFS($E$64:$KF$64,$E$57:$KF$57,'20_Timeline'!K11) -> 0 | L12: =SUMIFS($E$64:$KF$64,$E$57:$KF$57,'20_Timeline'!L11) -> 0 | ... R12: =SUMIFS($E$64:$KF$64,$E$57:$KF$57,'20_Timeline'!R11) -> 0
B13: IDC capitalised (construction) | C13: ETB | D13: =SUM(E13:R13) -> 17535682 | E13: =SUMIFS($E$66:$KF$66,$E$57:$KF$57,'20_Timeline'!E11) -> 0 | F13: =SUMIFS($E$66:$KF$66,$E$57:$KF$57,'20_Timeline'!F11) -> 7972174.2 | G13: =SUMIFS($E$66:$KF$66,$E$57:$KF$57,'20_Timeline'!G11) -> 9563507.7 | H13: =SUMIFS($E$66:$KF$66,$E$57:$KF$57,'20_Timeline'!H11) -> 0 | I13: =SUMIFS($E$66:$KF$66,$E$57:$KF$57,'20_Timeline'!I11) -> 0 | J13: =SUMIFS($E$66:$KF$66,$E$57:$KF$57,'20_Timeline'!J11) -> 0 | K13: =SUMIFS($E$66:$KF$66,$E$57:$KF$57,'20_Timeline'!K11) -> 0 | L13: =SUMIFS($E$66:$KF$66,$E$57:$KF$57,'20_Timeline'!L11) -> 0 | ... R13: =SUMIFS($E$66:$KF$66,$E$57:$KF$57,'20_Timeline'!R11) -> 0
B14: Interest capitalised (grace) | C14: ETB | D14: =SUM(E14:R14) -> 0 | E14: =SUMIFS($E$67:$KF$67,$E$57:$KF$57,'20_Timeline'!E11) -> 0 | F14: =SUMIFS($E$67:$KF$67,$E$57:$KF$57,'20_Timeline'!F11) -> 0 | G14: =SUMIFS($E$67:$KF$67,$E$57:$KF$57,'20_Timeline'!G11) -> 0 | H14: =SUMIFS($E$67:$KF$67,$E$57:$KF$57,'20_Timeline'!H11) -> 0 | I14: =SUMIFS($E$67:$KF$67,$E$57:$KF$57,'20_Timeline'!I11) -> 0 | J14: =SUMIFS($E$67:$KF$67,$E$57:$KF$57,'20_Timeline'!J11) -> 0 | K14: =SUMIFS($E$67:$KF$67,$E$57:$KF$57,'20_Timeline'!K11) -> 0 | L14: =SUMIFS($E$67:$KF$67,$E$57:$KF$57,'20_Timeline'!L11) -> 0 | ... R14: =SUMIFS($E$67:$KF$67,$E$57:$KF$57,'20_Timeline'!R11) -> 0
B15: Interest paid | C15: ETB | D15: =SUM(E15:R15) -> 38971347 | E15: =SUMIFS($E$68:$KF$68,$E$57:$KF$57,'20_Timeline'!E11) -> 0 | F15: =SUMIFS($E$68:$KF$68,$E$57:$KF$57,'20_Timeline'!F11) -> 0 | G15: =SUMIFS($E$68:$KF$68,$E$57:$KF$57,'20_Timeline'!G11) -> 0 | H15: =SUMIFS($E$68:$KF$68,$E$57:$KF$57,'20_Timeline'!H11) -> 0 | I15: =SUMIFS($E$68:$KF$68,$E$57:$KF$57,'20_Timeline'!I11) -> 14569759 | J15: =SUMIFS($E$68:$KF$68,$E$57:$KF$57,'20_Timeline'!J11) -> 7991598.9 | K15: =SUMIFS($E$68:$KF$68,$E$57:$KF$57,'20_Timeline'!K11) -> 3268392.5 | L15: =SUMIFS($E$68:$KF$68,$E$57:$KF$57,'20_Timeline'!L11) -> 3018006.1 | ... R15: =SUMIFS($E$68:$KF$68,$E$57:$KF$57,'20_Timeline'!R11) -> 422402.14
B16: Interest expense (P&L) | C16: ETB | D16: =SUM(E16:R16) -> 38971347 | E16: =E15+E14 -> 0 | F16: =F15+F14 -> 0 | G16: =G15+G14 -> 0 | H16: =H15+H14 -> 0 | I16: =I15+I14 -> 14569759 | J16: =J15+J14 -> 7991598.9 | K16: =K15+K14 -> 3268392.5 | L16: =L15+L14 -> 3018006.1 | ... R16: =R15+R14 -> 422402.14
B17: Scheduled principal | C17: ETB | D17: =SUM(E17:R17) -> 25486969 | E17: =SUMIFS($E$72:$KF$72,$E$57:$KF$57,'20_Timeline'!E11) -> 0 | F17: =SUMIFS($E$72:$KF$72,$E$57:$KF$57,'20_Timeline'!F11) -> 0 | G17: =SUMIFS($E$72:$KF$72,$E$57:$KF$57,'20_Timeline'!G11) -> 0 | H17: =SUMIFS($E$72:$KF$72,$E$57:$KF$57,'20_Timeline'!H11) -> 0 | I17: =SUMIFS($E$72:$KF$72,$E$57:$KF$57,'20_Timeline'!I11) -> 0 | J17: =SUMIFS($E$72:$KF$72,$E$57:$KF$57,'20_Timeline'!J11) -> 3124000 | K17: =SUMIFS($E$72:$KF$72,$E$57:$KF$57,'20_Timeline'!K11) -> 1578227.2 | L17: =SUMIFS($E$72:$KF$72,$E$57:$KF$57,'20_Timeline'!L11) -> 1828613.6 | ... R17: =SUMIFS($E$72:$KF$72,$E$57:$KF$57,'20_Timeline'!R11) -> 4424217.6
B18: Cash sweep prepayment | C18: ETB | D18: =SUM(E18:R18) -> 1.0766292e+08 | E18: =SUMIFS($E$74:$KF$74,$E$57:$KF$57,'20_Timeline'!E11) -> 0 | F18: =SUMIFS($E$74:$KF$74,$E$57:$KF$57,'20_Timeline'!F11) -> 0 | G18: =SUMIFS($E$74:$KF$74,$E$57:$KF$57,'20_Timeline'!G11) -> 0 | H18: =SUMIFS($E$74:$KF$74,$E$57:$KF$57,'20_Timeline'!H11) -> 0 | I18: =SUMIFS($E$74:$KF$74,$E$57:$KF$57,'20_Timeline'!I11) -> 78736994 | J18: =SUMIFS($E$74:$KF$74,$E$57:$KF$57,'20_Timeline'!J11) -> 28925931 | K18: =SUMIFS($E$74:$KF$74,$E$57:$KF$57,'20_Timeline'!K11) -> 0 | L18: =SUMIFS($E$74:$KF$74,$E$57:$KF$57,'20_Timeline'!L11) -> 0 | ... R18: =SUMIFS($E$74:$KF$74,$E$57:$KF$57,'20_Timeline'!R11) -> 0
B19: Debt service (interest paid + scheduled principal) | C19: ETB | D19: =SUM(E19:R19) -> 64458316 | E19: =E15+E17 -> 0 | F19: =F15+F17 -> 0 | G19: =G15+G17 -> 0 | H19: =H15+H17 -> 0 | I19: =I15+I17 -> 14569759 | J19: =J15+J17 -> 11115599 | K19: =K15+K17 -> 4846619.8 | L19: =L15+L17 -> 4846619.8 | ... R19: =R15+R17 -> 4846619.8
B20: Closing loan balance | C20: ETB | D20: =R20 -> 0 | E20: =SUMIFS($E$75:$KF$75,$E$53:$KF$53,'20_Timeline'!E21) -> 0 | F20: =SUMIFS($E$75:$KF$75,$E$53:$KF$53,'20_Timeline'!F21) -> 1.1177085e+08 | G20: =SUMIFS($E$75:$KF$75,$E$53:$KF$53,'20_Timeline'!G21) -> 1.3314989e+08 | H20: =SUMIFS($E$75:$KF$75,$E$53:$KF$53,'20_Timeline'!H21) -> 1.3314989e+08 | I20: =SUMIFS($E$75:$KF$75,$E$53:$KF$53,'20_Timeline'!I21) -> 54412900 | J20: =SUMIFS($E$75:$KF$75,$E$53:$KF$53,'20_Timeline'!J21) -> 22362969 | K20: =SUMIFS($E$75:$KF$75,$E$53:$KF$53,'20_Timeline'!K21) -> 20784742 | L20: =SUMIFS($E$75:$KF$75,$E$53:$KF$53,'20_Timeline'!L21) -> 18956128 | ... R20: =SUMIFS($E$75:$KF$75,$E$53:$KF$53,'20_Timeline'!R21) -> 0
B21: Opening loan balance | C21: ETB | E21: 0 | F21: =E20 -> 0 | G21: =F20 -> 1.1177085e+08 | H21: =G20 -> 1.3314989e+08 | I21: =H20 -> 1.3314989e+08 | J21: =I20 -> 54412900 | K21: =J20 -> 22362969 | L21: =K20 -> 20784742 | M21: =L20 -> 18956128 | ... R21: =Q20 -> 4424217.6
B22: Land lease principal paid | C22: ETB | D22: =SUM(E22:R22) -> 54000000 | E22: =SUMIFS($E$84:$KF$84,$E$57:$KF$57,'20_Timeline'!E11) -> 0 | F22: =SUMIFS($E$84:$KF$84,$E$57:$KF$57,'20_Timeline'!F11) -> 4500000 | G22: =SUMIFS($E$84:$KF$84,$E$57:$KF$57,'20_Timeline'!G11) -> 4500000 | H22: =SUMIFS($E$84:$KF$84,$E$57:$KF$57,'20_Timeline'!H11) -> 0 | I22: =SUMIFS($E$84:$KF$84,$E$57:$KF$57,'20_Timeline'!I11) -> 4500000 | J22: =SUMIFS($E$84:$KF$84,$E$57:$KF$57,'20_Timeline'!J11) -> 4500000 | K22: =SUMIFS($E$84:$KF$84,$E$57:$KF$57,'20_Timeline'!K11) -> 4500000 | L22: =SUMIFS($E$84:$KF$84,$E$57:$KF$57,'20_Timeline'!L11) -> 4500000 | ... R22: =SUMIFS($E$84:$KF$84,$E$57:$KF$57,'20_Timeline'!R11) -> 4500000
B23: Land lease interest | C23: ETB | D23: =SUM(E23:R23) -> 92610000 | E23: =SUMIFS($E$85:$KF$85,$E$57:$KF$57,'20_Timeline'!E11) -> 0 | F23: =SUMIFS($E$85:$KF$85,$E$57:$KF$57,'20_Timeline'!F11) -> 9450000 | G23: =SUMIFS($E$85:$KF$85,$E$57:$KF$57,'20_Timeline'!G11) -> 9135000 | H23: =SUMIFS($E$85:$KF$85,$E$57:$KF$57,'20_Timeline'!H11) -> 0 | I23: =SUMIFS($E$85:$KF$85,$E$57:$KF$57,'20_Timeline'!I11) -> 8820000 | J23: =SUMIFS($E$85:$KF$85,$E$57:$KF$57,'20_Timeline'!J11) -> 8505000 | K23: =SUMIFS($E$85:$KF$85,$E$57:$KF$57,'20_Timeline'!K11) -> 8190000 | L23: =SUMIFS($E$85:$KF$85,$E$57:$KF$57,'20_Timeline'!L11) -> 7875000 | ... R23: =SUMIFS($E$85:$KF$85,$E$57:$KF$57,'20_Timeline'!R11) -> 5985000
B24: Lease liability recognised | C24: ETB | D24: =SUM(E24:R24) -> 135000000 | E24: =SUMIFS($E$81:$KF$81,$E$57:$KF$57,'20_Timeline'!E11) -> 135000000 | F24: =SUMIFS($E$81:$KF$81,$E$57:$KF$57,'20_Timeline'!F11) -> 0 | G24: =SUMIFS($E$81:$KF$81,$E$57:$KF$57,'20_Timeline'!G11) -> 0 | H24: =SUMIFS($E$81:$KF$81,$E$57:$KF$57,'20_Timeline'!H11) -> 0 | I24: =SUMIFS($E$81:$KF$81,$E$57:$KF$57,'20_Timeline'!I11) -> 0 | J24: =SUMIFS($E$81:$KF$81,$E$57:$KF$57,'20_Timeline'!J11) -> 0 | K24: =SUMIFS($E$81:$KF$81,$E$57:$KF$57,'20_Timeline'!K11) -> 0 | L24: =SUMIFS($E$81:$KF$81,$E$57:$KF$57,'20_Timeline'!L11) -> 0 | ... R24: =SUMIFS($E$81:$KF$81,$E$57:$KF$57,'20_Timeline'!R11) -> 0
B25: Closing lease liability | C25: ETB | D25: =R25 -> 81000000 | E25: =SUMIFS($E$86:$KF$86,$E$53:$KF$53,'20_Timeline'!E21) -> 135000000 | F25: =SUMIFS($E$86:$KF$86,$E$53:$KF$53,'20_Timeline'!F21) -> 130500000 | G25: =SUMIFS($E$86:$KF$86,$E$53:$KF$53,'20_Timeline'!G21) -> 126000000 | H25: =SUMIFS($E$86:$KF$86,$E$53:$KF$53,'20_Timeline'!H21) -> 126000000 | I25: =SUMIFS($E$86:$KF$86,$E$53:$KF$53,'20_Timeline'!I21) -> 121500000 | J25: =SUMIFS($E$86:$KF$86,$E$53:$KF$53,'20_Timeline'!J21) -> 117000000 | K25: =SUMIFS($E$86:$KF$86,$E$53:$KF$53,'20_Timeline'!K21) -> 112500000 | L25: =SUMIFS($E$86:$KF$86,$E$53:$KF$53,'20_Timeline'!L21) -> 108000000 | ... R25: =SUMIFS($E$86:$KF$86,$E$53:$KF$53,'20_Timeline'!R21) -> 81000000
B27: Loan scalars and lender summary | C27: የብድር ማጠቃለያ
B28: Months between repayments | C28: months | D28: =CHOOSE(FREQ,1,3,12) -> 3
B29: Tenor after completion | C29: months | D29: =TENOR_Y*12 -> 120
B30: Number of scheduled repayments | C30: no. | D30: =MAX(0,INT((TENOR_M-GRACE_M)/FREQ_M)) -> 36
B31: Annual lease instalment | C31: ETB | D31: =IF(LEASE_N>0,LAND_VALUE*(1-LEASE_DP)/LEASE_N,0)*IF(LAND_TYPE=1,1,0) -> 4500000
B32: Total drawdowns | C32: ETB | D32: =$D$64 -> 1.1561421e+08
B33: Total interest capitalised (IDC + grace) | C33: ETB | D33: =$D$66+$D$67 -> 17535682
B34: Total interest (all) | C34: ETB | D34: =$D$65 -> 56507029
B35: Total principal repaid (scheduled + sweep) | C35: ETB | D35: =$D$72+$D$74 -> 1.3314989e+08
B36: Peak debt (incl. capitalised interest) | C36: ETB | D36: =$D$75 -> 1.3314989e+08
B37: Balance at start of repayment | C37: ETB | D37: =$D$69 -> 54412900
B38: Average life after completion | C38: years | D38: =IF(LN_PRIN_TOT>0,$D$79/LN_PRIN_TOT,0) -> 1.9512519
B39: Final repayment month index | C39: no. | D39: =$D$77 -> 150
B40: Final repayment date | C40: date | D40: =IF(LN_TLAST>0,EDATE(START_DATE,LN_TLAST)-1,0) -> 50951
B41: First scheduled repayment month | C41: no. | D41: =IF($D$78=999,0,$D$78) -> 45
B42: Instalment at first scheduled repayment | C42: ETB | D42: =IF(LN_TFIRST>0,INDEX(E76:KF76,LN_TFIRST),0) -> 1418577.2
B43: Monthly-equivalent instalment | C43: ETB | D43: =LN_INSTAL/FREQ_M -> 472859.07
B44: Balance outstanding at end of tenor | C44: ETB | D44: =SUMIFS(E75:KF75,E55:KF55,MIN(TENOR_M,288-CONSTR_EFF)) -> 0
B45: Balance outstanding at end of O10 | C45: ETB | D45: =SUMIFS(E75:KF75,E55:KF55,12*OPS_YEARS) -> 0
B46: Min DSCR (from ratios) | C46: x | D46: ='43_Ratios'!$D$25 -> 1.7426163
B47: Average DSCR | C47: x | D47: ='43_Ratios'!$D$26 -> 4.3987313
B48: LLCR at completion | C48: x | D48: ='43_Ratios'!$D$28 -> 1.4612169
B49: Min interest cover (ICR) | C49: x | D49: ='43_Ratios'!$D$29 -> 1.6433148
B50: Max gearing | C50: % | D50: ='43_Ratios'!$D$30 -> 0.95335
B52: Timing and rate | C52: ጊዜና የወለድ መጠን
B53: Month t | C53: no. | E53: ='20_Timeline'!E37 -> 1 | F53: ='20_Timeline'!F37 -> 2 | G53: ='20_Timeline'!G37 -> 3 | H53: ='20_Timeline'!H37 -> 4 | I53: ='20_Timeline'!I37 -> 5 | J53: ='20_Timeline'!J37 -> 6 | K53: ='20_Timeline'!K37 -> 7 | L53: ='20_Timeline'!L37 -> 8 | ... KF53: ='20_Timeline'!KF37 -> 288
B54: Construction flag | C54: flag | D54: =SUM(E54:KF54) -> 30 | E54: ='20_Timeline'!E39 -> 1 | F54: ='20_Timeline'!F39 -> 1 | G54: ='20_Timeline'!G39 -> 1 | H54: ='20_Timeline'!H39 -> 1 | I54: ='20_Timeline'!I39 -> 1 | J54: ='20_Timeline'!J39 -> 1 | K54: ='20_Timeline'!K39 -> 1 | L54: ='20_Timeline'!L39 -> 1 | ... KF54: ='20_Timeline'!KF39 -> 0
B55: Months after completion k | C55: no. | E55: ='20_Timeline'!E40 -> -29 | F55: ='20_Timeline'!F40 -> -28 | G55: ='20_Timeline'!G40 -> -27 | H55: ='20_Timeline'!H40 -> -26 | I55: ='20_Timeline'!I40 -> -25 | J55: ='20_Timeline'!J40 -> -24 | K55: ='20_Timeline'!K40 -> -23 | L55: ='20_Timeline'!L40 -> -22 | ... KF55: ='20_Timeline'!KF40 -> 258
B56: Loan year after completion | C56: no. | E56: ='20_Timeline'!E42 -> 0 | F56: ='20_Timeline'!F42 -> 0 | G56: ='20_Timeline'!G42 -> 0 | H56: ='20_Timeline'!H42 -> 0 | I56: ='20_Timeline'!I42 -> 0 | J56: ='20_Timeline'!J42 -> 0 | K56: ='20_Timeline'!K42 -> 0 | L56: ='20_Timeline'!L42 -> 0 | ... KF56: ='20_Timeline'!KF42 -> 22
B57: Annual period index | C57: no. | E57: ='20_Timeline'!E43 -> 1 | F57: ='20_Timeline'!F43 -> 1 | G57: ='20_Timeline'!G43 -> 1 | H57: ='20_Timeline'!H43 -> 1 | I57: ='20_Timeline'!I43 -> 1 | J57: ='20_Timeline'!J43 -> 1 | K57: ='20_Timeline'!K43 -> 1 | L57: ='20_Timeline'!L43 -> 1 | ... KF57: ='20_Timeline'!KF43 -> 0
B58: Interest rate (p.a.) | C58: % | E58: =MAX(0,(IF(AND(RATE_TYPE=2,E56>0),INDEX(RATE_PATH,MIN(10,MAX(1,E56))),RATE)+D_RATE_ADD)*D_RATE_F) -> 0.15 | F58: =MAX(0,(IF(AND(RATE_TYPE=2,F56>0),INDEX(RATE_PATH,MIN(10,MAX(1,F56))),RATE)+D_RATE_ADD)*D_RATE_F) -> 0.15 | G58: =MAX(0,(IF(AND(RATE_TYPE=2,G56>0),INDEX(RATE_PATH,MIN(10,MAX(1,G56))),RATE)+D_RATE_ADD)*D_RATE_F) -> 0.15 | H58: =MAX(0,(IF(AND(RATE_TYPE=2,H56>0),INDEX(RATE_PATH,MIN(10,MAX(1,H56))),RATE)+D_RATE_ADD)*D_RATE_F) -> 0.15 | I58: =MAX(0,(IF(AND(RATE_TYPE=2,I56>0),INDEX(RATE_PATH,MIN(10,MAX(1,I56))),RATE)+D_RATE_ADD)*D_RATE_F) -> 0.15 | J58: =MAX(0,(IF(AND(RATE_TYPE=2,J56>0),INDEX(RATE_PATH,MIN(10,MAX(1,J56))),RATE)+D_RATE_ADD)*D_RATE_F) -> 0.15 | K58: =MAX(0,(IF(AND(RATE_TYPE=2,K56>0),INDEX(RATE_PATH,MIN(10,MAX(1,K56))),RATE)+D_RATE_ADD)*D_RATE_F) -> 0.15 | L58: =MAX(0,(IF(AND(RATE_TYPE=2,L56>0),INDEX(RATE_PATH,MIN(10,MAX(1,L56))),RATE)+D_RATE_ADD)*D_RATE_F) -> 0.15 | ... KF58: =MAX(0,(IF(AND(RATE_TYPE=2,KF56>0),INDEX(RATE_PATH,MIN(10,MAX(1,KF56))),RATE)+D_RATE_ADD)*D_RATE_F) -> 0.15
B59: Grace flag | C59: flag | D59: =SUM(E59:KF59) -> 12 | E59: =IF(AND(E55>=1,E55<=GRACE_M),1,0) -> 0 | F59: =IF(AND(F55>=1,F55<=GRACE_M),1,0) -> 0 | G59: =IF(AND(G55>=1,G55<=GRACE_M),1,0) -> 0 | H59: =IF(AND(H55>=1,H55<=GRACE_M),1,0) -> 0 | I59: =IF(AND(I55>=1,I55<=GRACE_M),1,0) -> 0 | J59: =IF(AND(J55>=1,J55<=GRACE_M),1,0) -> 0 | K59: =IF(AND(K55>=1,K55<=GRACE_M),1,0) -> 0 | L59: =IF(AND(L55>=1,L55<=GRACE_M),1,0) -> 0 | ... KF59: =IF(AND(KF55>=1,KF55<=GRACE_M),1,0) -> 0
B60: Repayment event flag | C60: flag | D60: =SUM(E60:KF60) -> 36 | E60: =IF(AND(E55>GRACE_M,E55<=GRACE_M+N_PAY*FREQ_M,MOD(E55-GRACE_M,FREQ_M)=0),1,0) -> 0 | F60: =IF(AND(F55>GRACE_M,F55<=GRACE_M+N_PAY*FREQ_M,MOD(F55-GRACE_M,FREQ_M)=0),1,0) -> 0 | G60: =IF(AND(G55>GRACE_M,G55<=GRACE_M+N_PAY*FREQ_M,MOD(G55-GRACE_M,FREQ_M)=0),1,0) -> 0 | H60: =IF(AND(H55>GRACE_M,H55<=GRACE_M+N_PAY*FREQ_M,MOD(H55-GRACE_M,FREQ_M)=0),1,0) -> 0 | I60: =IF(AND(I55>GRACE_M,I55<=GRACE_M+N_PAY*FREQ_M,MOD(I55-GRACE_M,FREQ_M)=0),1,0) -> 0 | J60: =IF(AND(J55>GRACE_M,J55<=GRACE_M+N_PAY*FREQ_M,MOD(J55-GRACE_M,FREQ_M)=0),1,0) -> 0 | K60: =IF(AND(K55>GRACE_M,K55<=GRACE_M+N_PAY*FREQ_M,MOD(K55-GRACE_M,FREQ_M)=0),1,0) -> 0 | L60: =IF(AND(L55>GRACE_M,L55<=GRACE_M+N_PAY*FREQ_M,MOD(L55-GRACE_M,FREQ_M)=0),1,0) -> 0 | ... KF60: =IF(AND(KF55>GRACE_M,KF55<=GRACE_M+N_PAY*FREQ_M,MOD(KF55-GRACE_M,FREQ_M)=0),1,0) -> 0
B61: Remaining payments incl. this one | C61: no. | E61: =IF(E60=1,N_PAY-(E55-GRACE_M)/FREQ_M+1,0) -> 0 | F61: =IF(F60=1,N_PAY-(F55-GRACE_M)/FREQ_M+1,0) -> 0 | G61: =IF(G60=1,N_PAY-(G55-GRACE_M)/FREQ_M+1,0) -> 0 | H61: =IF(H60=1,N_PAY-(H55-GRACE_M)/FREQ_M+1,0) -> 0 | I61: =IF(I60=1,N_PAY-(I55-GRACE_M)/FREQ_M+1,0) -> 0 | J61: =IF(J60=1,N_PAY-(J55-GRACE_M)/FREQ_M+1,0) -> 0 | K61: =IF(K60=1,N_PAY-(K55-GRACE_M)/FREQ_M+1,0) -> 0 | L61: =IF(L60=1,N_PAY-(L55-GRACE_M)/FREQ_M+1,0) -> 0 | ... KF61: =IF(KF60=1,N_PAY-(KF55-GRACE_M)/FREQ_M+1,0) -> 0
B62: Loan balance | C62: የብድር ቀሪ ሂሳብ
B63: Opening balance | C63: ETB | E63: =0 -> 0 | F63: =E75 -> 0 | G63: =F75 -> 0 | H63: =G75 -> 0 | I63: =H75 -> 0 | J63: =I75 -> 0 | K63: =J75 -> 0 | L63: =K75 -> 0 | M63: =L75 -> 0 | ... KF63: =KE75 -> 0
B64: Drawdowns | C64: ETB | D64: =SUM(E64:KF64) -> 1.1561421e+08 | E64: ='23_Construction'!E67 -> 0 | F64: ='23_Construction'!F67 -> 0 | G64: ='23_Construction'!G67 -> 0 | H64: ='23_Construction'!H67 -> 0 | I64: ='23_Construction'!I67 -> 0 | J64: ='23_Construction'!J67 -> 0 | K64: ='23_Construction'!K67 -> 0 | L64: ='23_Construction'!L67 -> 0 | ... AZ64: ='23_Construction'!AZ67 -> 0 | BA64: 0 | BB64: 0 | BC64: 0 | BD64: 0 | BE64: 0 | BF64: 0 | BG64: 0 | BH64: 0 | BI64: 0 | BJ64: 0 | BK64: 0 | BL64: 0 | BM64: 0 | BN64: 0 | BO64: 0 | BP64: 0 | BQ64: 0 | BR64: 0 | BS64: 0 | BT64: 0 | BU64: 0 | BV64: 0 | BW64: 0 | BX64: 0 | BY64: 0 | BZ64: 0 | CA64: 0 | CB64: 0 | CC64: 0 | CD64: 0 | CE64: 0 | CF64: 0 | CG64: 0 | CH64: 0 | CI64: 0 | CJ64: 0 | CK64: 0 | CL64: 0 | CM64: 0 | CN64: 0 | CO64: 0 | CP64: 0 | CQ64: 0 | CR64: 0 | CS64: 0 | CT64: 0 | CU64: 0 | CV64: 0 | CW64: 0 | CX64: 0 | CY64: 0 | CZ64: 0 | DA64: 0 | DB64: 0 | DC64: 0 | DD64: 0 | DE64: 0 | DF64: 0 | DG64: 0 | DH64: 0 | DI64: 0 | DJ64: 0 | DK64: 0 | DL64: 0 | DM64: 0 | DN64: 0 | DO64: 0 | DP64: 0 | DQ64: 0 | DR64: 0 | DS64: 0 | DT64: 0 | DU64: 0 | DV64: 0 | DW64: 0 | DX64: 0 | DY64: 0 | DZ64: 0 | EA64: 0 | EB64: 0 | EC64: 0 | ED64: 0 | EE64: 0 | EF64: 0 | EG64: 0 | EH64: 0 | EI64: 0 | EJ64: 0 | EK64: 0 | EL64: 0 | EM64: 0 | EN64: 0 | EO64: 0 | EP64: 0 | EQ64: 0 | ER64: 0 | ES64: 0 | ET64: 0 | EU64: 0 | EV64: 0 | EW64: 0 | EX64: 0 | EY64: 0 | EZ64: 0 | FA64: 0 | FB64: 0 | FC64: 0 | FD64: 0 | FE64: 0 | FF64: 0 | FG64: 0 | FH64: 0 | FI64: 0 | FJ64: 0 | FK64: 0 | FL64: 0 | FM64: 0 | FN64: 0 | FO64: 0 | FP64: 0 | FQ64: 0 | FR64: 0 | FS64: 0 | FT64: 0 | FU64: 0 | FV64: 0 | FW64: 0 | FX64: 0 | FY64: 0 | FZ64: 0 | GA64: 0 | GB64: 0 | GC64: 0 | GD64: 0 | GE64: 0 | GF64: 0 | GG64: 0 | GH64: 0 | GI64: 0 | GJ64: 0 | GK64: 0 | GL64: 0 | GM64: 0 | GN64: 0 | GO64: 0 | GP64: 0 | GQ64: 0 | GR64: 0 | GS64: 0 | GT64: 0 | GU64: 0 | GV64: 0 | GW64: 0 | GX64: 0 | GY64: 0 | GZ64: 0 | HA64: 0 | HB64: 0 | HC64: 0 | HD64: 0 | HE64: 0 | HF64: 0 | HG64: 0 | HH64: 0 | HI64: 0 | HJ64: 0 | HK64: 0 | HL64: 0 | HM64: 0 | HN64: 0 | HO64: 0 | HP64: 0 | HQ64: 0 | HR64: 0 | HS64: 0 | HT64: 0 | HU64: 0 | HV64: 0 | HW64: 0 | HX64: 0 | HY64: 0 | HZ64: 0 | IA64: 0 | IB64: 0 | IC64: 0 | ID64: 0 | IE64: 0 | IF64: 0 | IG64: 0 | IH64: 0 | II64: 0 | IJ64: 0 | IK64: 0 | IL64: 0 | IM64: 0 | IN64: 0 | IO64: 0 | IP64: 0 | IQ64: 0 | IR64: 0 | IS64: 0 | IT64: 0 | IU64: 0 | IV64: 0 | IW64: 0 | IX64: 0 | IY64: 0 | IZ64: 0 | JA64: 0 | JB64: 0 | JC64: 0 | JD64: 0 | JE64: 0 | JF64: 0 | JG64: 0 | JH64: 0 | JI64: 0 | JJ64: 0 | JK64: 0 | JL64: 0 | JM64: 0 | JN64: 0 | JO64: 0 | JP64: 0 | JQ64: 0 | JR64: 0 | JS64: 0 | JT64: 0 | JU64: 0 | JV64: 0 | JW64: 0 | JX64: 0 | JY64: 0 | JZ64: 0 | KA64: 0 | KB64: 0 | KC64: 0 | KD64: 0 | KE64: 0 | KF64: 0
B65: Interest accrued | C65: ETB | D65: =SUM(E65:KF65) -> 56507029 | E65: =(E63+E64)*E58/12 -> 0 | F65: =(F63+F64)*F58/12 -> 0 | G65: =(G63+G64)*G58/12 -> 0 | H65: =(H63+H64)*H58/12 -> 0 | I65: =(I63+I64)*I58/12 -> 0 | J65: =(J63+J64)*J58/12 -> 0 | K65: =(K63+K64)*K58/12 -> 0 | L65: =(L63+L64)*L58/12 -> 0 | ... KF65: =(KF63+KF64)*KF58/12 -> 0
B66: Interest capitalised – construction (IDC) | C66: ETB | D66: =SUM(E66:KF66) -> 17535682 | E66: =IF(E54=1,E65,0) -> 0 | F66: =IF(F54=1,F65,0) -> 0 | G66: =IF(G54=1,G65,0) -> 0 | H66: =IF(H54=1,H65,0) -> 0 | I66: =IF(I54=1,I65,0) -> 0 | J66: =IF(J54=1,J65,0) -> 0 | K66: =IF(K54=1,K65,0) -> 0 | L66: =IF(L54=1,L65,0) -> 0 | ... KF66: =IF(KF54=1,KF65,0) -> 0
B67: Interest capitalised – grace | C67: ETB | D67: =SUM(E67:KF67) -> 0 | E67: =IF(AND(E59=1,GRACE_TYPE=2),E65,0) -> 0 | F67: =IF(AND(F59=1,GRACE_TYPE=2),F65,0) -> 0 | G67: =IF(AND(G59=1,GRACE_TYPE=2),G65,0) -> 0 | H67: =IF(AND(H59=1,GRACE_TYPE=2),H65,0) -> 0 | I67: =IF(AND(I59=1,GRACE_TYPE=2),I65,0) -> 0 | J67: =IF(AND(J59=1,GRACE_TYPE=2),J65,0) -> 0 | K67: =IF(AND(K59=1,GRACE_TYPE=2),K65,0) -> 0 | L67: =IF(AND(L59=1,GRACE_TYPE=2),L65,0) -> 0 | ... KF67: =IF(AND(KF59=1,GRACE_TYPE=2),KF65,0) -> 0
B68: Interest paid in cash | C68: ETB | D68: =SUM(E68:KF68) -> 38971347 | E68: =E65-E66-E67 -> 0 | F68: =F65-F66-F67 -> 0 | G68: =G65-G66-G67 -> 0 | H68: =H65-H66-H67 -> 0 | I68: =I65-I66-I67 -> 0 | J68: =J65-J66-J67 -> 0 | K68: =K65-K66-K67 -> 0 | L68: =L65-L66-L67 -> 0 | ... KF68: =KF65-KF66-KF67 -> 0
B69: Balance at start of repayment | C69: ETB | D69: =MAX(E69:KF69) -> 54412900 | E69: =IF(E55=GRACE_M+1,E63,0) -> 0 | F69: =IF(F55=GRACE_M+1,F63,E69) -> 0 | G69: =IF(G55=GRACE_M+1,G63,F69) -> 0 | H69: =IF(H55=GRACE_M+1,H63,G69) -> 0 | I69: =IF(I55=GRACE_M+1,I63,H69) -> 0 | J69: =IF(J55=GRACE_M+1,J63,I69) -> 0 | K69: =IF(K55=GRACE_M+1,K63,J69) -> 0 | L69: =IF(L55=GRACE_M+1,L63,K69) -> 0 | M69: =IF(M55=GRACE_M+1,M63,L69) -> 0 | ... KF69: =IF(KF55=GRACE_M+1,KF63,KE69) -> 54412900
B70: Periodic rate | C70: % | E70: =E58*FREQ_M/12 -> 0.0375 | F70: =F58*FREQ_M/12 -> 0.0375 | G70: =G58*FREQ_M/12 -> 0.0375 | H70: =H58*FREQ_M/12 -> 0.0375 | I70: =I58*FREQ_M/12 -> 0.0375 | J70: =J58*FREQ_M/12 -> 0.0375 | K70: =K58*FREQ_M/12 -> 0.0375 | L70: =L58*FREQ_M/12 -> 0.0375 | ... KF70: =KF58*FREQ_M/12 -> 0.0375
B71: Balloon amount | C71: ETB | E71: =IF(REPAY_TYPE=3,BALLOON_PCT*E69,0) -> 0 | F71: =IF(REPAY_TYPE=3,BALLOON_PCT*F69,0) -> 0 | G71: =IF(REPAY_TYPE=3,BALLOON_PCT*G69,0) -> 0 | H71: =IF(REPAY_TYPE=3,BALLOON_PCT*H69,0) -> 0 | I71: =IF(REPAY_TYPE=3,BALLOON_PCT*I69,0) -> 0 | J71: =IF(REPAY_TYPE=3,BALLOON_PCT*J69,0) -> 0 | K71: =IF(REPAY_TYPE=3,BALLOON_PCT*K69,0) -> 0 | L71: =IF(REPAY_TYPE=3,BALLOON_PCT*L69,0) -> 0 | ... KF71: =IF(REPAY_TYPE=3,BALLOON_PCT*KF69,0) -> 0
B72: Scheduled principal | C72: ETB | D72: =SUM(E72:KF72) -> 25486969 | E72: =IF(E60=1,IF(E61<=1,E63+E67,MAX(0,MIN(E63+E67,IF(REPAY_TYPE=2,(E63-E71)/E61,PMT(E70,E61,-E63,E71)-E63*E70)))),0) -> 0 | F72: =IF(F60=1,IF(F61<=1,F63+F67,MAX(0,MIN(F63+F67,IF(REPAY_TYPE=2,(F63-F71)/F61,PMT(F70,F61,-F63,F71)-F63*F70)))),0) -> 0 | G72: =IF(G60=1,IF(G61<=1,G63+G67,MAX(0,MIN(G63+G67,IF(REPAY_TYPE=2,(G63-G71)/G61,PMT(G70,G61,-G63,G71)-G63*G70)))),0) -> 0 | H72: =IF(H60=1,IF(H61<=1,H63+H67,MAX(0,MIN(H63+H67,IF(REPAY_TYPE=2,(H63-H71)/H61,PMT(H70,H61,-H63,H71)-H63*H70)))),0) -> 0 | I72: =IF(I60=1,IF(I61<=1,I63+I67,MAX(0,MIN(I63+I67,IF(REPAY_TYPE=2,(I63-I71)/I61,PMT(I70,I61,-I63,I71)-I63*I70)))),0) -> 0 | J72: =IF(J60=1,IF(J61<=1,J63+J67,MAX(0,MIN(J63+J67,IF(REPAY_TYPE=2,(J63-J71)/J61,PMT(J70,J61,-J63,J71)-J63*J70)))),0) -> 0 | K72: =IF(K60=1,IF(K61<=1,K63+K67,MAX(0,MIN(K63+K67,IF(REPAY_TYPE=2,(K63-K71)/K61,PMT(K70,K61,-K63,K71)-K63*K70)))),0) -> 0 | L72: =IF(L60=1,IF(L61<=1,L63+L67,MAX(0,MIN(L63+L67,IF(REPAY_TYPE=2,(L63-L71)/L61,PMT(L70,L61,-L63,L71)-L63*L70)))),0) -> 0 | ... KF72: =IF(KF60=1,IF(KF61<=1,KF63+KF67,MAX(0,MIN(KF63+KF67,IF(REPAY_TYPE=2,(KF63-KF71)/KF61,PMT(KF70,KF61,-KF63,KF71)-KF63*KF70)))),0) -> 0
B73: Cash sweep base (sales proceeds) | C73: ETB | D73: =SUM(E73:KF73) -> 2.6915731e+08 | E73: =IF(E55=1,HAND_TOT,0)+IF(AND(E55>=12,MOD(E55,12)=0,E55<=12*OPS_YEARS),INDEX(SALES_COLL_OPS,MAX(1,MIN(10,E55/12))),0) -> 0 | F73: =IF(F55=1,HAND_TOT,0)+IF(AND(F55>=12,MOD(F55,12)=0,F55<=12*OPS_YEARS),INDEX(SALES_COLL_OPS,MAX(1,MIN(10,F55/12))),0) -> 0 | G73: =IF(G55=1,HAND_TOT,0)+IF(AND(G55>=12,MOD(G55,12)=0,G55<=12*OPS_YEARS),INDEX(SALES_COLL_OPS,MAX(1,MIN(10,G55/12))),0) -> 0 | H73: =IF(H55=1,HAND_TOT,0)+IF(AND(H55>=12,MOD(H55,12)=0,H55<=12*OPS_YEARS),INDEX(SALES_COLL_OPS,MAX(1,MIN(10,H55/12))),0) -> 0 | I73: =IF(I55=1,HAND_TOT,0)+IF(AND(I55>=12,MOD(I55,12)=0,I55<=12*OPS_YEARS),INDEX(SALES_COLL_OPS,MAX(1,MIN(10,I55/12))),0) -> 0 | J73: =IF(J55=1,HAND_TOT,0)+IF(AND(J55>=12,MOD(J55,12)=0,J55<=12*OPS_YEARS),INDEX(SALES_COLL_OPS,MAX(1,MIN(10,J55/12))),0) -> 0 | K73: =IF(K55=1,HAND_TOT,0)+IF(AND(K55>=12,MOD(K55,12)=0,K55<=12*OPS_YEARS),INDEX(SALES_COLL_OPS,MAX(1,MIN(10,K55/12))),0) -> 0 | L73: =IF(L55=1,HAND_TOT,0)+IF(AND(L55>=12,MOD(L55,12)=0,L55<=12*OPS_YEARS),INDEX(SALES_COLL_OPS,MAX(1,MIN(10,L55/12))),0) -> 0 | ... KF73: =IF(KF55=1,HAND_TOT,0)+IF(AND(KF55>=12,MOD(KF55,12)=0,KF55<=12*OPS_YEARS),INDEX(SALES_COLL_OPS,MAX(1,MIN(10,KF55/12))),0) -> 0
B74: Cash sweep prepayment | C74: ETB | D74: =SUM(E74:KF74) -> 1.0766292e+08 | E74: =MIN(MAX(0,E63+E64+E66+E67-E72),SWEEP*E73) -> 0 | F74: =MIN(MAX(0,F63+F64+F66+F67-F72),SWEEP*F73) -> 0 | G74: =MIN(MAX(0,G63+G64+G66+G67-G72),SWEEP*G73) -> 0 | H74: =MIN(MAX(0,H63+H64+H66+H67-H72),SWEEP*H73) -> 0 | I74: =MIN(MAX(0,I63+I64+I66+I67-I72),SWEEP*I73) -> 0 | J74: =MIN(MAX(0,J63+J64+J66+J67-J72),SWEEP*J73) -> 0 | K74: =MIN(MAX(0,K63+K64+K66+K67-K72),SWEEP*K73) -> 0 | L74: =MIN(MAX(0,L63+L64+L66+L67-L72),SWEEP*L73) -> 0 | ... KF74: =MIN(MAX(0,KF63+KF64+KF66+KF67-KF72),SWEEP*KF73) -> 0
B75: Closing balance | C75: ETB | D75: =MAX(E75:KF75) -> 1.3314989e+08 | E75: =E63+E64+E66+E67-E72-E74 -> 0 | F75: =F63+F64+F66+F67-F72-F74 -> 0 | G75: =G63+G64+G66+G67-G72-G74 -> 0 | H75: =H63+H64+H66+H67-H72-H74 -> 0 | I75: =I63+I64+I66+I67-I72-I74 -> 0 | J75: =J63+J64+J66+J67-J72-J74 -> 0 | K75: =K63+K64+K66+K67-K72-K74 -> 0 | L75: =L63+L64+L66+L67-L72-L74 -> 0 | ... KF75: =KF63+KF64+KF66+KF67-KF72-KF74 -> 0
B76: Scheduled debt service (interest paid + principal) | C76: ETB | D76: =SUM(E76:KF76) -> 64458316 | E76: =E68+E72 -> 0 | F76: =F68+F72 -> 0 | G76: =G68+G72 -> 0 | H76: =H68+H72 -> 0 | I76: =I68+I72 -> 0 | J76: =J68+J72 -> 0 | K76: =K68+K72 -> 0 | L76: =L68+L72 -> 0 | ... KF76: =KF68+KF72 -> 0
B77: Helper: month index if principal paid | C77: no. | D77: =MAX(E77:KF77) -> 150 | E77: =IF(E72+E74>0,E53,0) -> 0 | F77: =IF(F72+F74>0,F53,0) -> 0 | G77: =IF(G72+G74>0,G53,0) -> 0 | H77: =IF(H72+H74>0,H53,0) -> 0 | I77: =IF(I72+I74>0,I53,0) -> 0 | J77: =IF(J72+J74>0,J53,0) -> 0 | K77: =IF(K72+K74>0,K53,0) -> 0 | L77: =IF(L72+L74>0,L53,0) -> 0 | ... KF77: =IF(KF72+KF74>0,KF53,0) -> 0
B78: Helper: month index of scheduled payment (else 999) | C78: no. | D78: =MIN(E78:KF78) -> 45 | E78: =IF(E72>0,E53,999) -> 999 | F78: =IF(F72>0,F53,999) -> 999 | G78: =IF(G72>0,G53,999) -> 999 | H78: =IF(H72>0,H53,999) -> 999 | I78: =IF(I72>0,I53,999) -> 999 | J78: =IF(J72>0,J53,999) -> 999 | K78: =IF(K72>0,K53,999) -> 999 | L78: =IF(L72>0,L53,999) -> 999 | ... KF78: =IF(KF72>0,KF53,999) -> 999
B79: Helper: principal × years after completion | C79: ETB | D79: =SUM(E79:KF79) -> 2.5980898e+08 | E79: =(E72+E74)*MAX(0,E55)/12 -> 0 | F79: =(F72+F74)*MAX(0,F55)/12 -> 0 | G79: =(G72+G74)*MAX(0,G55)/12 -> 0 | H79: =(H72+H74)*MAX(0,H55)/12 -> 0 | I79: =(I72+I74)*MAX(0,I55)/12 -> 0 | J79: =(J72+J74)*MAX(0,J55)/12 -> 0 | K79: =(K72+K74)*MAX(0,K55)/12 -> 0 | L79: =(L72+L74)*MAX(0,L55)/12 -> 0 | ... KF79: =(KF72+KF74)*MAX(0,KF55)/12 -> 0
B80: Land lease liability | C80: የሊዝ ዕዳ
